Workbook

Sheet README_v7
A1: Genesis OS v7 Scoring Workbook
A3: Why v7 exists | B3: The prior engine was too linear and too compressed in the middle. In the 26x26 random simulation, Compatibility clustered in the 520-694 band while Chemistry sat unrealistically high for almost everyone. v7 restructures the scoring stack so behavior and stability are the gatekeepers, chemistry is support, and zodiac/numerology are overlays instead of co-captains.
A4: What changed | B4: 1) Added gated scoring (AlignmentWeighted × Gate) instead of pure linear averaging. 2) Lowered chemistry/cosmic influence. 3) Added answer-level proxy metrics for execution, repair, pacing, attachment risk, openness, accountability, reciprocity, and chemistry bias. 4) Added ML / Genesis OS label dictionary. 5) Added revised tier rules that separate strong, stable, and magnetic-but-risky.
A5: How to use this file | B5: Use AnswerBank_v7 for answer-level metrics and labels. Use Schema_v7 for exact weights, normalizations, and formulas. Use Engine_v7 for the pair-level formula blueprint. Use TierRules_v7 for final tier assignment. Existing v4/v5 sheets are preserved for traceability.
A6: Design principle | B6: Compatibility should not be lifted by chemistry, polarity, zodiac, or numerology if behavioral alignment and stability are weak. High scores should require both fit and hold.

Sheet Schema_v5
A1: Category | B1: Name | C1: Value | D1: Notes
A2: Normalization | B2: SCORE_WEIGHT_MIN | C2: 3 | D2: AnswerBank_v4 score_weight min
A3: Normalization | B3: SCORE_WEIGHT_MAX | C3: 10 | D3: AnswerBank_v4 score_weight max
A4: Normalization | B4: COMP_WEIGHT_MIN | C4: 4 | D4: AnswerBank_v4 compatibility_weight min
A5: Normalization | B5: COMP_WEIGHT_MAX | C5: 10 | D5: AnswerBank_v4 compatibility_weight max
A6: Normalization | B6: READINESS_MAX | C6: 10 | D6: readiness_points_v3 scale
A7: Normalization | B7: STANCE_MAX | C7: 10 | D7: compatibility_stance_v3 scale
A8: Normalization | B8: FORECAST_MAX | C8: 10 | D8: forecast_points_v3 scale
A9: Normalization | B9: PATTERN_RISK_MAX | C9: 1.8 | D9: pattern_risk max in AnswerBank
A10: Normalization | B10: CLUSTER_PENALTY_MAX_PER_ANSWER | C10: 14 | D10: cluster_penalty_points max per answer
A11: Normalization | B11: POL_MASC_MIN | C11: -0.4 | D11: polarity_masc_delta_v3 min
A12: Normalization | B12: POL_MASC_MAX | C12: 1.8 | D12: polarity_masc_delta_v3 max
A13: Normalization | B13: POL_FEM_MIN | C13: -1.6 | D13: polarity_fem_delta_v3 min
... A35: Bonuses/Penalties | B35: HARD_PENALTY_MAX | C35: 0.18 | D35: Normalized adjustment

Sheet MatchEngine_v5
A1: Metric | B1: Value | C1: Notes
A2: ArchetypeNorm | B2: =IFERROR(((0.5*VLOOKUP(FinalScores_v5!E4&"|"&FinalScores_v5!E6,ArchetypeLookup_v4!$A$2:$B$101,2,FALSE)+0.2*VLOOKUP(FinalScores_v5!E4&"|"&FinalScores_v5!E7,ArchetypeLookup_v4!$A$2:$B$101,2,FALSE)+0.2*VLOOKUP(FinalScores_v5!E5&"|"&FinalScores_v5!E6,ArchetypeLookup_v4!$A$2:$B$101,2,FALSE)+0.1*VLOOKUP(FinalScores_v5!E5&"|"&FinalScores_v5!E7,ArchetypeLookup_v4!$A$2:$B$101,2,FALSE))-2)/7,0.5) | C2: Archetype pairing normalized from 2–9 to 0–1
A3: CommNorm | B3: =IFERROR((VLOOKUP(FinalScores_v5!E16,CommLookup_v4!$A$2:$B$16,2,FALSE)-2)/7,0.5) | C3: Communication style (normalized)
A4: RegNorm | B4: =IFERROR((VLOOKUP(FinalScores_v5!E17,RegLookup_v4!$A$2:$B$11,2,FALSE)-3)/7,0.5) | C4: Regulation style (normalized)
A5: LoveNorm | B5: =IFERROR((VLOOKUP(FinalScores_v5!E18,LoveLookup_v4!$A$2:$B$16,2,FALSE)-5)/5,0.6) | C5: Love language fit proxy (normalized)
A6: Readiness_A | B6: =TestHarness_v4!B64 | C6: 0–100
A7: Readiness_B | B7: =TestHarness_v4!B65 | C7: 0–100
A8: ReadinessPairNorm | B8: =MAX(0,((B6+B7)/200) - 0.25*ABS(B6-B7)/100) | C8: Average minus mismatch penalty
A9: ForecastNormPair | B9: =IFERROR((SUMPRODUCT(TestHarness_v4!$B$10:$B$59,TestHarness_v4!$H$10:$H$59)+SUMPRODUCT(TestHarness_v4!$B$10:$B$59,TestHarness_v4!$L$10:$L$59))/(2*SUM(TestHarness_v4!$B$10:$B$59)*Schema_v5!$C$8),0.5) | C9: Weighted forecast points normalized
A10: ClusterPenaltyPairRaw | B10: =MIN(35,0.35*(FinalScores_v5!B5+FinalScores_v5!B6)) | C10: Same as v4 cap
A11: ClusterPenaltyNorm | B11: =MIN(1,B10/35) | C11: 0–1
A12: IntegrityPenaltyRaw | B12: =FinalScores_v5!E40 | C12: 0–80 current logic
A13: IntegrityPenaltyNorm | B13: =MIN(1,B12/80) | C13: 0–1
A14: ShadowRiskRaw | B14: =(TestHarness_v4!B83+TestHarness_v4!B84)/2 | C14: Average shadow intensity
A15: ShadowRiskNorm | B15: =MIN(1,MAX(0,B14/10)) | C15: Assumes 0–10 scale
A16: AttractionPatternNorm | B16: =0.5 | C16: Neutral until you build attraction-pattern model
A17: PolarityNorm | B17: =FinalScores_v5!E35 | C17: Current polarity placeholder (0–1)
A18: ZodiacNorm | B18: =FinalScores_v5!E31 | C18: From AstrologyLookup_v5 zodiac_norm
A19: NumerologyNorm | B19: =FinalScores_v5!E33 | C19: From NumerologyLookup_v5 adjusted_numerology_norm
A20: BehavioralCore | B20: =Schema_v5!$C$15*(Schema_v5!$C$19*B2+Schema_v5!$C$20*B3+Schema_v5!$C$21*B4+Schema_v5!$C$22*B5+Schema_v5!$C$23*B8) | C20: Includes BehavioralCore weight (0.52) * inner mix
A21: StabilityCore | B21: =Schema_v5!$C$16*(Schema_v5!$C$24*(1-B15)+Schema_v5!$C$25*(1-B13)+Schema_v5!$C$26*(1-B11)+Schema_v5!$C$27*B9) | C21: Includes Stability weight (0.23) * inner mix
A22: ChemistryCore | B22: =Schema_v5!$C$17*(Schema_v5!$C$28*B18+Schema_v5!$C$29*B17) | C22: Includes Chemistry weight (0.13) * inner mix
A23: CosmicCore | B23: =Schema_v5!$C$18*(Schema_v5!$C$30*B19+Schema_v5!$C$31*B20) | C23: Includes Cosmic weight (0.12) * inner mix
A24: InteractionBonus | B24: =0 | C24: Normalized -0.06..+0.06 (hook your InteractionRules)
A25: HardPenalty | B25: =0 | C25: Normalized 0..0.18 (severe contradiction / dangerous pair)
A26: RawMatch | B26: =MAX(0,MIN(1,B22+B23+B24+B25 + B26 - B27)) | C26: Clamped 0–1
A27: CompatibilityScore_350_850 | B27: =350+500*B28 | C27: Headline score
A28: StabilityScore_0_100 | B28: =100*(B23/Schema_v5!$C$16) | C28: Remove outer weight to show stability itself
A29: ChemistryScore_0_100 | B29: =100*(B24/Schema_v5!$C$17) | C29: Remove outer weight to show chemistry itself
A30: CosmicOverlayScore_0_100 | B30: =100*(B25/Schema_v5!$C$18) | C30: Remove outer weight to show cosmic overlay itself
A31: TierLabel | B31: =IF(AND(B29>=750,B30>=72,B31>=60),"Soul-aligned",IF(AND(B29>=670,B29<=749,B30>=58),"Strong potential",IF(AND(B29>=650,B31>=75,B30<58),"Magnetic but risky",IF(AND(B29>=560,B29<=669),"Possible but unstable",IF(OR(B29<560,B30<40),"Red flag zone","Unclassified"))))) | C31: Uses the tier logic you specified
A32: TierReasonPrimary | B32: ="Top driver: "&IF(B30<58,"Stability","Compatibility") | C32: Simple placeholder; refine later
A33: TierReasonSecondary | B33: ="Watch: "&IF(B15>0.5,"Shadow activation","Pace/needs mismatch") | C33: Simple placeholder; refine later

Sheet README_v4
A1: Genesis OS v4.1 — Deterministic Scoring Workbook (Full formulas, pre-user-data)
A3: Sheets:
A4: • TestHarness_v4 → enter answer_ids for two users (Q1–Q60). Computes readiness + BehaviorCore + penalties.
A5: • FinalScores_v4 → computes Compatibility 350–850 and Forecast 0–100 using all matrices + the v4 deterministic formula.
A7: Rule: Q1–Q50 count toward readiness/behavior. Q51–Q60 are shadow/integrity only.

Sheet AnswerBank_v4
A1: answer_id | B1: canonical_q | C1: question_number_int | D1: phase | E1: question_weight_v3 | F1: dimension_primary | G1: dimension_secondary | H1: question_text | I1: answer_option_id | J1: answer_letter | K1: answer_text | L1: score_weight | M1: compatibility_weight | N1: readiness_points_v3 | O1: compatibility_stance_v3 | P1: forecast_points_v3 | Q1: archetype | R1: archetype_id | S1: shadow_type | T1: shadow_type_id | U1: shadow_risk_points_v3 | V1: polarity_tag | W1: polarity_masc_delta_v3 | X1: polarity_fem_delta_v3 | Y1: comm_style | Z1: regulation_style | AA1: love_language | AB1: cluster_tags | AC1: cluster_1 | AD1: cluster_2 | AE1: cluster_penalty_points | AF1: pattern_tag | AG1: match_behavior_tag | AH1: pattern_risk | AI1: consistency_flag | AJ1: integrity_flag_v3 | AK1: drift_relevance | AL1: forecast_relevance | AM1: energy_type_tag | AN1: emotion_family | AO1: emotion_cell | AP1: version_snapshot
A2: Q01_A | B2: 1 | C2: 1 | D2: Core | E2: 1 | F2: CommunicationHealth | G2: EmotionalNeeds | H2: When something feels off between you and someone you're dating, what usually happens next-internally or outwardly? | I2: A | J2: A | K2: It's probably nothing. I just shift into neutral and let it play out. If they bring it up, cool. If not, I'm not pushing it. | L2: 3 | M2: 4 | N2: 0 | O2: 0 | P2: 0 | Q2: Icebox | R2: 1 | U2: 0 | V2: masc:1.8;fem:-1.6 | W2: 1.8 | X2: -1.6 | Y2: COMM_Avoidant | Z2: REG_Suppressor | AA2: LANG_Time | AB2: Vulnerability_Loop , Pursuer_Distancer | AC2: Vulnerability_Loop | AD2: Pursuer_Distancer | AE2: 11 | AF2: emotional disengage | AG2: passive drifter | AH2: 0 | AI2: yes | AJ2: no | AK2: yes | AL2: yes | AP2: v3_2026-03-19
A3: Q01_B | B3: 1 | C3: 1 | D3: Core | E3: 1 | F3: CommunicationHealth | G3: EmotionalNeeds | I3: B | J3: B | K3: I start rereading everything. The tone in a text. A pause that felt a little too long. I like turning it into a puzzle to solve. | L3: 6 | M3: 7 | N3: 4 | O3: 6 | P3: 4 | Q3: Analyzer | R3: 2 | U3: 0 | V3: masc:1.4;fem:0.1 | W3: 1.4 | X3: 0.1 | Y3: COMM_Logical | Z3: REG_SelfSoother | AA3: LANG_Service | AB3: Trust_Tension | AC3: Trust_Tension | AE3: 6 | AF3: overanalysis | AG3: hyper-vigilant decoder | AH3: 0 | AI3: yes | AJ3: no | AK3: yes | AL3: yes | AP3: v3_2026-03-19
A4: Q01_C | B4: 1 | C4: 1 | D4: Core | E4: 1 | F4: CommunicationHealth | G4: EmotionalNeeds | I4: C | J4: C | K4: I'll bring something up, but I usually wrap it in a joke or a side comment. I'd rather ease into it than make it feel too serious. | L4: 7 | M4: 8 | N4: 6 | O4: 8 | P4: 8 | Q4: Translator | R4: 3 | U4: 0 | V4: masc:-0.1;fem:1.6 | W4: -0.1 | X4: 1.6 | Y4: COMM_Indirect | Z4: REG_CoRegulator | AA4: LANG_Words | AE4: 0 | AF4: soft entry communication | AG4: light approach | AH4: 0 | AI4: no | AJ4: no | AK4: yes | AL4: yes | AP4: v3_2026-03-19
A5: Q01_D | B5: 1 | C5: 1 | D5: Core | E5: 1 | F5: CommunicationHealth | G5: EmotionalNeeds | I5: D | J5: D | K5: I usually wait. Not to avoid it, just to feel it out first. I've learned not everything needs a reaction, but if it lingers, I'll say something. | L5: 8 | M5: 8 | N5: 8 | O5: 8 | P5: 6 | Q5: Survivor | R5: 8 | U5: 0 | V5: masc:0.3;fem:1.3 | W5: 0.3 | X5: 1.3 | Y5: COMM_Emotional | Z5: REG_SelfSoother | AA5: LANG_Service | AE5: 0 | AF5: measured patience | AG5: cautious feeler | AH5: 0.6 | AI5: no | AJ5: no | AK5: yes | AL5: yes | AP5: v3_2026-03-19
A6: Q01_E | B6: 1 | C6: 1 | D6: Core | E6: 1 | F6: CommunicationHealth | G6: EmotionalNeeds | I6: E | J6: E | K6: I don't do weird energy. I'm not unkind, but I also don't pretend. If something's off, I'm not sitting in it quietly. | L6: 9 | M6: 9 | N6: 10 | O6: 10 | P6: 10 | Q6: Regulated Grown-Up | R6: 9 | U6: 0 | V6: masc:1.1;fem:0.9 | W6: 1.1 | X6: 0.9 | Y6: COMM_Direct | Z6: REG_CoRegulator | AA6: LANG_Words | AE6: 0 | AF6: direct boundary setting | AG6: clear communicator | AH6: 0 | AI6: no | AJ6: no | AK6: yes | AL6: yes | AP6: v3_2026-03-19
A7: Q02_A | B7: 2 | C7: 2 | D7: Core | E7: 1 | F7: CommunicationHealth | G7: EmotionalNeeds | H7: You bring up something that bothered you. They brush it off or make a joke. What's your honest reaction? | I7: A | J7: A | K7: Not surprised. I usually go quieter after that. I've seen this play out before, no point chasing clarity where it's not offered. | L7: 5 | M7: 6 | N7: 0 | O7: 0 | P7: 0 | Q7: Quiet Exit | R7: 4 | U7: 0 | V7: masc:1.4;fem:-1.3 | W7: 1.4 | X7: -1.3 | Y7: COMM_Avoidant | Z7: REG_Suppressor | AA7: LANG_Time | AB7: Vulnerability_Loop , Pursuer_Distancer | AC7: Vulnerability_Loop | AD7: Pursuer_Distancer | AE7: 11 | AF7: withdrawal after dismissal | AG7: silent step-back | AH7: 0.8 | AI7: yes | AJ7: no | AK7: yes | AL7: yes | AP7: v3_2026-03-19
A8: Q02_B | B8: 2 | C8: 2 | D8: Core | E8: 1 | F8: CommunicationHealth | G8: EmotionalNeeds | I8: B | J8: B | K8: I'll play along, but it definitely changes how I see them. I keep score, even if they never know it. | L8: 4 | M8: 5 | N8: 0 | O8: 0 | P8: 0 | Q8: Performer | R8: 7 | U8: 0 | V8: masc:0.3;fem:0.5 | W8: 0.3 | X8: 0.5 | Y8: COMM_Indirect | Z8: REG_Distractor | AA8: LANG_Gifts | AB8: Control_Avoidance , Scorekeeping_Echo | AC8: Control_Avoidance | AD8: Scorekeeping_Echo | AE8: 14 | AF8: private resentment | AG8: image-based keeper | AH8: 1.2 | AI8: yes | AJ8: no | AK8: yes | AL8: yes | AP8: v3_2026-03-19
A9: Q02_C | B9: 2 | C9: 2 | D9: Core | E9: 1 | F9: CommunicationHealth | G9: EmotionalNeeds | I9: C | J9: C | K9: I bring it up again, but this time they can probably hear the shift in my tone. I'm not trying to argue, I just need them to actually hear me. | L9: 8 | M9: 8 | N9: 8 | O9: 8 | P9: 8 | Q9: Fixer | R9: 5 | U9: 0 | V9: masc:-0.4;fem:2.0 | W9: -0.4 | X9: 2 | Y9: COMM_Emotional | Z9: REG_CoRegulator | AA9: LANG_Service | AE9: 0 | AF9: persistence for resolution | AG9: consistent communicator | AH9: 0 | AI9: no | AJ9: no | AK9: yes | AL9: yes | AP9: v3_2026-03-19
A10: Q02_D | B10: 2 | C10: 2 | D10: Core | E10: 1 | F10: CommunicationHealth | G10: EmotionalNeeds | I10: D | J10: D | K10: I laugh too, but it sticks with me. Hours later I'm still replaying what I said, wondering if I should've just kept quiet. | L10: 5 | M10: 6 | N10: 2 | O10: 4 | P10: 2 | Q10: Phantom Seeker | R10: 10 | U10: 0 | V10: masc:-0.2;fem:1.5 | W10: -0.2 | X10: 1.5 | Y10: COMM_Emotional | Z10: REG_SelfSoother | AA10: LANG_Touch | AB10: Conflict_Flip | AC10: Conflict_Flip | AE10: 4 | AF10: quiet rumination | AG10: soft stewer | AH10: 0 | AI10: yes | AJ10: no | AK10: yes | AL10: yes | AP10: v3_2026-03-19
A11: Q02_E | B11: 2 | C11: 2 | D11: Core | E11: 1 | F11: CommunicationHealth | G11: EmotionalNeeds | I11: E | J11: E | K11: I clock that fast. If I opened up and they shrugged it off, I don't ask again. I don't mind being the bad guy if it means protecting my peace. | L11: 9 | M11: 9 | N11: 10 | O11: 10 | P11: 10 | Q11: Regulated Grown-Up | R11: 9 | U11: 0 | V11: masc:1.1;fem:0.9 | W11: 1.1 | X11: 0.9 | Y11: COMM_Direct | Z11: REG_CoRegulator | AA11: LANG_Words | AE11: 0 | AF11: fast boundary recognition | AG11: peace protector | AH11: 0 | AI11: no | AJ11: no | AK11: yes | AL11: yes | AP11: v3_2026-03-19
A12: Q03_A | B12: 3 | C12: 3 | D12: Core | E12: 1 | F12: CommunicationHealth | G12: EmotionalNeeds | H12: You start catching feelings and realizing you actually like this person. How does your energy shift? | I12: A | J12: A | K12: I pull back a little. Not to play games, I just need space to check if I'm seeing it clearly before I lean in. | L12: 6 | M12: 7 | N12: 2 | O12: 2 | P12: 0 | Q12: Icebox | R12: 1 | U12: 0 | V12: masc:1.8;fem:-1.6 | W12: 1.8 | X12: -1.6 | Y12: COMM_Avoidant | Z12: REG_Suppressor | AA12: LANG_Time | AE12: 0 | AF12: cautious distance | AG12: safety checker | AH12: 0.5 | AI12: no | AJ12: no | AK12: yes | AL12: yes | AP12: v3_2026-03-19
A13: Q03_B | B13: 3 | C13: 3 | D13: Core | E13: 1 | F13: CommunicationHealth | G13: EmotionalNeeds | I13: B | J13: B | K13: I start imagining what it could be. I try not to get ahead of myself, I just like feeling what it can be. | L13: 7 | M13: 8 | N13: 4 | O13: 6 | P13: 4 | Q13: Romantic Idealist | R13: 6 | U13: 0 | V13: masc:-0.4;fem:1.5 | W13: -0.4 | X13: 1.5 | Y13: COMM_Emotional | Z13: REG_Distractor | AA13: LANG_Gifts | AB13: Humor_Shield , Affection_Mismatch | AC13: Humor_Shield | AD13: Affection_Mismatch | AE13: 7 | AF13: guarded playfulness | AG13: safe tester | AH13: 0.2 | AI13: yes | AJ13: no | AK13: yes | AL13: yes | AP13: v3_2026-03-19
A14: Q03_C | B14: 3 | C14: 3 | D14: Core | E14: 1 | F14: CommunicationHealth | G14: EmotionalNeeds | I14: C | J14: C | K14: I don't say much, but I start showing up more, checking in, remembering little things. That's usually how I start showing my interest. | L14: 8 | M14: 9 | N14: 8 | O14: 8 | P14: 8 | Q14: Analyzer | R14: 2 | U14: 0 | V14: masc:1.4;fem:0.1 | W14: 1.4 | X14: 0.1 | Y14: COMM_Logical | Z14: REG_SelfSoother | AA14: LANG_Service | AE14: 0 | AF14: steady investment | AG14: quiet prover | AH14: 0 | AI14: no | AJ14: no | AK14: yes | AL14: yes | AP14: v3_2026-03-19
A15: Q03_D | B15: 3 | C15: 3 | D15: Core | E15: 1 | F15: CommunicationHealth | G15: EmotionalNeeds | I15: D | J15: D | K15: I want them to like me back, but I need to know it's safe first. So I keep it light while I wait on their actions. | L15: 6 | M15: 6 | N15: 4 | O15: 2 | P15: 2 | Q15: Phantom Seeker | R15: 10 | U15: 0 | V15: masc:-0.2;fem:1.5 | W15: -0.2 | X15: 1.5 | Y15: COMM_Emotional | Z15: REG_SelfSoother | AA15: LANG_Touch | AB15: Humor_Shield , Affection_Mismatch | AC15: Humor_Shield | AD15: Affection_Mismatch | AE15: 7 | AF15: guarded playfulness | AG15: safe tester | AH15: 0 | AI15: yes | AJ15: no | AK15: yes | AL15: yes | AP15: v3_2026-03-19
A16: Q03_E | B16: 3 | C16: 3 | D16: Core | E16: 1 | F16: CommunicationHealth | G16: EmotionalNeeds | I16: E | J16: E | K16: If I like someone, yeah, it shows. But I've learned not to lean too far until I know they're showing up too. I'm not trying to guess where I stand. | L16: 9 | M16: 9 | N16: 10 | O16: 10 | P16: 10 | Q16: Regulated Grown-Up | R16: 9 | U16: 0 | V16: masc:1.1;fem:0.9 | W16: 1.1 | X16: 0.9 | Y16: COMM_Direct | Z16: REG_CoRegulator | AA16: LANG_Words | AE16: 0 | AF16: balanced openness | AG16: readiness matcher | AH16: 0.2 | AI16: no | AJ16: no | AK16: yes | AL16: yes | AP16: v3_2026-03-19
A17: Q04_A | B17: 4 | C17: 4 | D17: Core | E17: 1 | F17: CommunicationHealth | G17: EmotionalNeeds | H17: You're starting to notice some red flags. Nothing explosive, just little things that don't sit right. What do you do with that feeling? | I17: A | J17: A | K17: I keep watching. I've learned not to bring things up too early. People need time to reveal themselves. | L17: 7 | M17: 8 | N17: 6 | O17: 6 | P17: 6 | Q17: Analyzer | R17: 2 | U17: 0 | V17: masc:1.4;fem:0.1 | W17: 1.4 | X17: 0.1 | Y17: COMM_Logical | Z17: REG_SelfSoother | AA17: LANG_Service | AE17: 0 | AF17: silent observation | AG17: patient tracker | AH17: 1.2 | AI17: no | AJ17: no | AK17: yes | AL17: yes | AP17: v3_2026-03-19
A18: Q04_B | B18: 4 | C18: 4 | D18: Core | E18: 1 | F18: CommunicationHealth | G18: EmotionalNeeds | I18: B | J18: B | K18: I ignore it at first. I don't want to ruin a good thing by overthinking. Sometimes I just want it to stay good for a little while. | L18: 5 | M18: 6 | N18: 2 | O18: 2 | P18: 0 | Q18: Romantic Idealist | R18: 6 | U18: 0 | V18: masc:-0.4;fem:1.5 | W18: -0.4 | X18: 1.5 | Y18: COMM_Emotional | Z18: REG_Distractor | AA18: LANG_Gifts | AB18: Commitment_Ambiguity | AC18: Commitment_Ambiguity | AE18: 5 | AF18: optimism over caution | AG18: avoidant hope | AH18: 0.6 | AI18: yes | AJ18: no | AK18: yes | AL18: yes | AP18: v3_2026-03-19
A19: Q04_C | B19: 4 | C19: 4 | D19: Core | E19: 1 | F19: CommunicationHealth | G19: EmotionalNeeds | I19: C | J19: C | K19: I call it out. I just say what I see. I'd rather know now than waste time. | L19: 10 | M19: 10 | N19: 10 | O19: 10 | P19: 10 | Q19: Regulated Grown-Up | R19: 9 | U19: 0 | V19: masc:1.1;fem:0.9 | W19: 1.1 | X19: 0.9 | Y19: COMM_Direct | Z19: REG_CoRegulator | AA19: LANG_Words | AE19: 0 | AF19: early clarity | AG19: straight talker | AH19: 0 | AI19: no | AJ19: no | AK19: yes | AL19: yes | AP19: v3_2026-03-19
A20: Q04_D | B20: 4 | C20: 4 | D20: Core | E20: 1 | F20: CommunicationHealth | G20: EmotionalNeeds | I20: D | J20: D | K20: I tell myself I'm just being too picky or expecting too much. So I wait. I just stop texting first and start holding back. | L20: 4 | M20: 5 | N20: 0 | O20: 2 | P20: 0 | Q20: Phantom Seeker | R20: 10 | U20: 0 | V20: masc:-0.2;fem:1.5 | W20: -0.2 | X20: 1.5 | Y20: COMM_Emotional | Z20: REG_SelfSoother | AA20: LANG_Touch | AB20: Commitment_Ambiguity | AC20: Commitment_Ambiguity | AE20: 5 | AF20: self-doubt delay | AG20: pullback protector | AH20: 0.6 | AI20: yes | AJ20: no | AK20: yes | AL20: yes | AP20: v3_2026-03-19
A21: Q04_E | B21: 4 | C21: 4 | D21: Core | E21: 1 | F21: CommunicationHealth | G21: EmotionalNeeds | I21: E | J21: E | K21: I've learned not to announce when I'm done, I just leave when I'm sure. I downplay it out loud, but mentally I start planning my exit. | L21: 8 | M21: 8 | N21: 4 | O21: 4 | P21: 0 | Q21: Quiet Exit | R21: 4 | U21: 0 | V21: masc:1.4;fem:-1.3 | W21: 1.4 | X21: -1.3 | Y21: COMM_Avoidant | Z21: REG_Suppressor | AA21: LANG_Time | AE21: 0 | AF21: silent exit plan | AG21: strategic withdrawer | AH21: 1.2 | AI21: no | AJ21: no | AK21: yes | AL21: yes | AP21: v3_2026-03-19
A22: Q05_A | B22: 5 | C22: 5 | D22: Core | E22: 1 | F22: CommunicationHealth | G22: EmotionalNeeds | H22: You open up about something personal. They listen, but they don't really respond or say much. How do you take that? | I22: A | J22: A | K22: I don't expect much from people emotionally. I just log it as "noted" and move on. No point getting deep with someone who doesn't meet you there. | L22: 4 | M22: 5 | N22: 0 | O22: 0 | P22: 0 | Q22: Icebox | R22: 1 | U22: 0 | V22: masc:1.8;fem:-1.6 | W22: 1.8 | X22: -1.6 | Y22: COMM_Avoidant | Z22: REG_Suppressor | AA22: LANG_Time | AB22: Scorekeeping_Echo , Vulnerability_Loop | AC22: Scorekeeping_Echo | AD22: Vulnerability_Loop | AE22: 13 | AF22: low expectation logging | AG22: cool detacher | AH22: 0.6 | AI22: yes | AJ22: no | AK22: yes | AL22: yes | AP22: v3_2026-03-19
A23: Q05_B | B23: 5 | C23: 5 | D23: Core | E23: 1 | F23: CommunicationHealth | G23: EmotionalNeeds | I23: B | J23: B | K23: I brush it off, but I don't forget it. Stuff like that reminds me who's safe and who just wants the easy version of me. | L23: 6 | M23: 7 | N23: 4 | O23: 6 | P23: 6 | Q23: Survivor | R23: 8 | U23: 0 | V23: masc:0.3;fem:1.3 | W23: 0.3 | X23: 1.3 | Y23: COMM_Emotional | Z23: REG_SelfSoother | AA23: LANG_Service | AE23: 0 | AF23: guarded memory | AG23: loyalty filter | AH23: 0 | AI23: no | AJ23: no | AK23: yes | AL23: yes | AP23: v3_2026-03-19
A24: Q05_C | B24: 5 | C24: 5 | D24: Core | E24: 1 | F24: CommunicationHealth | G24: EmotionalNeeds | I24: C | J24: C | K24: I try to explain again, maybe they didn't get it. And if they still don't? I stop showing that side to someone who doesn't see me. | L24: 8 | M24: 9 | N24: 8 | O24: 10 | P24: 8 | Q24: Fixer | R24: 5 | U24: 0 | V24: masc:-0.4;fem:2.0 | W24: -0.4 | X24: 2 | Y24: COMM_Emotional | Z24: REG_CoRegulator | AA24: LANG_Service | AE24: 0 | AF24: repair attempt | AG24: persistent helper | AH24: 0 | AI24: no | AJ24: no | AK24: yes | AL24: yes | AP24: v3_2026-03-19
A25: Q05_D | B25: 5 | C25: 5 | D25: Core | E25: 1 | F25: CommunicationHealth | G25: EmotionalNeeds | I25: D | J25: D | K25: I keep it smooth, but I notice the shift. Makes me rethink what I share next time, it's easier to just stay surface when people don't respond. | L25: 5 | M25: 6 | N25: 0 | O25: 2 | P25: 0 | Q25: Performer | R25: 7 | U25: 0 | V25: masc:0.3;fem:0.5 | W25: 0.3 | X25: 0.5 | Y25: COMM_Indirect | Z25: REG_Distractor | AA25: LANG_Gifts | AB25: Public_Private_Split , Conflict_Flip | AC25: Public_Private_Split | AD25: Conflict_Flip | AE25: 8 | AF25: image-based withdrawal | AG25: surface masker | AH25: 1.2 | AI25: yes | AJ25: no | AK25: yes | AL25: yes | AP25: v3_2026-03-19
A26: Q05_E | B26: 5 | C26: 5 | D26: Core | E26: 1 | F26: CommunicationHealth | G26: EmotionalNeeds | I26: E | J26: E | K26: Silence says a lot. I take note. If they care, it'll show later, if not, I don't open that part of me again. | L26: 9 | M26: 9 | N26: 10 | O26: 10 | P26: 10 | Q26: Regulated Grown-Up | R26: 9 | U26: 0 | V26: masc:1.1;fem:0.9 | W26: 1.1 | X26: 0.9 | Y26: COMM_Direct | Z26: REG_CoRegulator | AA26: LANG_Words | AE26: 0 | AF26: high awareness | AG26: calm sentinel | AH26: 0 | AI26: no | AJ26: no | AK26: yes | AL26: yes | AP26: v3_2026-03-19
A27: Q06_A | B27: 6 | C27: 6 | D27: Core | E27: 1 | F27: CommunicationHealth | G27: EmotionalNeeds | H27: Question 6: One day they're into you, then distant the next. How do you handle the mixed signals? | I27: A | J27: A | K27: If you're hot and cold, I'm room temperature and gone. I'm not here to decode moods. | L27: 9 | M27: 9 | N27: 10 | O27: 10 | P27: 10 | Q27: Regulated Grown-Up | R27: 9 | U27: 0 | V27: masc:1.1;fem:0.9 | W27: 1.1 | X27: 0.9 | Y27: COMM_Direct | Z27: REG_CoRegulator | AA27: LANG_Words | AE27: 0 | AF27: blunt detachment | AG27: immediate cutoff | AH27: 1.2 | AI27: no | AJ27: no | AK27: yes | AL27: yes | AP27: v3_2026-03-19
A28: Q06_B | B28: 6 | C28: 6 | D28: Core | E28: 1 | F28: CommunicationHealth | G28: EmotionalNeeds | I28: B | J28: B | K28: I recheck our last texts. Then I reread mine. Then I wonder if I should've said less, or more. I don't bring it up, but it definitely rewires how I respond. | L28: 5 | M28: 6 | N28: 4 | O28: 4 | P28: 2 | Q28: Analyzer | R28: 2 | U28: 0 | V28: masc:1.4;fem:0.1 | W28: 1.4 | X28: 0.1 | Y28: COMM_Logical | Z28: REG_SelfSoother | AA28: LANG_Service | AB28: Trust_Tension | AC28: Trust_Tension | AE28: 6 | AF28: emotional spiral | AG28: overanalyzer | AH28: 0 | AI28: yes | AJ28: no | AK28: yes | AL28: yes | AP28: v3_2026-03-19
A29: Q06_C | B29: 6 | C29: 6 | D29: Core | E29: 1 | F29: CommunicationHealth | G29: EmotionalNeeds | I29: C | J29: C | K29: I back off. They'll either notice or they won't. I'm not chasing people who don't know what they want. | L29: 4 | M29: 5 | N29: 0 | O29: 0 | P29: 0 | Q29: Icebox | R29: 1 | U29: 0 | V29: masc:1.8;fem:-1.6 | W29: 1.8 | X29: -1.6 | Y29: COMM_Avoidant | Z29: REG_Suppressor | AA29: LANG_Time | AB29: Vulnerability_Loop | AC29: Vulnerability_Loop | AE29: 5 | AF29: quiet burn | AG29: disengaged pullback | AH29: 0.6 | AI29: yes | AJ29: no | AK29: yes | AL29: yes | AP29: v3_2026-03-19
A30: Q06_D | B30: 6 | C30: 6 | D30: Core | E30: 1 | F30: CommunicationHealth | G30: EmotionalNeeds | I30: D | J30: D | K30: I stop bringing things up. If they don't want me, I'm not going to beg to be understood. I've played that game before. | L30: 6 | M30: 7 | N30: 4 | O30: 4 | P30: 4 | Q30: Fixer | R30: 5 | U30: 0 | V30: masc:-0.4;fem:2.0 | W30: -0.4 | X30: 2 | Y30: COMM_Emotional | Z30: REG_CoRegulator | AA30: LANG_Service | AB30: Affection_Mismatch , Independence_Collision | AC30: Affection_Mismatch | AD30: Independence_Collision | AE30: 9 | AF30: resigned caregiver | AG30: silent surrender | AH30: 1.2 | AI30: yes | AJ30: no | AK30: yes | AL30: yes | AP30: v3_2026-03-19
A31: Q06_E | B31: 6 | C31: 6 | D31: Core | E31: 1 | F31: CommunicationHealth | G31: EmotionalNeeds | I31: E | J31: E | K31: I tell myself it's probably just stress or a bad week. I don't want to give up too early, but it's hard not to notice when it shifts. | L31: 7 | M31: 8 | N31: 6 | O31: 6 | P31: 4 | Q31: Romantic Idealist | R31: 6 | U31: 0 | V31: masc:-0.4;fem:1.5 | W31: -0.4 | X31: 1.5 | Y31: COMM_Emotional | Z31: REG_Distractor | AA31: LANG_Gifts | AE31: 0 | AF31: tired hope | AG31: cautious optimist | AH31: 0 | AI31: no | AJ31: no | AK31: yes | AL31: yes | AP31: v3_2026-03-19
A32: Q07_A | B32: 7 | C32: 7 | D32: Core | E32: 1 | F32: CommunicationHealth | G32: EmotionalNeeds | H32: Question 7: You're deep in conversation and they suddenly shut down or go cold. What's your move? | I32: A | J32: A | K32: I pause. I've learned not everything's about me. If they want to talk, they will. If not, I don't chase silence. | L32: 8 | M32: 8 | N32: 4 | O32: 4 | P32: 0 | Q32: Icebox | R32: 1 | U32: 0 | V32: masc:1.8;fem:-1.6 | W32: 1.8 | X32: -1.6 | Y32: COMM_Avoidant | Z32: REG_Suppressor | AA32: LANG_Time | AE32: 0 | AF32: calm detachment | AG32: patient withdrawer | AH32: 0.8 | AI32: no | AJ32: no | AK32: yes | AL32: yes | AP32: v3_2026-03-19
A33: Q07_B | B33: 7 | C33: 7 | D33: Core | E33: 1 | F33: CommunicationHealth | G33: EmotionalNeeds | I33: B | J33: B | K33: I immediately think I said something wrong. I start scanning every word trying to figure out what triggered it. | L33: 5 | M33: 6 | N33: 4 | O33: 4 | P33: 2 | Q33: Analyzer | R33: 2 | U33: 0 | V33: masc:1.4;fem:0.1 | W33: 1.4 | X33: 0.1 | Y33: COMM_Logical | Z33: REG_SelfSoother | AA33: LANG_Service | AB33: Vulnerability_Loop | AC33: Vulnerability_Loop | AE33: 5 | AF33: inner spiral | AG33: self-blamer | AH33: 0 | AI33: yes | AJ33: no | AK33: yes | AL33: yes | AP33: v3_2026-03-19
A34: Q07_C | B34: 7 | C34: 7 | D34: Core | E34: 1 | F34: CommunicationHealth | G34: EmotionalNeeds | I34: C | J34: C | K34: I'll ask once. If it's brushed off or ignored, I shift. I'm not the type to sit in someone else's silence for long. | L34: 9 | M34: 9 | N34: 10 | O34: 10 | P34: 10 | Q34: Regulated Grown-Up | R34: 9 | U34: 0 | V34: masc:1.1;fem:0.9 | W34: 1.1 | X34: 0.9 | Y34: COMM_Direct | Z34: REG_CoRegulator | AA34: LANG_Words | AE34: 0 | AF34: direct with boundaries | AG34: firm line-setter | AH34: 0 | AI34: no | AJ34: no | AK34: yes | AL34: yes | AP34: v3_2026-03-19
A35: Q07_D | B35: 7 | C35: 7 | D35: Core | E35: 1 | F35: CommunicationHealth | G35: EmotionalNeeds | I35: D | J35: D | K35: I try to keep the mood up, shift the subject, make it feel less tense, even if I'm freaking out a little inside. | L35: 6 | M35: 7 | N35: 4 | O35: 4 | P35: 2 | Q35: Performer | R35: 7 | U35: 0 | V35: masc:0.3;fem:0.5 | W35: 0.3 | X35: 0.5 | Y35: COMM_Indirect | Z35: REG_Distractor | AA35: LANG_Gifts | AB35: Vulnerability_Loop | AC35: Vulnerability_Loop | AE35: 5 | AF35: smooth cover-up | AG35: tension diffuser | AH35: 0 | AI35: yes | AJ35: no | AK35: yes | AL35: yes | AP35: v3_2026-03-19
A36: Q07_E | B36: 7 | C36: 7 | D36: Core | E36: 1 | F36: CommunicationHealth | G36: EmotionalNeeds | I36: E | J36: E | K36: I feel it, but I don't say anything. I stay present, hoping they'll come back to me on their own. | L36: 6 | M36: 6 | N36: 4 | O36: 4 | P36: 4 | Q36: Translator | R36: 3 | U36: 0 | V36: masc:-0.1;fem:1.6 | W36: -0.1 | X36: 1.6 | Y36: COMM_Indirect | Z36: REG_CoRegulator | AA36: LANG_Words | AB36: Vulnerability_Loop | AC36: Vulnerability_Loop | AE36: 5 | AF36: gentle waiter | AG36: silent holder | AH36: 0.6 | AI36: yes | AJ36: no | AK36: yes | AL36: yes | AP36: v3_2026-03-19
A37: Q08_A | B37: 8 | C37: 8 | D37: Core | E37: 1 | F37: CommunicationHealth | G37: EmotionalNeeds | H37: Question 8: You feel them pulling away. They haven't said it, but the shift is obvious. What runs through your head first? | I37: A | J37: A | K37: Here we go again. I already know how this plays out. I stop trying the second I feel myself caring more than they do. | L37: 5 | M37: 5 | N37: 4 | O37: 2 | P37: 2 | Q37: Survivor | R37: 8 | U37: 0 | V37: masc:0.3;fem:1.3 | W37: 0.3 | X37: 1.3 | Y37: COMM_Emotional | Z37: REG_SelfSoother | AA37: LANG_Service | AB37: Vulnerability_Loop | AC37: Vulnerability_Loop | AE37: 5 | AF37: pain-calibrated exit | AG37: early withdrawer | AH37: 0.6 | AI37: yes | AJ37: no | AK37: yes | AL37: yes | AP37: v3_2026-03-19
A38: Q08_B | B38: 8 | C38: 8 | D38: Core | E38: 1 | F38: CommunicationHealth | G38: EmotionalNeeds | I38: B | J38: B | K38: It's subtle, but I clock everything. Less emojis. Slower replies. Something's off, I just haven't figured out what yet. | L38: 7 | M38: 8 | N38: 6 | O38: 6 | P38: 6 | Q38: Analyzer | R38: 2 | U38: 0 | V38: masc:1.4;fem:0.1 | W38: 1.4 | X38: 0.1 | Y38: COMM_Logical | Z38: REG_SelfSoother | AA38: LANG_Service | AE38: 0 | AF38: pattern tracker | AG38: micro-signal reader | AH38: 0.6 | AI38: no | AJ38: no | AK38: yes | AL38: yes | AP38: v3_2026-03-19
A39: Q08_C | B39: 8 | C39: 8 | D39: Core | E39: 1 | F39: CommunicationHealth | G39: EmotionalNeeds | I39: C | J39: C | K39: I don't ask. I just start detaching. If you're fading, I'm not chasing. I've done that before, and I don't owe anyone a meltdown. | L39: 5 | M39: 6 | N39: 0 | O39: 2 | P39: 0 | Q39: Quiet Exit | R39: 4 | U39: 0 | V39: masc:1.4;fem:-1.3 | W39: 1.4 | X39: -1.3 | Y39: COMM_Avoidant | Z39: REG_Suppressor | AA39: LANG_Time | AB39: Vulnerability_Loop | AC39: Vulnerability_Loop | AE39: 5 | AF39: soft boundary | AG39: quiet exit | AH39: 0.2 | AI39: yes | AJ39: no | AK39: yes | AL39: yes | AP39: v3_2026-03-19
A40: Q08_D | B40: 8 | C40: 8 | D40: Core | E40: 1 | F40: CommunicationHealth | G40: EmotionalNeeds | I40: D | J40: D | K40: Maybe they just need space. I try not to assume the worst... but yeah, it's hard not to take it personal. | L40: 7 | M40: 8 | N40: 6 | O40: 6 | P40: 4 | Q40: Romantic Idealist | R40: 6 | U40: 0 | V40: masc:-0.4;fem:1.5 | W40: -0.4 | X40: 1.5 | Y40: COMM_Emotional | Z40: REG_Distractor | AA40: LANG_Gifts | AE40: 0 | AF40: fragile optimism | AG40: tentative hope | AH40: 0 | AI40: no | AJ40: no | AK40: yes | AL40: yes | AP40: v3_2026-03-19
A41: Q08_E | B41: 8 | C41: 8 | D41: Core | E41: 1 | F41: CommunicationHealth | G41: EmotionalNeeds | I41: E | J41: E | K41: Cool. If they're gonna play distant, I'll be busy too. I'm not built to beg for consistency. | L41: 4 | M41: 5 | N41: 0 | O41: 0 | P41: 0 | Q41: Icebox | R41: 1 | U41: 0 | V41: masc:1.8;fem:-1.6 | W41: 1.8 | X41: -1.6 | Y41: COMM_Avoidant | Z41: REG_Suppressor | AA41: LANG_Time | AB41: Vulnerability_Loop , Pursuer_Distancer | AC41: Vulnerability_Loop | AD41: Pursuer_Distancer | AE41: 11 | AF41: defensive control | AG41: mirrored distance | AH41: 0 | AI41: yes | AJ41: no | AK41: yes | AL41: yes | AP41: v3_2026-03-19
A42: Q09_A | B42: 9 | C42: 9 | D42: Core | E42: 1.05 | F42: ConflictRepair | G42: CommunicationHealth | H42: Question 9: They cancel plans last minute. No real reason, no reschedule. How do you take it? | I42: A | J42: A | K42: Noted. That's usually my cue to start pulling my energy back. I don't throw a fit, I just stop handing out access. | L42: 7 | M42: 8 | N42: 4 | O42: 4 | P42: 0 | Q42: Quiet Exit | R42: 4 | U42: 0 | V42: masc:1.4;fem:-1.3 | W42: 1.4 | X42: -1.3 | Y42: COMM_Avoidant | Z42: REG_Suppressor | AA42: LANG_Time | AE42: 0 | AF42: soft withdrawal | AG42: quiet boundary | AH42: 0.2 | AI42: no | AJ42: no | AK42: yes | AL42: yes | AP42: v3_2026-03-19
A43: Q09_B | B43: 9 | C43: 9 | D43: Core | E43: 1.05 | F43: ConflictRepair | G43: CommunicationHealth | I43: B | J43: B | K43: I act like it's fine, but it lingers. Now I'm checking who else they were with, what story that timing fits into. I overthink for a living. | L43: 5 | M43: 6 | N43: 4 | O43: 4 | P43: 2 | Q43: Analyzer | R43: 2 | U43: 0 | V43: masc:1.4;fem:0.1 | W43: 1.4 | X43: 0.1 | Y43: COMM_Logical | Z43: REG_SelfSoother | AA43: LANG_Service | AB43: Vulnerability_Loop | AC43: Vulnerability_Loop | AE43: 5 | AF43: obsessive cross-referencer | AG43: trust checker | AH43: 0 | AI43: yes | AJ43: no | AK43: yes | AL43: yes | AP43: v3_2026-03-19
A44: Q09_C | B44: 9 | C44: 9 | D44: Core | E44: 1.05 | F44: ConflictRepair | G44: CommunicationHealth | I44: C | J44: C | K44: It stings. I replay the texts a few times, wondering what I said or didn't say. I don't bring it up, but I definitely adjust after that. | L44: 5 | M44: 6 | N44: 2 | O44: 4 | P44: 2 | Q44: Phantom Seeker | R44: 10 | U44: 0 | V44: masc:-0.2;fem:1.5 | W44: -0.2 | X44: 1.5 | Y44: COMM_Emotional | Z44: REG_SelfSoother | AA44: LANG_Touch | AB44: Vulnerability_Loop | AC44: Vulnerability_Loop | AE44: 5 | AF44: internalizer pullback | AG44: cautious retreater | AH44: 0 | AI44: yes | AJ44: no | AK44: yes | AL44: yes | AP44: v3_2026-03-19
A45: Q09_D | B45: 9 | C45: 9 | D45: Core | E45: 1.05 | F45: ConflictRepair | G45: CommunicationHealth | I45: D | J45: D | K45: I get annoyed, then weirdly try harder. Like maybe if I'm more consistent, they'll start matching that. It never really works, but I still do it. | L45: 4 | M45: 5 | N45: 2 | O45: 2 | P45: 2 | Q45: Fixer | R45: 5 | U45: 0 | V45: masc:-0.4;fem:2.0 | W45: -0.4 | X45: 2 | Y45: COMM_Emotional | Z45: REG_CoRegulator | AA45: LANG_Service | AB45: Commitment_Ambiguity | AC45: Commitment_Ambiguity | AE45: 5 | AF45: conditional effort loop | AG45: overcompensator | AH45: 0 | AI45: yes | AJ45: no | AK45: yes | AL45: yes | AP45: v3_2026-03-19
A46: Q09_E | B46: 9 | C46: 9 | D46: Core | E46: 1.05 | F46: ConflictRepair | G46: CommunicationHealth | I46: E | J46: E | K46: Cool. That tells me everything I needed to know. I move different after that, no announcement required. | L46: 4 | M46: 5 | N46: 0 | O46: 0 | P46: 0 | Q46: Icebox | R46: 1 | U46: 0 | V46: masc:1.8;fem:-1.6 | W46: 1.8 | X46: -1.6 | Y46: COMM_Avoidant | Z46: REG_Suppressor | AA46: LANG_Time | AE46: 0 | AF46: cold logic | AG46: decisive exit | AH46: 0.6 | AI46: no | AJ46: no | AK46: yes | AL46: yes | AP46: v3_2026-03-19
A47: Q10_A | B47: 10 | C47: 10 | D47: Core | E47: 1.05 | F47: ConflictRepair | G47: CommunicationHealth | H47: Question 10: They come to you for comfort when things go wrong-but you're not sure they'd do the same for you. What runs through your mind? | I47: A | J47: A | K47: I play the part, but I clock the imbalance. I've been the safe place before, doesn't mean they ever planned to stay. | L47: 7 | M47: 8 | N47: 6 | O47: 8 | P47: 6 | Q47: Survivor | R47: 8 | U47: 0 | V47: masc:0.3;fem:1.3 | W47: 0.3 | X47: 1.3 | Y47: COMM_Emotional | Z47: REG_SelfSoother | AA47: LANG_Service | AE47: 0 | AF47: burned-out responder | AG47: guarded giver | AH47: 0 | AI47: no | AJ47: no | AK47: yes | AL47: yes | AP47: v3_2026-03-19
A48: Q10_B | B48: 10 | C48: 10 | D48: Core | E48: 1.05 | F48: ConflictRepair | G48: CommunicationHealth | I48: B | J48: B | K48: I try to be what they need, hoping maybe this time they'll realize I'm more than a backup plan. | L48: 6 | M48: 7 | N48: 4 | O48: 6 | P48: 4 | Q48: Fixer | R48: 5 | U48: 0 | V48: masc:-0.4;fem:2.0 | W48: -0.4 | X48: 2 | Y48: COMM_Emotional | Z48: REG_CoRegulator | AA48: LANG_Service | AB48: Commitment_Ambiguity | AC48: Commitment_Ambiguity | AE48: 5 | AF48: approval-seeking caretaker | AG48: hopeful server | AH48: 0 | AI48: yes | AJ48: no | AK48: yes | AL48: yes | AP48: v3_2026-03-19
A49: Q10_C | B49: 10 | C49: 10 | D49: Core | E49: 1.05 | F49: ConflictRepair | G49: CommunicationHealth | I49: C | J49: C | K49: I comfort them, but in my head I'm already creating distance. If I can't count on them too, this whole thing is one-sided. | L49: 7 | M49: 8 | N49: 6 | O49: 8 | P49: 6 | Q49: Analyzer | R49: 2 | U49: 0 | V49: masc:1.4;fem:0.1 | W49: 1.4 | X49: 0.1 | Y49: COMM_Logical | Z49: REG_SelfSoother | AA49: LANG_Service | AE49: 0 | AF49: measured pullback | AG49: quiet assessor | AH49: 0 | AI49: no | AJ49: no | AK49: yes | AL49: yes | AP49: v3_2026-03-19
A50: Q10_D | B50: 10 | C50: 10 | D50: Core | E50: 1.05 | F50: ConflictRepair | G50: CommunicationHealth | I50: D | J50: D | K50: I act calm, but I feel it. When I need someone, I keep it to myself, so watching them lean on me makes the silence louder. | L50: 5 | M50: 6 | N50: 2 | O50: 4 | P50: 2 | Q50: Phantom Seeker | R50: 10 | U50: 0 | V50: masc:-0.2;fem:1.5 | W50: -0.2 | X50: 1.5 | Y50: COMM_Emotional | Z50: REG_SelfSoother | AA50: LANG_Touch | AB50: Transparency_Gap | AC50: Transparency_Gap | AE50: 5 | AF50: quiet resentment | AG50: unspoken holder | AH50: 0 | AI50: yes | AJ50: no | AK50: yes | AL50: yes | AP50: v3_2026-03-19
A51: Q10_E | B51: 10 | C51: 10 | D51: Core | E51: 1.05 | F51: ConflictRepair | G51: CommunicationHealth | I51: E | J51: E | K51: I give them what they need in the moment. Then I sit with the feeling later, wondering why I always end up being the one who shows up. | L51: 6 | M51: 7 | N51: 4 | O51: 4 | P51: 4 | Q51: Romantic Idealist | R51: 6 | U51: 0 | V51: masc:-0.4;fem:1.5 | W51: -0.4 | X51: 1.5 | Y51: COMM_Emotional | Z51: REG_Distractor | AA51: LANG_Gifts | AE51: 0 | AF51: tired loyal dreamer | AG51: devoted but drained | AH51: 0 | AI51: no | AJ51: no | AK51: yes | AL51: yes | AP51: v3_2026-03-19
A52: Q11_A | B52: 11 | C52: 11 | D52: Core | E52: 1.05 | F52: ConflictRepair | G52: CommunicationHealth | H52: They start acting distant-less replies, colder tone, still polite. What's your first move? | I52: A | J52: A | K52: I give them space. If they want to talk, they will. If not, I take the hint. | L52: 7 | M52: 8 | N52: 4 | O52: 4 | P52: 0 | Q52: Icebox | R52: 1 | U52: 0 | V52: masc:1.8;fem:-1.6 | W52: 1.8 | X52: -1.6 | Y52: COMM_Avoidant | Z52: REG_Suppressor | AA52: LANG_Time | AE52: 0 | AF52: detached cool | AG52: patient withdrawer | AH52: 1.2 | AI52: no | AJ52: no | AK52: yes | AL52: yes | AP52: v3_2026-03-19
A53: Q11_B | B53: 11 | C53: 11 | D53: Core | E53: 1.05 | F53: ConflictRepair | G53: CommunicationHealth | I53: B | J53: B | K53: I reread every text. Then I spiral into what I should've said differently. | L53: 4 | M53: 5 | N53: 2 | O53: 2 | P53: 2 | Q53: Analyzer | R53: 2 | U53: 0 | V53: masc:1.4;fem:0.1 | W53: 1.4 | X53: 0.1 | Y53: COMM_Logical | Z53: REG_SelfSoother | AA53: LANG_Service | AB53: Trust_Tension | AC53: Trust_Tension | AE53: 6 | AF53: ruminating replayer | AG53: overanalyzer | AH53: 0 | AI53: yes | AJ53: no | AK53: yes | AL53: yes | AP53: v3_2026-03-19
A54: Q11_C | B54: 11 | C54: 11 | D54: Core | E54: 1.05 | F54: ConflictRepair | G54: CommunicationHealth | I54: C | J54: C | K54: I mirror their shift. If they're pulling back, so am I, no explanations. | L54: 6 | M54: 7 | N54: 2 | O54: 2 | P54: 0 | Q54: Quiet Exit | R54: 4 | U54: 0 | V54: masc:1.4;fem:-1.3 | W54: 1.4 | X54: -1.3 | Y54: COMM_Avoidant | Z54: REG_Suppressor | AA54: LANG_Time | AB54: Pursuer_Distancer | AC54: Pursuer_Distancer | AE54: 6 | AF54: soft echo | AG54: mirrored withdrawal | AH54: 0.6 | AI54: yes | AJ54: no | AK54: yes | AL54: yes | AP54: v3_2026-03-19
A55: Q11_D | B55: 11 | C55: 11 | D55: Core | E55: 1.05 | F55: ConflictRepair | G55: CommunicationHealth | I55: D | J55: D | K55: I try to re-engage them. Make them laugh. Be light. I don't want to feel the shift. | L55: 6 | M55: 7 | N55: 4 | O55: 4 | P55: 2 | Q55: Performer | R55: 7 | U55: 0 | V55: masc:0.3;fem:0.5 | W55: 0.3 | X55: 0.5 | Y55: COMM_Indirect | Z55: REG_Distractor | AA55: LANG_Gifts | AB55: Vulnerability_Loop | AC55: Vulnerability_Loop | AE55: 5 | AF55: mood manager | AG55: tension diffuser | AH55: 0 | AI55: yes | AJ55: no | AK55: yes | AL55: yes | AP55: v3_2026-03-19
A56: Q11_E | B56: 11 | C56: 11 | D56: Core | E56: 1.05 | F56: ConflictRepair | G56: CommunicationHealth | I56: E | J56: E | K56: I sit with it, hoping they'll come back on their own. I don't press. I just wait. | L56: 7 | M56: 8 | N56: 6 | O56: 8 | P56: 8 | Q56: Translator | R56: 3 | U56: 0 | V56: masc:-0.1;fem:1.6 | W56: -0.1 | X56: 1.6 | Y56: COMM_Indirect | Z56: REG_CoRegulator | AA56: LANG_Words | AE56: 0 | AF56: gentle responder | AG56: quiet holder | AH56: 0 | AI56: no | AJ56: no | AK56: yes | AL56: yes | AP56: v3_2026-03-19
A57: Q12_A | B57: 12 | C57: 12 | D57: Core | E57: 1.05 | F57: ConflictRepair | G57: CommunicationHealth | H57: They used to check in every day. Now they don't. You haven't brought it up yet. What's brewing in your head? | I57: A | J57: A | K57: Something changed. I don't know what, but it's not just in my head. | L57: 7 | M57: 8 | N57: 6 | O57: 8 | P57: 6 | Q57: Analyzer | R57: 2 | U57: 0 | V57: masc:1.4;fem:0.1 | W57: 1.4 | X57: 0.1 | Y57: COMM_Logical | Z57: REG_SelfSoother | AA57: LANG_Service | AE57: 0 | AF57: pattern watcher | AG57: subtle signal reader | AH57: 0 | AI57: no | AJ57: no | AK57: yes | AL57: yes | AP57: v3_2026-03-19
A58: Q12_B | B58: 12 | C58: 12 | D58: Core | E58: 1.05 | F58: ConflictRepair | G58: CommunicationHealth | I58: B | J58: B | K58: I try not to assume. I wait. If I ask and it's nothing, I'll feel stupid. | L58: 5 | M58: 6 | N58: 2 | O58: 4 | P58: 2 | Q58: Phantom Seeker | R58: 10 | U58: 0 | V58: masc:-0.2;fem:1.5 | W58: -0.2 | X58: 1.5 | Y58: COMM_Emotional | Z58: REG_SelfSoother | AA58: LANG_Touch | AB58: Vulnerability_Loop | AC58: Vulnerability_Loop | AE58: 5 | AF58: doubtful waiter | AG58: hesitant checker | AH58: 0 | AI58: yes | AJ58: no | AK58: yes | AL58: yes | AP58: v3_2026-03-19
A59: Q12_C | B59: 12 | C59: 12 | D59: Core | E59: 1.05 | F59: ConflictRepair | G59: CommunicationHealth | I59: C | J59: C | K59: I bring it up again, but this time they can probably hear the shift in my tone. I'm not trying to argue-I just need them to actually hear me. | L59: 9 | M59: 9 | N59: 10 | O59: 10 | P59: 10 | Q59: Regulated Grown-Up | R59: 9 | U59: 0 | V59: masc:1.1;fem:0.9 | W59: 1.1 | X59: 0.9 | Y59: COMM_Direct | Z59: REG_CoRegulator | AA59: LANG_Words | AE59: 0 | AF59: calm confronter | AG59: direct communicator | AH59: 0 | AI59: no | AJ59: no | AK59: yes | AL59: yes | AP59: v3_2026-03-19
A60: Q12_D | B60: 12 | C60: 12 | D60: Core | E60: 1.05 | F60: ConflictRepair | G60: CommunicationHealth | I60: D | J60: D | K60: I joke about it to see how they react. If they don't bite, I pull back quietly. | L60: 6 | M60: 7 | N60: 2 | O60: 2 | P60: 0 | Q60: Performer | R60: 7 | U60: 0 | V60: masc:0.3;fem:0.5 | W60: 0.3 | X60: 0.5 | Y60: COMM_Indirect | Z60: REG_Distractor | AA60: LANG_Gifts | AB60: Vulnerability_Loop , Scorekeeping_Echo | AC60: Vulnerability_Loop | AD60: Scorekeeping_Echo | AE60: 13 | AF60: playful tester | AG60: indirect feeler | AH60: 0.8 | AI60: yes | AJ60: no | AK60: yes | AL60: yes | AP60: v3_2026-03-19
A61: Q12_E | B61: 12 | C61: 12 | D61: Core | E61: 1.05 | F61: ConflictRepair | G61: CommunicationHealth | I61: E | J61: E | K61: I shift before they get the chance to. I've seen this pattern before, I know how it ends. | L61: 6 | M61: 7 | N61: 4 | O61: 6 | P61: 4 | Q61: Survivor | R61: 8 | U61: 0 | V61: masc:0.3;fem:1.3 | W61: 0.3 | X61: 1.3 | Y61: COMM_Emotional | Z61: REG_SelfSoother | AA61: LANG_Service | AB61: Vulnerability_Loop | AC61: Vulnerability_Loop | AE61: 5 | AF61: pain-preemptive responder | AG61: early exit planner | AH61: 0 | AI61: yes | AJ61: no | AK61: yes | AL61: yes | AP61: v3_2026-03-19
A62: Q13_A | B62: 13 | C62: 13 | D62: Core | E62: 1.05 | F62: ConflictRepair | G62: CommunicationHealth | H62: They say they like you-but they're inconsistent. What part of you answers that first? | I62: A | J62: A | K62: I just need space to check if I'm seeing it clearly before I lean in. Not to play games. | L62: 8 | M62: 8 | N62: 4 | O62: 4 | P62: 2 | Q62: Quiet Exit | R62: 4 | U62: 0 | V62: masc:1.4;fem:-1.3 | W62: 1.4 | X62: -1.3 | Y62: COMM_Avoidant | Z62: REG_Suppressor | AA62: LANG_Time | AE62: 0 | AF62: observer mode | AG62: cautious engager | AH62: 0.2 | AI62: no | AJ62: no | AK62: yes | AL62: yes | AP62: v3_2026-03-19
A63: Q13_B | B63: 13 | C63: 13 | D63: Core | E63: 1.05 | F63: ConflictRepair | G63: CommunicationHealth | I63: B | J63: B | K63: I start imagining what it could be. I try not to get ahead of myself, I just like feeling what it can be. | L63: 7 | M63: 8 | N63: 6 | O63: 6 | P63: 4 | Q63: Romantic Idealist | R63: 6 | U63: 0 | V63: masc:-0.4;fem:1.5 | W63: -0.4 | X63: 1.5 | Y63: COMM_Emotional | Z63: REG_Distractor | AA63: LANG_Gifts | AE63: 0 | AF63: daydreaming hopeful | AG63: romantic visionary | AH63: 0 | AI63: no | AJ63: no | AK63: yes | AL63: yes | AP63: v3_2026-03-19
A64: Q13_C | B64: 13 | C64: 13 | D64: Core | E64: 1.05 | F64: ConflictRepair | G64: CommunicationHealth | I64: C | J64: C | K64: I don't say much, but I start showing up more, checking in, remembering little things. That's usually how I start showing my interest. | L64: 8 | M64: 9 | N64: 8 | O64: 10 | P64: 8 | Q64: Translator | R64: 3 | U64: 0 | V64: masc:-0.1;fem:1.6 | W64: -0.1 | X64: 1.6 | Y64: COMM_Indirect | Z64: REG_CoRegulator | AA64: LANG_Words | AE64: 0 | AF64: steady signaler | AG64: consistent investor | AH64: 0 | AI64: no | AJ64: no | AK64: yes | AL64: yes | AP64: v3_2026-03-19
A65: Q13_D | B65: 13 | C65: 13 | D65: Core | E65: 1.05 | F65: ConflictRepair | G65: CommunicationHealth | I65: D | J65: D | K65: I want them to like me back, but I need to know it's safe first, so I keep it light while I wait on their actions. | L65: 7 | M65: 8 | N65: 4 | O65: 6 | P65: 4 | Q65: Performer | R65: 7 | U65: 0 | V65: masc:0.3;fem:0.5 | W65: 0.3 | X65: 0.5 | Y65: COMM_Indirect | Z65: REG_Distractor | AA65: LANG_Gifts | AE65: 0 | AF65: strategic flirter | AG65: cautious charmer | AH65: 0.2 | AI65: no | AJ65: no | AK65: yes | AL65: yes | AP65: v3_2026-03-19
A66: Q13_E | B66: 13 | C66: 13 | D66: Core | E66: 1.05 | F66: ConflictRepair | G66: CommunicationHealth | I66: E | J66: E | K66: If I like someone, it shows, but I don't rush just because the vibe is good. I wait to see if the energy stays real. | L66: 8 | M66: 9 | N66: 4 | O66: 6 | P66: 2 | Q66: Icebox | R66: 1 | U66: 0 | V66: masc:1.8;fem:-1.6 | W66: 1.8 | X66: -1.6 | Y66: COMM_Avoidant | Z66: REG_Suppressor | AA66: LANG_Time | AE66: 0 | AF66: guarded realist | AG66: patient tester | AH66: 0.6 | AI66: no | AJ66: no | AK66: yes | AL66: yes | AP66: v3_2026-03-19
A67: Q14_A | B67: 14 | C67: 14 | D67: Core | E67: 1.05 | F67: ConflictRepair | G67: CommunicationHealth | H67: They keep you in the loop, but never quite make you the priority. What shifts in you? | I67: A | J67: A | K67: I mirror it. They get the same version of me they're handing out. No extra effort for bare minimum. | L67: 7 | M67: 8 | N67: 4 | O67: 4 | P67: 0 | Q67: Icebox | R67: 1 | U67: 0 | V67: masc:1.8;fem:-1.6 | W67: 1.8 | X67: -1.6 | Y67: COMM_Avoidant | Z67: REG_Suppressor | AA67: LANG_Time | AE67: 0 | AF67: tactical disengagement | AG67: mirrored detachment | AH67: 0.6 | AI67: no | AJ67: no | AK67: yes | AL67: yes | AP67: v3_2026-03-19
A68: Q14_B | B68: 14 | C68: 14 | D68: Core | E68: 1.05 | F68: ConflictRepair | G68: CommunicationHealth | I68: B | J68: B | K68: I start overexplaining, why I care, what I mean, what I hope for. I try to make it easier to choose me. | L68: 5 | M68: 6 | N68: 4 | O68: 4 | P68: 4 | Q68: Fixer | R68: 5 | U68: 0 | V68: masc:-0.4;fem:2.0 | W68: -0.4 | X68: 2 | Y68: COMM_Emotional | Z68: REG_CoRegulator | AA68: LANG_Service | AB68: Vulnerability_Loop | AC68: Vulnerability_Loop | AE68: 5 | AF68: emotional sales pitch | AG68: approval seeker | AH68: 0 | AI68: yes | AJ68: no | AK68: yes | AL68: yes | AP68: v3_2026-03-19
A69: Q14_C | B69: 14 | C69: 14 | D69: Core | E69: 1.05 | F69: ConflictRepair | G69: CommunicationHealth | I69: C | J69: C | K69: I act like I don't care, but it eats at me. I show up less, talk less, but I'm still watching every move. | L69: 5 | M69: 6 | N69: 2 | O69: 4 | P69: 2 | Q69: Phantom Seeker | R69: 10 | U69: 0 | V69: masc:-0.2;fem:1.5 | W69: -0.2 | X69: 1.5 | Y69: COMM_Emotional | Z69: REG_SelfSoother | AA69: LANG_Touch | AB69: Vulnerability_Loop | AC69: Vulnerability_Loop | AE69: 5 | AF69: internal retreat | AG69: quiet stewer | AH69: 0 | AI69: yes | AJ69: no | AK69: yes | AL69: yes | AP69: v3_2026-03-19
A70: Q14_D | B70: 14 | C70: 14 | D70: Core | E70: 1.05 | F70: ConflictRepair | G70: CommunicationHealth | I70: D | J70: D | K70: I pretend I'm fine, but the shift gets loud. Suddenly I'm noticing who they respond to faster. Who gets their energy. | L70: 6 | M70: 7 | N70: 4 | O70: 4 | P70: 2 | Q70: Analyzer | R70: 2 | U70: 0 | V70: masc:1.4;fem:0.1 | W70: 1.4 | X70: 0.1 | Y70: COMM_Logical | Z70: REG_SelfSoother | AA70: LANG_Service | AB70: Vulnerability_Loop | AC70: Vulnerability_Loop | AE70: 5 | AF70: silent scorekeeper | AG70: attention tracker | AH70: 1.8 | AI70: yes | AJ70: no | AK70: yes | AL70: yes | AP70: v3_2026-03-19
A71: Q14_E | B71: 14 | C71: 14 | D71: Core | E71: 1.05 | F71: ConflictRepair | G71: CommunicationHealth | I71: E | J71: E | K71: I clock it, stash the receipt, and stop reaching out. I've made that mistake before, won't repeat it. | L71: 8 | M71: 9 | N71: 4 | O71: 6 | P71: 2 | Q71: Quiet Exit | R71: 4 | U71: 0 | V71: masc:1.4;fem:-1.3 | W71: 1.4 | X71: -1.3 | Y71: COMM_Avoidant | Z71: REG_Suppressor | AA71: LANG_Time | AE71: 0 | AF71: strategic shutdown | AG71: decisive withdrawer | AH71: 0.6 | AI71: no | AJ71: no | AK71: yes | AL71: yes | AP71: v3_2026-03-19
A72: Q15_A | B72: 15 | C72: 15 | D72: Core | E72: 1.05 | F72: ConflictRepair | G72: CommunicationHealth | H72: They respond fast. They remember what you say. No mixed signals. It's easy. How does your brain react to that kind of consistency? | I72: A | J72: A | K72: I wait for the twist. Nobody's that into me for no reason. I enjoy it, but I stay suspicious. | L72: 6 | M72: 7 | N72: 4 | O72: 6 | P72: 4 | Q72: Survivor | R72: 8 | U72: 0 | V72: masc:0.3;fem:1.3 | W72: 0.3 | X72: 1.3 | Y72: COMM_Emotional | Z72: REG_SelfSoother | AA72: LANG_Service | AB72: Vulnerability_Loop | AC72: Vulnerability_Loop | AE72: 5 | AF72: trauma-calibrated skepticism | AG72: guarded receiver | AH72: 0 | AI72: yes | AJ72: no | AK72: yes | AL72: yes | AP72: v3_2026-03-19
A73: Q15_B | B73: 15 | C73: 15 | D73: Core | E73: 1.05 | F73: ConflictRepair | G73: CommunicationHealth | I73: B | J73: B | K73: I get anxious. Like... if it's this easy now, what happens when I actually need something? | L73: 5 | M73: 6 | N73: 2 | O73: 4 | P73: 2 | Q73: Phantom Seeker | R73: 10 | U73: 0 | V73: masc:-0.2;fem:1.5 | W73: -0.2 | X73: 1.5 | Y73: COMM_Emotional | Z73: REG_SelfSoother | AA73: LANG_Touch | AB73: Vulnerability_Loop | AC73: Vulnerability_Loop | AE73: 5 | AF73: fragile trust reflex | AG73: uneasy believer | AH73: 0 | AI73: yes | AJ73: no | AK73: yes | AL73: yes | AP73: v3_2026-03-19
A74: Q15_C | B74: 15 | C74: 15 | D74: Core | E74: 1.05 | F74: ConflictRepair | G74: CommunicationHealth | I74: C | J74: C | K74: I like it, but I start checking what they want from me. Nobody invests like that unless they're expecting a return. | L74: 6 | M74: 7 | N74: 4 | O74: 6 | P74: 4 | Q74: Analyzer | R74: 2 | U74: 0 | V74: masc:1.4;fem:0.1 | W74: 1.4 | X74: 0.1 | Y74: COMM_Logical | Z74: REG_SelfSoother | AA74: LANG_Service | AB74: Vulnerability_Loop | AC74: Vulnerability_Loop | AE74: 5 | AF74: reciprocity scanner | AG74: cautious assessor | AH74: 0 | AI74: yes | AJ74: no | AK74: yes | AL74: yes | AP74: v3_2026-03-19
A75: Q15_D | B75: 15 | C75: 15 | D75: Core | E75: 1.05 | F75: ConflictRepair | G75: CommunicationHealth | I75: D | J75: D | K75: I try not to mess it up. I overthink everything I send back. It feels good, but fragile. | L75: 6 | M75: 7 | N75: 4 | O75: 4 | P75: 2 | Q75: Performer | R75: 7 | U75: 0 | V75: masc:0.3;fem:0.5 | W75: 0.3 | X75: 0.5 | Y75: COMM_Indirect | Z75: REG_Distractor | AA75: LANG_Gifts | AB75: Vulnerability_Loop | AC75: Vulnerability_Loop | AE75: 5 | AF75: image anxiety | AG75: careful performer | AH75: 0 | AI75: yes | AJ75: no | AK75: yes | AL75: yes | AP75: v3_2026-03-19
A76: Q15_E | B76: 15 | C76: 15 | D76: Core | E76: 1.05 | F76: ConflictRepair | G76: CommunicationHealth | I76: E | J76: E | K76: I match it, but I don't flood it. Feels rare, and I'm not about to fumble it with weird energy. | L76: 9 | M76: 9 | N76: 6 | O76: 6 | P76: 2 | Q76: Icebox | R76: 1 | U76: 0 | V76: masc:1.8;fem:-1.6 | W76: 1.8 | X76: -1.6 | Y76: COMM_Avoidant | Z76: REG_Suppressor | AA76: LANG_Time | AE76: 0 | AF76: cautious returner | AG76: balanced engager | AH76: 0 | AI76: no | AJ76: no | AK76: yes | AL76: yes | AP76: v3_2026-03-19
A77: Q16_A | B77: 16 | C77: 16 | D77: Core | E77: 1.05 | F77: ConflictRepair | G77: CommunicationHealth | H77: They go from warm to cold out of nowhere. What's your first move? | I77: A | J77: A | K77: If you're hot and cold, I'm room temperature and gone. I'm not here to decode moods. | L77: 9 | M77: 9 | N77: 10 | O77: 10 | P77: 10 | Q77: Regulated Grown-Up | R77: 9 | U77: 0 | V77: masc:1.1;fem:0.9 | W77: 1.1 | X77: 0.9 | Y77: COMM_Direct | Z77: REG_CoRegulator | AA77: LANG_Words | AE77: 0 | AF77: blunt detachment | AG77: immediate cutoff | AH77: 1.2 | AI77: no | AJ77: no | AK77: yes | AL77: yes | AP77: v3_2026-03-19
A78: Q16_B | B78: 16 | C78: 16 | D78: Core | E78: 1.05 | F78: ConflictRepair | G78: CommunicationHealth | I78: B | J78: B | K78: I recheck our last texts. Then I reread mine. Then I wonder if I should've said less, or more. I don't bring it up, but it definitely rewires how I respond. | L78: 5 | M78: 6 | N78: 4 | O78: 4 | P78: 2 | Q78: Analyzer | R78: 2 | U78: 0 | V78: masc:1.4;fem:0.1 | W78: 1.4 | X78: 0.1 | Y78: COMM_Logical | Z78: REG_SelfSoother | AA78: LANG_Service | AB78: Trust_Tension | AC78: Trust_Tension | AE78: 6 | AF78: emotional spiral | AG78: overanalyzer | AH78: 0 | AI78: yes | AJ78: no | AK78: yes | AL78: yes | AP78: v3_2026-03-19
A79: Q16_C | B79: 16 | C79: 16 | D79: Core | E79: 1.05 | F79: ConflictRepair | G79: CommunicationHealth | I79: C | J79: C | K79: I back off. They'll either notice or they won't. I'm not chasing people who don't know what they want. | L79: 4 | M79: 5 | N79: 0 | O79: 0 | P79: 0 | Q79: Icebox | R79: 1 | U79: 0 | V79: masc:1.8;fem:-1.6 | W79: 1.8 | X79: -1.6 | Y79: COMM_Avoidant | Z79: REG_Suppressor | AA79: LANG_Time | AB79: Vulnerability_Loop | AC79: Vulnerability_Loop | AE79: 5 | AF79: quiet burn | AG79: disengaged pullback | AH79: 0.6 | AI79: yes | AJ79: no | AK79: yes | AL79: yes | AP79: v3_2026-03-19
A80: Q16_D | B80: 16 | C80: 16 | D80: Core | E80: 1.05 | F80: ConflictRepair | G80: CommunicationHealth | I80: D | J80: D | K80: I stop bringing things up. If they don't want me, I'm not going to beg to be understood. I've played that game before. | L80: 6 | M80: 7 | N80: 4 | O80: 4 | P80: 4 | Q80: Fixer | R80: 5 | U80: 0 | V80: masc:-0.4;fem:2.0 | W80: -0.4 | X80: 2 | Y80: COMM_Emotional | Z80: REG_CoRegulator | AA80: LANG_Service | AB80: Affection_Mismatch , Independence_Collision | AC80: Affection_Mismatch | AD80: Independence_Collision | AE80: 9 | AF80: resigned caregiver | AG80: silent surrender | AH80: 1.2 | AI80: yes | AJ80: no | AK80: yes | AL80: yes | AP80: v3_2026-03-19
A81: Q16_E | B81: 16 | C81: 16 | D81: Core | E81: 1.05 | F81: ConflictRepair | G81: CommunicationHealth | I81: E | J81: E | K81: I tell myself it's probably just stress or a bad week. I don't want to give up too early, but it's hard not to notice when it shifts. | L81: 7 | M81: 8 | N81: 6 | O81: 6 | P81: 4 | Q81: Romantic Idealist | R81: 6 | U81: 0 | V81: masc:-0.4;fem:1.5 | W81: -0.4 | X81: 1.5 | Y81: COMM_Emotional | Z81: REG_Distractor | AA81: LANG_Gifts | AE81: 0 | AF81: tired hope | AG81: cautious optimist | AH81: 0 | AI81: no | AJ81: no | AK81: yes | AL81: yes | AP81: v3_2026-03-19
A82: Q17_A | B82: 17 | C82: 17 | D82: Core | E82: 1.1 | F82: EmotionalRegulation | G82: AttachmentSafety | H82: You're deep in conversation and they suddenly shut down or go quiet. What do you do next? | I82: A | J82: A | K82: I give them space. If they want to talk, they will. If not, I take the hint. | L82: 8 | M82: 8 | N82: 4 | O82: 4 | P82: 0 | Q82: Icebox | R82: 1 | U82: 0 | V82: masc:1.8;fem:-1.6 | W82: 1.8 | X82: -1.6 | Y82: COMM_Avoidant | Z82: REG_Suppressor | AA82: LANG_Time | AE82: 0 | AF82: detached cool | AG82: patient withdrawer | AH82: 1.2 | AI82: no | AJ82: no | AK82: yes | AL82: yes | AP82: v3_2026-03-19
A83: Q17_B | B83: 17 | C83: 17 | D83: Core | E83: 1.1 | F83: EmotionalRegulation | G83: AttachmentSafety | I83: B | J83: B | K83: I immediately think I said something wrong. I start scanning every word trying to figure out what triggered it. | L83: 4 | M83: 5 | N83: 2 | O83: 2 | P83: 2 | Q83: Analyzer | R83: 2 | U83: 0 | V83: masc:1.4;fem:0.1 | W83: 1.4 | X83: 0.1 | Y83: COMM_Logical | Z83: REG_SelfSoother | AA83: LANG_Service | AB83: Vulnerability_Loop | AC83: Vulnerability_Loop | AE83: 5 | AF83: inner spiral | AG83: self-blamer | AH83: 0 | AI83: yes | AJ83: no | AK83: yes | AL83: yes | AP83: v3_2026-03-19
A84: Q17_C | B84: 17 | C84: 17 | D84: Core | E84: 1.1 | F84: EmotionalRegulation | G84: AttachmentSafety | I84: C | J84: C | K84: I'll ask once. If it's brushed off or ignored, I shift. I'm not the type to sit in someone else's silence for long. | L84: 9 | M84: 9 | N84: 10 | O84: 10 | P84: 10 | Q84: Regulated Grown-Up | R84: 9 | U84: 0 | V84: masc:1.1;fem:0.9 | W84: 1.1 | X84: 0.9 | Y84: COMM_Direct | Z84: REG_CoRegulator | AA84: LANG_Words | AE84: 0 | AF84: direct with boundaries | AG84: firm line-setter | AH84: 0 | AI84: no | AJ84: no | AK84: yes | AL84: yes | AP84: v3_2026-03-19
A85: Q17_D | B85: 17 | C85: 17 | D85: Core | E85: 1.1 | F85: EmotionalRegulation | G85: AttachmentSafety | I85: D | J85: D | K85: I try to keep the mood up, shift the subject, make it feel less tense, even if I'm freaking out a little inside. | L85: 6 | M85: 7 | N85: 4 | O85: 4 | P85: 2 | Q85: Performer | R85: 7 | U85: 0 | V85: masc:0.3;fem:0.5 | W85: 0.3 | X85: 0.5 | Y85: COMM_Indirect | Z85: REG_Distractor | AA85: LANG_Gifts | AB85: Vulnerability_Loop | AC85: Vulnerability_Loop | AE85: 5 | AF85: smooth cover-up | AG85: tension diffuser | AH85: 0 | AI85: yes | AJ85: no | AK85: yes | AL85: yes | AP85: v3_2026-03-19
A86: Q17_E | B86: 17 | C86: 17 | D86: Core | E86: 1.1 | F86: EmotionalRegulation | G86: AttachmentSafety | I86: E | J86: E | K86: I feel it, but I don't say anything. I stay present, hoping they'll come back to me on their own. | L86: 6 | M86: 6 | N86: 4 | O86: 4 | P86: 4 | Q86: Translator | R86: 3 | U86: 0 | V86: masc:-0.1;fem:1.6 | W86: -0.1 | X86: 1.6 | Y86: COMM_Indirect | Z86: REG_CoRegulator | AA86: LANG_Words | AB86: Vulnerability_Loop | AC86: Vulnerability_Loop | AE86: 5 | AF86: gentle waiter | AG86: silent holder | AH86: 0.6 | AI86: yes | AJ86: no | AK86: yes | AL86: yes | AP86: v3_2026-03-19
A87: Q18_A | B87: 18 | C87: 18 | D87: Core | E87: 1.1 | F87: EmotionalRegulation | G87: AttachmentSafety | H87: They open up to you-then start pulling back. No explanation, just distance. What do you do with that shift? | I87: A | J87: A | K87: I match the energy. You pull back? I pull back faster. I've learned not to chase clarity from people who hide when it gets real. | L87: 7 | M87: 8 | N87: 4 | O87: 4 | P87: 0 | Q87: Icebox | R87: 1 | U87: 0 | V87: masc:1.8;fem:-1.6 | W87: 1.8 | X87: -1.6 | Y87: COMM_Avoidant | Z87: REG_Suppressor | AA87: LANG_Time | AE87: 0 | AF87: fast mirror exit | AG87: decisive mirror | AH87: 0.8 | AI87: no | AJ87: no | AK87: yes | AL87: yes | AP87: v3_2026-03-19
A88: Q18_B | B88: 18 | C88: 18 | D88: Core | E88: 1.1 | F88: EmotionalRegulation | G88: AttachmentSafety | I88: B | J88: B | K88: I start thinking I pushed too far. I replay the moment, wondering what I said that made them go quiet. It usually ends with me blaming myself. | L88: 4 | M88: 5 | N88: 2 | O88: 2 | P88: 2 | Q88: Analyzer | R88: 2 | U88: 0 | V88: masc:1.4;fem:0.1 | W88: 1.4 | X88: 0.1 | Y88: COMM_Logical | Z88: REG_SelfSoother | AA88: LANG_Service | AB88: Vulnerability_Loop | AC88: Vulnerability_Loop | AE88: 5 | AF88: shame loop | AG88: self-blamer | AH88: 0 | AI88: yes | AJ88: no | AK88: yes | AL88: yes | AP88: v3_2026-03-19
A89: Q18_C | B89: 18 | C89: 18 | D89: Core | E89: 1.1 | F89: EmotionalRegulation | G89: AttachmentSafety | I89: C | J89: C | K89: I wait. Sometimes people get scared when they feel seen, I don't want to add pressure, but I definitely notice the change. | L89: 7 | M89: 8 | N89: 6 | O89: 6 | P89: 4 | Q89: Romantic Idealist | R89: 6 | U89: 0 | V89: masc:-0.4;fem:1.5 | W89: -0.4 | X89: 1.5 | Y89: COMM_Emotional | Z89: REG_Distractor | AA89: LANG_Gifts | AE89: 0 | AF89: patient rationalizer | AG89: hopeful waiter | AH89: 0 | AI89: no | AJ89: no | AK89: yes | AL89: yes | AP89: v3_2026-03-19
A90: Q18_D | B90: 18 | C90: 18 | D90: Core | E90: 1.1 | F90: EmotionalRegulation | G90: AttachmentSafety | I90: D | J90: D | K90: I go into fix-it mode. Check in more. Try to feel lighter, easier, more fun, anything to bring us back to how it felt before. | L90: 5 | M90: 6 | N90: 4 | O90: 4 | P90: 4 | Q90: Fixer | R90: 5 | U90: 0 | V90: masc:-0.4;fem:2.0 | W90: -0.4 | X90: 2 | Y90: COMM_Emotional | Z90: REG_CoRegulator | AA90: LANG_Service | AB90: Vulnerability_Loop | AC90: Vulnerability_Loop | AE90: 5 | AF90: emotional reset attempt | AG90: overcompensator | AH90: 0 | AI90: yes | AJ90: no | AK90: yes | AL90: yes | AP90: v3_2026-03-19
A91: Q18_E | B91: 18 | C91: 18 | D91: Core | E91: 1.1 | F91: EmotionalRegulation | G91: AttachmentSafety | I91: E | J91: E | K91: I make myself busy. I don't ask, I don't chase. But I clock it. I'll still be polite, but they won't get the same version of me again. | L91: 7 | M91: 8 | N91: 4 | O91: 4 | P91: 0 | Q91: Quiet Exit | R91: 4 | U91: 0 | V91: masc:1.4;fem:-1.3 | W91: 1.4 | X91: -1.3 | Y91: COMM_Avoidant | Z91: REG_Suppressor | AA91: LANG_Time | AE91: 0 | AF91: soft lockdown | AG91: guarded exit | AH91: 0 | AI91: no | AJ91: no | AK91: yes | AL91: yes | AP91: v3_2026-03-19
A92: Q19_A | B92: 19 | C92: 19 | D92: Core | E92: 1.1 | F92: EmotionalRegulation | G92: AttachmentSafety | H92: You're starting to really like them. But they haven't asked much about you. How do you handle that imbalance? | I92: A | J92: A | K92: I clock it. If they're not curious, they're not serious. I don't make speeches, I just start pulling back and let them figure it out. | L92: 8 | M92: 9 | N92: 4 | O92: 6 | P92: 2 | Q92: Icebox | R92: 1 | U92: 0 | V92: masc:1.8;fem:-1.6 | W92: 1.8 | X92: -1.6 | Y92: COMM_Avoidant | Z92: REG_Suppressor | AA92: LANG_Time | AE92: 0 | AF92: quiet disengagement | AG92: measured pullback | AH92: 0 | AI92: no | AJ92: no | AK92: yes | AL92: yes | AP92: v3_2026-03-19
A93: Q19_B | B93: 19 | C93: 19 | D93: Core | E93: 1.1 | F93: EmotionalRegulation | G93: AttachmentSafety | I93: B | J93: B | K93: I start telling little stories about myself anyway, hoping they'll finally ask more. When they don't, it stings more than I let on. | L93: 5 | M93: 6 | N93: 2 | O93: 2 | P93: 0 | Q93: Phantom Seeker | R93: 10 | U93: 0 | V93: masc:-0.2;fem:1.5 | W93: -0.2 | X93: 1.5 | Y93: COMM_Emotional | Z93: REG_SelfSoother | AA93: LANG_Touch | AB93: Scorekeeping_Echo | AC93: Scorekeeping_Echo | AE93: 8 | AF93: indirect yearning | AG93: subtle tester | AH93: 0.2 | AI93: yes | AJ93: no | AK93: yes | AL93: yes | AP93: v3_2026-03-19
A94: Q19_C | B94: 19 | C94: 19 | D94: Core | E94: 1.1 | F94: EmotionalRegulation | G94: AttachmentSafety | I94: C | J94: C | K94: I keep the conversation going but note the pattern. If it keeps feeling one-sided, I stop investing. Curiosity should go both ways. | L94: 7 | M94: 8 | N94: 6 | O94: 8 | P94: 6 | Q94: Analyzer | R94: 2 | U94: 0 | V94: masc:1.4;fem:0.1 | W94: 1.4 | X94: 0.1 | Y94: COMM_Logical | Z94: REG_SelfSoother | AA94: LANG_Service | AE94: 0 | AF94: measured monitoring | AG94: balanced assessor | AH94: 0 | AI94: no | AJ94: no | AK94: yes | AL94: yes | AP94: v3_2026-03-19
A95: Q19_D | B95: 19 | C95: 19 | D95: Core | E95: 1.1 | F95: EmotionalRegulation | G95: AttachmentSafety | I95: D | J95: D | K95: I assume I'm just too much or not interesting enough. So I shrink a little. Try to be easier to be around, maybe then they'll lean in. | L95: 4 | M95: 5 | N95: 2 | O95: 2 | P95: 2 | Q95: Fixer | R95: 5 | U95: 0 | V95: masc:-0.4;fem:2.0 | W95: -0.4 | X95: 2 | Y95: COMM_Emotional | Z95: REG_CoRegulator | AA95: LANG_Service | AB95: Commitment_Ambiguity | AC95: Commitment_Ambiguity | AE95: 5 | AF95: self-dimming | AG95: self-minimizer | AH95: 0 | AI95: yes | AJ95: no | AK95: yes | AL95: yes | AP95: v3_2026-03-19
A96: Q19_E | B96: 19 | C96: 19 | D96: Core | E96: 1.1 | F96: EmotionalRegulation | G96: AttachmentSafety | I96: E | J96: E | K96: If they're not asking, I stop sharing. It's not rejection, it's just proof they're not where I am. That tells me all I need to know. | L96: 9 | M96: 9 | N96: 10 | O96: 10 | P96: 10 | Q96: Regulated Grown-Up | R96: 9 | U96: 0 | V96: masc:1.1;fem:0.9 | W96: 1.1 | X96: 0.9 | Y96: COMM_Direct | Z96: REG_CoRegulator | AA96: LANG_Words | AE96: 0 | AF96: blunt boundary recognition | AG96: decisive assessor | AH96: 0 | AI96: no | AJ96: no | AK96: yes | AL96: yes | AP96: v3_2026-03-19
A97: Q20_A | B97: 20 | C97: 20 | D97: Core | E97: 1.1 | F97: EmotionalRegulation | G97: AttachmentSafety | H97: They say they're "just not ready for anything serious," but keep texting, flirting, and staying close. What do you do with that? | I97: A | J97: A | K97: I don't chase maybes. If you're not ready, I'm not holding space hoping you'll get there. I move different after that. | L97: 9 | M97: 9 | N97: 10 | O97: 10 | P97: 10 | Q97: Regulated Grown-Up | R97: 9 | U97: 0 | V97: masc:1.1;fem:0.9 | W97: 1.1 | X97: 0.9 | Y97: COMM_Direct | Z97: REG_CoRegulator | AA97: LANG_Words | AE97: 0 | AF97: emotional detachment with clarity | AG97: clean exit | AH97: 0.2 | AI97: no | AJ97: no | AK97: yes | AL97: yes | AP97: v3_2026-03-19
A98: Q20_B | B98: 20 | C98: 20 | D98: Core | E98: 1.1 | F98: EmotionalRegulation | G98: AttachmentSafety | I98: B | J98: B | K98: I downplay what I want. I'd rather keep them close than scare them off. I tell myself maybe they'll change their mind. | L98: 4 | M98: 5 | N98: 0 | O98: 2 | P98: 0 | Q98: Phantom Seeker | R98: 10 | U98: 0 | V98: masc:-0.2;fem:1.5 | W98: -0.2 | X98: 1.5 | Y98: COMM_Emotional | Z98: REG_SelfSoother | AA98: LANG_Touch | AB98: Commitment_Ambiguity | AC98: Commitment_Ambiguity | AE98: 5 | AF98: self-silencing attachment | AG98: avoidant hope | AH98: 0.6 | AI98: yes | AJ98: no | AK98: yes | AL98: yes | AP98: v3_2026-03-19
A99: Q20_C | B99: 20 | C99: 20 | D99: Core | E99: 1.1 | F99: EmotionalRegulation | G99: AttachmentSafety | I99: C | J99: C | K99: I lean into the attention while it's there, but I'm already preparing for them to dip. I know how this story ends, I just don't rush it. | L99: 6 | M99: 7 | N99: 2 | O99: 2 | P99: 0 | Q99: Icebox | R99: 1 | U99: 0 | V99: masc:1.8;fem:-1.6 | W99: 1.8 | X99: -1.6 | Y99: COMM_Avoidant | Z99: REG_Suppressor | AA99: LANG_Time | AE99: 0 | AF99: detached indulgence | AG99: slow detacher | AH99: 1.2 | AI99: no | AJ99: no | AK99: yes | AL99: yes | AP99: v3_2026-03-19
A100: Q20_D | B100: 20 | C100: 20 | D100: Core | E100: 1.1 | F100: EmotionalRegulation | G100: AttachmentSafety | I100: D | J100: D | K100: I start fixing it in my head. Maybe if I give it time, make things feel safer, they'll realize what we have. It's not manipulation, it's belief. | L100: 5 | M100: 6 | N100: 4 | O100: 4 | P100: 4 | Q100: Fixer | R100: 5 | U100: 0 | V100: masc:-0.4;fem:2.0 | W100: -0.4 | X100: 2 | Y100: COMM_Emotional | Z100: REG_CoRegulator | AA100: LANG_Service | AB100: Commitment_Ambiguity | AC100: Commitment_Ambiguity | AE100: 5 | AF100: subtle persuasion loop | AG100: hopeful fixer | AH100: 0.2 | AI100: yes | AJ100: no | AK100: yes | AL100: yes | AP100: v3_2026-03-19
...

Sheet QuestionWeights_v4
A1: q | B1: phase | C1: question_weight
A2: 1 | B2: Core | C2: 1
A3: 2 | B3: Core | C3: 1
A4: 3 | B4: Core | C4: 1
A5: 4 | B5: Core | C5: 1
A6: 5 | B6: Core | C6: 1
A7: 6 | B7: Core | C7: 1
A8: 7 | B8: Core | C8: 1
A9: 8 | B9: Core | C9: 1
A10: 9 | B10: Core | C10: 1.05
A11: 10 | B11: Core | C11: 1.05
A12: 11 | B12: Core | C12: 1.05
A13: 12 | B13: Core | C13: 1.05
... A61: 60 | B61: Shadow | C61: 1.35

Sheet ArchetypeLookup_v4
A1: pair_key | B1: score_2_9
A2: ANALYZER|ANALYZER | B2: 7
A3: ANALYZER|FIXER | B3: 6
A4: ANALYZER|ICEBOX | B4: 5
A5: ANALYZER|PHANTOM | B5: 4
A6: ANALYZER|QUIETEXIT | B6: 6
A7: ANALYZER|REGULATED | B7: 8
A8: ANALYZER|ROMANTIC | B8: 5
A9: ANALYZER|PERFORMER | B9: 4
A10: ANALYZER|SURVIVOR | B10: 6
A11: ANALYZER|TRANSLATOR | B11: 7
A12: FIXER|ANALYZER | B12: 6
A13: FIXER|FIXER | B13: 7
... A101: TRANSLATOR|TRANSLATOR | B101: 8

Sheet ShadowLookup_v4
A1: pair_key | B1: score_2_6
A2: MANIPULATOR_MANIPULATOR | B2: 3
A3: MANIPULATOR_STONEWALLER | B3: 2
A4: LOVEBOMBER_MANIPULATOR | B4: 2
A5: CHAMELEON_MANIPULATOR | B5: 2
A6: MANIPULATOR_SCOREKEEPER | B6: 2
A7: MANIPULATOR_SELFSABOTEUR | B7: 3
A8: MANIPULATOR_STONEWALLER | B8: 2
A9: STONEWALLER_STONEWALLER | B9: 4
A10: LOVEBOMBER_STONEWALLER | B10: 2
A11: CHAMELEON_STONEWALLER | B11: 4
A12: SCOREKEEPER_STONEWALLER | B12: 3
A13: SELFSABOTEUR_STONEWALLER | B13: 3
... A37: SELFSABOTEUR_SELFSABOTEUR | B37: 4

Sheet AstrologyLookup_v4
A1: pair_key | B1: score_1_10
A2: AR_M+AR_F | B2: 6
A3: AR_M+LI_F | B3: 7
A4: AR_M+TA_F | B4: 7
A5: AR_M+VI_F | B5: 6
A6: AR_M+SC_F | B6: 5
A7: AR_M+CA_F | B7: 4
A8: AR_M+GE_F | B8: 5
A9: AR_M+LE_F | B9: 8
A10: AR_M+CP_F | B10: 4
A11: AR_M+SG_F | B11: 6
A12: TA_M+TA_F | B12: 6
A13: AR_M+AQ_F | B13: 6
... A577: PI_F+CA_F | B577: 6

Sheet NumerologyLookup_v4
A1: pair_key | B1: score_1_10 | C1: weight_points
A2: 1+2 | B2: 6 | C2: 30
A3: 1+1 | B3: 7 | C3: 30
A4: 1+5 | B4: 9 | C4: 30
A5: 1+3 | B5: 6 | C5: 30
A6: 1+8 | B6: 6 | C6: 30
A7: 1+11 | B7: 6 | C7: 30
A8: 1+6 | B8: 6 | C8: 30
A9: 1+7 | B9: 8 | C9: 30
A10: 1+4 | B10: 6 | C10: 30
A11: 1+9 | B11: 8 | C11: 30
A12: 2+3 | B12: 6 | C12: 30
A13: 2+2 | B13: 7 | C13: 30
... A67: 9+22 | B67: 10 | C67: 30

Sheet CommLookup_v4
A1: pair_key | B1: score_1_10
A2: COMM_Avoidant+COMM_Direct | B2: 3
A3: COMM_Direct+COMM_Emotional | B3: 6
A4: COMM_Direct+COMM_Direct | B4: 8
A5: COMM_Avoidant+COMM_Emotional | B5: 5
A6: COMM_Avoidant+COMM_Avoidant | B6: 2
A7: COMM_Avoidant+COMM_Indirect | B7: 7
A8: COMM_Direct+COMM_Indirect | B8: 4
A9: COMM_Avoidant+COMM_Logical | B9: 6
A10: COMM_Direct+COMM_Logical | B10: 9
A11: COMM_Emotional+COMM_Emotional | B11: 7
A12: COMM_Emotional+COMM_Indirect | B12: 6
A13: COMM_Indirect+COMM_Logical | B13: 6
... A16: COMM_Indirect+COMM_Indirect | B16: 5

Sheet RegLookup_v4
A1: pair_key | B1: score_1_10
A2: REG_CoRegulator+REG_SelfSoother | B2: 10
A3: REG_Distractor+REG_SelfSoother | B3: 7
A4: REG_SelfSoother+REG_SelfSoother | B4: 8
A5: REG_Suppressor+REG_Suppressor | B5: 3
A6: REG_CoRegulator+REG_Distractor | B6: 6
A7: REG_Distractor+REG_Suppressor | B7: 4
A8: REG_CoRegulator+REG_CoRegulator | B8: 9
A9: REG_Distractor+REG_Distractor | B9: 7
A10: REG_SelfSoother+REG_Suppressor | B10: 6
A11: REG_CoRegulator+REG_Suppressor | B11: 5

Sheet LoveLookup_v4
A1: pair_key | B1: score_1_10
A2: LANG_Time+LANG_Touch | B2: 8
A3: LANG_Gifts+LANG_Words | B3: 6
A4: LANG_Time+LANG_Words | B4: 8
A5: LANG_Words+LANG_Words | B5: 9
A6: LANG_Gifts+LANG_Time | B6: 6
A7: LANG_Service+LANG_Time | B7: 9
A8: LANG_Touch+LANG_Words | B8: 7
A9: LANG_Gifts+LANG_Gifts | B9: 7
A10: LANG_Time+LANG_Time | B10: 10
A11: LANG_Service+LANG_Words | B11: 7
A12: LANG_Touch+LANG_Touch | B12: 9
A13: LANG_Gifts+LANG_Service | B13: 5
... A16: LANG_Service+LANG_Service | B16: 9

Sheet InteractionRules_v4
A1: rule_id | B1: source_type | C1: source_value | D1: target_type | E1: target_value | F1: pair_effect | G1: compatibility_modifier | H1: forecast_modifier | I1: source
A2: R1 | B2: archetype | C2: Analyzer | D2: shadow | E2: Stonewaller | F2: clarity pursuit meets withholding -> escalation | G2: -18 | H2: -12 | I2: Blueprint example
A3: R2 | B3: archetype | C3: Fixer | D3: archetype | E3: Survivor | F3: caretaker-protection dynamic; healing but imbalance risk | G3: 10 | H3: -4 | I3: Blueprint example
A4: R3 | B4: archetype | C4: Romantic Idealist | D4: archetype | E4: Performer | F4: spark + affirmation loop; fantasy amplification | G4: 12 | H4: -10 | I4: Blueprint example
A5: R4 | B5: archetype | C5: Translator | D5: archetype | E5: Regulated Grown-Up | F5: strong repair capacity + emotional translation | G5: 18 | H5: 12 | I5: Blueprint example
A6: R5 | F6: (add rules here) | G6: 0 | H6: 0 | I6: Editable

Sheet AstroSignMap_v4
A1: sun_sign | B1: abbr
A2: aries | B2: AR
A3: taurus | B3: TA
A4: gemini | B4: GE
A5: cancer | B5: CA
A6: leo | B6: LE
A7: virgo | B7: VI
A8: libra | B8: LI
A9: scorpio | B9: SC
A10: sagittarius | B10: SG
A11: capricorn | B11: CP
A12: aquarius | B12: AQ
A13: pisces | B13: PI

Sheet TestHarness_v4
A1: Test Harness (enter answer_id for each question)
A3: User A | F3: User B
A4: Gender (M/F) | B4: M | F4: Gender (M/F) | G4: F
A5: Sun sign (lowercase) | B5: aries | F5: Sun sign (lowercase) | G5: libra
A6: Life Path | B6: 1 | F6: Life Path | G6: 6
A9: q | B9: w_q | C9: dimension | D9: answer_id_A | E9: answer_id_B | F9: cA | G9: rA | H9: fA | I9: cpA | J9: cB | K9: rB | L9: fB | M9: cpB | N9: match | O9: quality | P9: pair_q | Q9: readinessContrA | R9: readinessContrB | S9: clusterA | T9: clusterB
A10: 1 | B10: =VLOOKUP(A10,QuestionWeights_v4!$A$2:$C$61,3,FALSE) | C10: =IFERROR(VLOOKUP(D10,AnswerBank_v5!$A$2:$AP$311,6,FALSE),"") | F10: =IFERROR(VLOOKUP(D10,AnswerBank_v5!$A$2:$AP$311,15,FALSE)/10,"") | G10: =IFERROR(VLOOKUP(D10,AnswerBank_v5!$A$2:$AP$311,14,FALSE)/10,"") | H10: =IFERROR(VLOOKUP(D10,AnswerBank_v5!$A$2:$AP$311,16,FALSE)/10,"") | I10: =IFERROR(VLOOKUP(D10,AnswerBank_v5!$A$2:$AP$311,31,FALSE),0) | J10: =IFERROR(VLOOKUP(E10,AnswerBank_v5!$A$2:$AP$311,15,FALSE)/10,"") | K10: =IFERROR(VLOOKUP(E10,AnswerBank_v5!$A$2:$AP$311,14,FALSE)/10,"") | L10: =IFERROR(VLOOKUP(E10,AnswerBank_v5!$A$2:$AP$311,16,FALSE)/10,"") | M10: =IFERROR(VLOOKUP(E10,AnswerBank_v5!$A$2:$AP$311,31,FALSE),0) | N10: =IF(OR(F10="",J10=""),"",1-ABS(F10-J10)) | O10: =IF(OR(G10="",K10="",H10="",L10=""),"",0.6+0.2*((G10+K10)/2)+0.2*((H10+L10)/2)) | P10: =IF(OR(B10="",N10="",O10=""),"",B10*N10*O10) | Q10: =IF(B10="", "", B10*(0.5*G10+0.2*H10+0.2*F10+0.1*(1-I10/25))) | R10: =IF(B10="", "", B10*(0.5*K10+0.2*L10+0.2*J10+0.1*(1-M10/25))) | S10: =IFERROR(VLOOKUP(D10,AnswerBank_v5!$A$2:$AP$311,29,FALSE),"") | T10: =IFERROR(VLOOKUP(E10,AnswerBank_v5!$A$2:$AP$311,29,FALSE),"")
A11: 2 | B11: =VLOOKUP(A11,QuestionWeights_v4!$A$2:$C$61,3,FALSE) | C11: =IFERROR(VLOOKUP(D11,AnswerBank_v5!$A$2:$AP$311,6,FALSE),"") | F11: =IFERROR(VLOOKUP(D11,AnswerBank_v5!$A$2:$AP$311,15,FALSE)/10,"") | G11: =IFERROR(VLOOKUP(D11,AnswerBank_v5!$A$2:$AP$311,14,FALSE)/10,"") | H11: =IFERROR(VLOOKUP(D11,AnswerBank_v5!$A$2:$AP$311,16,FALSE)/10,"") | I11: =IFERROR(VLOOKUP(D11,AnswerBank_v5!$A$2:$AP$311,31,FALSE),0) | J11: =IFERROR(VLOOKUP(E11,AnswerBank_v5!$A$2:$AP$311,15,FALSE)/10,"") | K11: =IFERROR(VLOOKUP(E11,AnswerBank_v5!$A$2:$AP$311,14,FALSE)/10,"") | L11: =IFERROR(VLOOKUP(E11,AnswerBank_v5!$A$2:$AP$311,16,FALSE)/10,"") | M11: =IFERROR(VLOOKUP(E11,AnswerBank_v5!$A$2:$AP$311,31,FALSE),0) | N11: =IF(OR(F11="",J11=""),"",1-ABS(F11-J11)) | O11: =IF(OR(G11="",K11="",H11="",L11=""),"",0.6+0.2*((G11+K11)/2)+0.2*((H11+L11)/2)) | P11: =IF(OR(B11="",N11="",O11=""),"",B11*N11*O11) | Q11: =IF(B11="", "", B11*(0.5*G11+0.2*H11+0.2*F11+0.1*(1-I11/25))) | R11: =IF(B11="", "", B11*(0.5*K11+0.2*L11+0.2*J11+0.1*(1-M11/25))) | S11: =IFERROR(VLOOKUP(D11,AnswerBank_v5!$A$2:$AP$311,29,FALSE),"") | T11: =IFERROR(VLOOKUP(E11,AnswerBank_v5!$A$2:$AP$311,29,FALSE),"")
A12: 3 | B12: =VLOOKUP(A12,QuestionWeights_v4!$A$2:$C$61,3,FALSE) | C12: =IFERROR(VLOOKUP(D12,AnswerBank_v5!$A$2:$AP$311,6,FALSE),"") | F12: =IFERROR(VLOOKUP(D12,AnswerBank_v5!$A$2:$AP$311,15,FALSE)/10,"") | G12: =IFERROR(VLOOKUP(D12,AnswerBank_v5!$A$2:$AP$311,14,FALSE)/10,"") | H12: =IFERROR(VLOOKUP(D12,AnswerBank_v5!$A$2:$AP$311,16,FALSE)/10,"") | I12: =IFERROR(VLOOKUP(D12,AnswerBank_v5!$A$2:$AP$311,31,FALSE),0) | J12: =IFERROR(VLOOKUP(E12,AnswerBank_v5!$A$2:$AP$311,15,FALSE)/10,"") | K12: =IFERROR(VLOOKUP(E12,AnswerBank_v5!$A$2:$AP$311,14,FALSE)/10,"") | L12: =IFERROR(VLOOKUP(E12,AnswerBank_v5!$A$2:$AP$311,16,FALSE)/10,"") | M12: =IFERROR(VLOOKUP(E12,AnswerBank_v5!$A$2:$AP$311,31,FALSE),0) | N12: =IF(OR(F12="",J12=""),"",1-ABS(F12-J12)) | O12: =IF(OR(G12="",K12="",H12="",L12=""),"",0.6+0.2*((G12+K12)/2)+0.2*((H12+L12)/2)) | P12: =IF(OR(B12="",N12="",O12=""),"",B12*N12*O12) | Q12: =IF(B12="", "", B12*(0.5*G12+0.2*H12+0.2*F12+0.1*(1-I12/25))) | R12: =IF(B12="", "", B12*(0.5*K12+0.2*L12+0.2*J12+0.1*(1-M12/25))) | S12: =IFERROR(VLOOKUP(D12,AnswerBank_v5!$A$2:$AP$311,29,FALSE),"") | T12: =IFERROR(VLOOKUP(E12,AnswerBank_v5!$A$2:$AP$311,29,FALSE),"")
A13: 4 | B13: =VLOOKUP(A13,QuestionWeights_v4!$A$2:$C$61,3,FALSE) | C13: =IFERROR(VLOOKUP(D13,AnswerBank_v5!$A$2:$AP$311,6,FALSE),"") | F13: =IFERROR(VLOOKUP(D13,AnswerBank_v5!$A$2:$AP$311,15,FALSE)/10,"") | G13: =IFERROR(VLOOKUP(D13,AnswerBank_v5!$A$2:$AP$311,14,FALSE)/10,"") | H13: =IFERROR(VLOOKUP(D13,AnswerBank_v5!$A$2:$AP$311,16,FALSE)/10,"") | I13: =IFERROR(VLOOKUP(D13,AnswerBank_v5!$A$2:$AP$311,31,FALSE),0) | J13: =IFERROR(VLOOKUP(E13,AnswerBank_v5!$A$2:$AP$311,15,FALSE)/10,"") | K13: =IFERROR(VLOOKUP(E13,AnswerBank_v5!$A$2:$AP$311,14,FALSE)/10,"") | L13: =IFERROR(VLOOKUP(E13,AnswerBank_v5!$A$2:$AP$311,16,FALSE)/10,"") | M13: =IFERROR(VLOOKUP(E13,AnswerBank_v5!$A$2:$AP$311,31,FALSE),0) | N13: =IF(OR(F13="",J13=""),"",1-ABS(F13-J13)) | O13: =IF(OR(G13="",K13="",H13="",L13=""),"",0.6+0.2*((G13+K13)/2)+0.2*((H13+L13)/2)) | P13: =IF(OR(B13="",N13="",O13=""),"",B13*N13*O13) | Q13: =IF(B13="", "", B13*(0.5*G13+0.2*H13+0.2*F13+0.1*(1-I13/25))) | R13: =IF(B13="", "", B13*(0.5*K13+0.2*L13+0.2*J13+0.1*(1-M13/25))) | S13: =IFERROR(VLOOKUP(D13,AnswerBank_v5!$A$2:$AP$311,29,FALSE),"") | T13: =IFERROR(VLOOKUP(E13,AnswerBank_v5!$A$2:$AP$311,29,FALSE),"")
A14: 5 | B14: =VLOOKUP(A14,QuestionWeights_v4!$A$2:$C$61,3,FALSE) | C14: =IFERROR(VLOOKUP(D14,AnswerBank_v5!$A$2:$AP$311,6,FALSE),"") | F14: =IFERROR(VLOOKUP(D14,AnswerBank_v5!$A$2:$AP$311,15,FALSE)/10,"") | G14: =IFERROR(VLOOKUP(D14,AnswerBank_v5!$A$2:$AP$311,14,FALSE)/10,"") | H14: =IFERROR(VLOOKUP(D14,AnswerBank_v5!$A$2:$AP$311,16,FALSE)/10,"") | I14: =IFERROR(VLOOKUP(D14,AnswerBank_v5!$A$2:$AP$311,31,FALSE),0) | J14: =IFERROR(VLOOKUP(E14,AnswerBank_v5!$A$2:$AP$311,15,FALSE)/10,"") | K14: =IFERROR(VLOOKUP(E14,AnswerBank_v5!$A$2:$AP$311,14,FALSE)/10,"") | L14: =IFERROR(VLOOKUP(E14,AnswerBank_v5!$A$2:$AP$311,16,FALSE)/10,"") | M14: =IFERROR(VLOOKUP(E14,AnswerBank_v5!$A$2:$AP$311,31,FALSE),0) | N14: =IF(OR(F14="",J14=""),"",1-ABS(F14-J14)) | O14: =IF(OR(G14="",K14="",H14="",L14=""),"",0.6+0.2*((G14+K14)/2)+0.2*((H14+L14)/2)) | P14: =IF(OR(B14="",N14="",O14=""),"",B14*N14*O14) | Q14: =IF(B14="", "", B14*(0.5*G14+0.2*H14+0.2*F14+0.1*(1-I14/25))) | R14: =IF(B14="", "", B14*(0.5*K14+0.2*L14+0.2*J14+0.1*(1-M14/25))) | S14: =IFERROR(VLOOKUP(D14,AnswerBank_v5!$A$2:$AP$311,29,FALSE),"") | T14: =IFERROR(VLOOKUP(E14,AnswerBank_v5!$A$2:$AP$311,29,FALSE),"")
A15: 6 | B15: =VLOOKUP(A15,QuestionWeights_v4!$A$2:$C$61,3,FALSE) | C15: =IFERROR(VLOOKUP(D15,AnswerBank_v5!$A$2:$AP$311,6,FALSE),"") | F15: =IFERROR(VLOOKUP(D15,AnswerBank_v5!$A$2:$AP$311,15,FALSE)/10,"") | G15: =IFERROR(VLOOKUP(D15,AnswerBank_v5!$A$2:$AP$311,14,FALSE)/10,"") | H15: =IFERROR(VLOOKUP(D15,AnswerBank_v5!$A$2:$AP$311,16,FALSE)/10,"") | I15: =IFERROR(VLOOKUP(D15,AnswerBank_v5!$A$2:$AP$311,31,FALSE),0) | J15: =IFERROR(VLOOKUP(E15,AnswerBank_v5!$A$2:$AP$311,15,FALSE)/10,"") | K15: =IFERROR(VLOOKUP(E15,AnswerBank_v5!$A$2:$AP$311,14,FALSE)/10,"") | L15: =IFERROR(VLOOKUP(E15,AnswerBank_v5!$A$2:$AP$311,16,FALSE)/10,"") | M15: =IFERROR(VLOOKUP(E15,AnswerBank_v5!$A$2:$AP$311,31,FALSE),0) | N15: =IF(OR(F15="",J15=""),"",1-ABS(F15-J15)) | O15: =IF(OR(G15="",K15="",H15="",L15=""),"",0.6+0.2*((G15+K15)/2)+0.2*((H15+L15)/2)) | P15: =IF(OR(B15="",N15="",O15=""),"",B15*N15*O15) | Q15: =IF(B15="", "", B15*(0.5*G15+0.2*H15+0.2*F15+0.1*(1-I15/25))) | R15: =IF(B15="", "", B15*(0.5*K15+0.2*L15+0.2*J15+0.1*(1-M15/25))) | S15: =IFERROR(VLOOKUP(D15,AnswerBank_v5!$A$2:$AP$311,29,FALSE),"") | T15: =IFERROR(VLOOKUP(E15,AnswerBank_v5!$A$2:$AP$311,29,FALSE),"")
A16: 7 | B16: =VLOOKUP(A16,QuestionWeights_v4!$A$2:$C$61,3,FALSE) | C16: =IFERROR(VLOOKUP(D16,AnswerBank_v5!$A$2:$AP$311,6,FALSE),"") | F16: =IFERROR(VLOOKUP(D16,AnswerBank_v5!$A$2:$AP$311,15,FALSE)/10,"") | G16: =IFERROR(VLOOKUP(D16,AnswerBank_v5!$A$2:$AP$311,14,FALSE)/10,"") | H16: =IFERROR(VLOOKUP(D16,AnswerBank_v5!$A$2:$AP$311,16,FALSE)/10,"") | I16: =IFERROR(VLOOKUP(D16,AnswerBank_v5!$A$2:$AP$311,31,FALSE),0) | J16: =IFERROR(VLOOKUP(E16,AnswerBank_v5!$A$2:$AP$311,15,FALSE)/10,"") | K16: =IFERROR(VLOOKUP(E16,AnswerBank_v5!$A$2:$AP$311,14,FALSE)/10,"") | L16: =IFERROR(VLOOKUP(E16,AnswerBank_v5!$A$2:$AP$311,16,FALSE)/10,"") | M16: =IFERROR(VLOOKUP(E16,AnswerBank_v5!$A$2:$AP$311,31,FALSE),0) | N16: =IF(OR(F16="",J16=""),"",1-ABS(F16-J16)) | O16: =IF(OR(G16="",K16="",H16="",L16=""),"",0.6+0.2*((G16+K16)/2)+0.2*((H16+L16)/2)) | P16: =IF(OR(B16="",N16="",O16=""),"",B16*N16*O16) | Q16: =IF(B16="", "", B16*(0.5*G16+0.2*H16+0.2*F16+0.1*(1-I16/25))) | R16: =IF(B16="", "", B16*(0.5*K16+0.2*L16+0.2*J16+0.1*(1-M16/25))) | S16: =IFERROR(VLOOKUP(D16,AnswerBank_v5!$A$2:$AP$311,29,FALSE),"") | T16: =IFERROR(VLOOKUP(E16,AnswerBank_v5!$A$2:$AP$311,29,FALSE),"")
A17: 8 | B17: =VLOOKUP(A17,QuestionWeights_v4!$A$2:$C$61,3,FALSE) | C17: =IFERROR(VLOOKUP(D17,AnswerBank_v5!$A$2:$AP$311,6,FALSE),"") | F17: =IFERROR(VLOOKUP(D17,AnswerBank_v5!$A$2:$AP$311,15,FALSE)/10,"") | G17: =IFERROR(VLOOKUP(D17,AnswerBank_v5!$A$2:$AP$311,14,FALSE)/10,"") | H17: =IFERROR(VLOOKUP(D17,AnswerBank_v5!$A$2:$AP$311,16,FALSE)/10,"") | I17: =IFERROR(VLOOKUP(D17,AnswerBank_v5!$A$2:$AP$311,31,FALSE),0) | J17: =IFERROR(VLOOKUP(E17,AnswerBank_v5!$A$2:$AP$311,15,FALSE)/10,"") | K17: =IFERROR(VLOOKUP(E17,AnswerBank_v5!$A$2:$AP$311,14,FALSE)/10,"") | L17: =IFERROR(VLOOKUP(E17,AnswerBank_v5!$A$2:$AP$311,16,FALSE)/10,"") | M17: =IFERROR(VLOOKUP(E17,AnswerBank_v5!$A$2:$AP$311,31,FALSE),0) | N17: =IF(OR(F17="",J17=""),"",1-ABS(F17-J17)) | O17: =IF(OR(G17="",K17="",H17="",L17=""),"",0.6+0.2*((G17+K17)/2)+0.2*((H17+L17)/2)) | P17: =IF(OR(B17="",N17="",O17=""),"",B17*N17*O17) | Q17: =IF(B17="", "", B17*(0.5*G17+0.2*H17+0.2*F17+0.1*(1-I17/25))) | R17: =IF(B17="", "", B17*(0.5*K17+0.2*L17+0.2*J17+0.1*(1-M17/25))) | S17: =IFERROR(VLOOKUP(D17,AnswerBank_v5!$A$2:$AP$311,29,FALSE),"") | T17: =IFERROR(VLOOKUP(E17,AnswerBank_v5!$A$2:$AP$311,29,FALSE),"")
A18: 9 | B18: =VLOOKUP(A18,QuestionWeights_v4!$A$2:$C$61,3,FALSE) | C18: =IFERROR(VLOOKUP(D18,AnswerBank_v5!$A$2:$AP$311,6,FALSE),"") | F18: =IFERROR(VLOOKUP(D18,AnswerBank_v5!$A$2:$AP$311,15,FALSE)/10,"") | G18: =IFERROR(VLOOKUP(D18,AnswerBank_v5!$A$2:$AP$311,14,FALSE)/10,"") | H18: =IFERROR(VLOOKUP(D18,AnswerBank_v5!$A$2:$AP$311,16,FALSE)/10,"") | I18: =IFERROR(VLOOKUP(D18,AnswerBank_v5!$A$2:$AP$311,31,FALSE),0) | J18: =IFERROR(VLOOKUP(E18,AnswerBank_v5!$A$2:$AP$311,15,FALSE)/10,"") | K18: =IFERROR(VLOOKUP(E18,AnswerBank_v5!$A$2:$AP$311,14,FALSE)/10,"") | L18: =IFERROR(VLOOKUP(E18,AnswerBank_v5!$A$2:$AP$311,16,FALSE)/10,"") | M18: =IFERROR(VLOOKUP(E18,AnswerBank_v5!$A$2:$AP$311,31,FALSE),0) | N18: =IF(OR(F18="",J18=""),"",1-ABS(F18-J18)) | O18: =IF(OR(G18="",K18="",H18="",L18=""),"",0.6+0.2*((G18+K18)/2)+0.2*((H18+L18)/2)) | P18: =IF(OR(B18="",N18="",O18=""),"",B18*N18*O18) | Q18: =IF(B18="", "", B18*(0.5*G18+0.2*H18+0.2*F18+0.1*(1-I18/25))) | R18: =IF(B18="", "", B18*(0.5*K18+0.2*L18+0.2*J18+0.1*(1-M18/25))) | S18: =IFERROR(VLOOKUP(D18,AnswerBank_v5!$A$2:$AP$311,29,FALSE),"") | T18: =IFERROR(VLOOKUP(E18,AnswerBank_v5!$A$2:$AP$311,29,FALSE),"")
A19: 10 | B19: =VLOOKUP(A19,QuestionWeights_v4!$A$2:$C$61,3,FALSE) | C19: =IFERROR(VLOOKUP(D19,AnswerBank_v5!$A$2:$AP$311,6,FALSE),"") | F19: =IFERROR(VLOOKUP(D19,AnswerBank_v5!$A$2:$AP$311,15,FALSE)/10,"") | G19: =IFERROR(VLOOKUP(D19,AnswerBank_v5!$A$2:$AP$311,14,FALSE)/10,"") | H19: =IFERROR(VLOOKUP(D19,AnswerBank_v5!$A$2:$AP$311,16,FALSE)/10,"") | I19: =IFERROR(VLOOKUP(D19,AnswerBank_v5!$A$2:$AP$311,31,FALSE),0) | J19: =IFERROR(VLOOKUP(E19,AnswerBank_v5!$A$2:$AP$311,15,FALSE)/10,"") | K19: =IFERROR(VLOOKUP(E19,AnswerBank_v5!$A$2:$AP$311,14,FALSE)/10,"") | L19: =IFERROR(VLOOKUP(E19,AnswerBank_v5!$A$2:$AP$311,16,FALSE)/10,"") | M19: =IFERROR(VLOOKUP(E19,AnswerBank_v5!$A$2:$AP$311,31,FALSE),0) | N19: =IF(OR(F19="",J19=""),"",1-ABS(F19-J19)) | O19: =IF(OR(G19="",K19="",H19="",L19=""),"",0.6+0.2*((G19+K19)/2)+0.2*((H19+L19)/2)) | P19: =IF(OR(B19="",N19="",O19=""),"",B19*N19*O19) | Q19: =IF(B19="", "", B19*(0.5*G19+0.2*H19+0.2*F19+0.1*(1-I19/25))) | R19: =IF(B19="", "", B19*(0.5*K19+0.2*L19+0.2*J19+0.1*(1-M19/25))) | S19: =IFERROR(VLOOKUP(D19,AnswerBank_v5!$A$2:$AP$311,29,FALSE),"") | T19: =IFERROR(VLOOKUP(E19,AnswerBank_v5!$A$2:$AP$311,29,FALSE),"")
A20: 11 | B20: =VLOOKUP(A20,QuestionWeights_v4!$A$2:$C$61,3,FALSE) | C20: =IFERROR(VLOOKUP(D20,AnswerBank_v5!$A$2:$AP$311,6,FALSE),"") | F20: =IFERROR(VLOOKUP(D20,AnswerBank_v5!$A$2:$AP$311,15,FALSE)/10,"") | G20: =IFERROR(VLOOKUP(D20,AnswerBank_v5!$A$2:$AP$311,14,FALSE)/10,"") | H20: =IFERROR(VLOOKUP(D20,AnswerBank_v5!$A$2:$AP$311,16,FALSE)/10,"") | I20: =IFERROR(VLOOKUP(D20,AnswerBank_v5!$A$2:$AP$311,31,FALSE),0) | J20: =IFERROR(VLOOKUP(E20,AnswerBank_v5!$A$2:$AP$311,15,FALSE)/10,"") | K20: =IFERROR(VLOOKUP(E20,AnswerBank_v5!$A$2:$AP$311,14,FALSE)/10,"") | L20: =IFERROR(VLOOKUP(E20,AnswerBank_v5!$A$2:$AP$311,16,FALSE)/10,"") | M20: =IFERROR(VLOOKUP(E20,AnswerBank_v5!$A$2:$AP$311,31,FALSE),0) | N20: =IF(OR(F20="",J20=""),"",1-ABS(F20-J20)) | O20: =IF(OR(G20="",K20="",H20="",L20=""),"",0.6+0.2*((G20+K20)/2)+0.2*((H20+L20)/2)) | P20: =IF(OR(B20="",N20="",O20=""),"",B20*N20*O20) | Q20: =IF(B20="", "", B20*(0.5*G20+0.2*H20+0.2*F20+0.1*(1-I20/25))) | R20: =IF(B20="", "", B20*(0.5*K20+0.2*L20+0.2*J20+0.1*(1-M20/25))) | S20: =IFERROR(VLOOKUP(D20,AnswerBank_v5!$A$2:$AP$311,29,FALSE),"") | T20: =IFERROR(VLOOKUP(E20,AnswerBank_v5!$A$2:$AP$311,29,FALSE),"")
A21: 12 | B21: =VLOOKUP(A21,QuestionWeights_v4!$A$2:$C$61,3,FALSE) | C21: =IFERROR(VLOOKUP(D21,AnswerBank_v5!$A$2:$AP$311,6,FALSE),"") | F21: =IFERROR(VLOOKUP(D21,AnswerBank_v5!$A$2:$AP$311,15,FALSE)/10,"") | G21: =IFERROR(VLOOKUP(D21,AnswerBank_v5!$A$2:$AP$311,14,FALSE)/10,"") | H21: =IFERROR(VLOOKUP(D21,AnswerBank_v5!$A$2:$AP$311,16,FALSE)/10,"") | I21: =IFERROR(VLOOKUP(D21,AnswerBank_v5!$A$2:$AP$311,31,FALSE),0) | J21: =IFERROR(VLOOKUP(E21,AnswerBank_v5!$A$2:$AP$311,15,FALSE)/10,"") | K21: =IFERROR(VLOOKUP(E21,AnswerBank_v5!$A$2:$AP$311,14,FALSE)/10,"") | L21: =IFERROR(VLOOKUP(E21,AnswerBank_v5!$A$2:$AP$311,16,FALSE)/10,"") | M21: =IFERROR(VLOOKUP(E21,AnswerBank_v5!$A$2:$AP$311,31,FALSE),0) | N21: =IF(OR(F21="",J21=""),"",1-ABS(F21-J21)) | O21: =IF(OR(G21="",K21="",H21="",L21=""),"",0.6+0.2*((G21+K21)/2)+0.2*((H21+L21)/2)) | P21: =IF(OR(B21="",N21="",O21=""),"",B21*N21*O21) | Q21: =IF(B21="", "", B21*(0.5*G21+0.2*H21+0.2*F21+0.1*(1-I21/25))) | R21: =IF(B21="", "", B21*(0.5*K21+0.2*L21+0.2*J21+0.1*(1-M21/25))) | S21: =IFERROR(VLOOKUP(D21,AnswerBank_v5!$A$2:$AP$311,29,FALSE),"") | T21: =IFERROR(VLOOKUP(E21,AnswerBank_v5!$A$2:$AP$311,29,FALSE),"")
... A59: 50 | B59: =VLOOKUP(A59,QuestionWeights_v4!$A$2:$C$61,3,FALSE) | C59: =IFERROR(VLOOKUP(D59,AnswerBank_v5!$A$2:$AP$311,6,FALSE),"") | F59: =IFERROR(VLOOKUP(D59,AnswerBank_v5!$A$2:$AP$311,15,FALSE)/10,"") | G59: =IFERROR(VLOOKUP(D59,AnswerBank_v5!$A$2:$AP$311,14,FALSE)/10,"") | H59: =IFERROR(VLOOKUP(D59,AnswerBank_v5!$A$2:$AP$311,16,FALSE)/10,"") | I59: =IFERROR(VLOOKUP(D59,AnswerBank_v5!$A$2:$AP$311,31,FALSE),0) | J59: =IFERROR(VLOOKUP(E59,AnswerBank_v5!$A$2:$AP$311,15,FALSE)/10,"") | K59: =IFERROR(VLOOKUP(E59,AnswerBank_v5!$A$2:$AP$311,14,FALSE)/10,"") | L59: =IFERROR(VLOOKUP(E59,AnswerBank_v5!$A$2:$AP$311,16,FALSE)/10,"") | M59: =IFERROR(VLOOKUP(E59,AnswerBank_v5!$A$2:$AP$311,31,FALSE),0) | N59: =IF(OR(F59="",J59=""),"",1-ABS(F59-J59)) | O59: =IF(OR(G59="",K59="",H59="",L59=""),"",0.6+0.2*((G59+K59)/2)+0.2*((H59+L59)/2)) | P59: =IF(OR(B59="",N59="",O59=""),"",B59*N59*O59) | Q59: =IF(B59="", "", B59*(0.5*G59+0.2*H59+0.2*F59+0.1*(1-I59/25))) | R59: =IF(B59="", "", B59*(0.5*K59+0.2*L59+0.2*J59+0.1*(1-M59/25))) | S59: =IFERROR(VLOOKUP(D59,AnswerBank_v5!$A$2:$AP$311,29,FALSE),"") | T59: =IFERROR(VLOOKUP(E59,AnswerBank_v5!$A$2:$AP$311,29,FALSE),"")
A61: Summary
A62: TotalWeight | B62: =SUM(B10:B59)
A63: BehaviorCore (0..1) | B63: =0.22*B70+0.2*B71+0.2*B72+0.14*B73+0.12*B74+0.12*B75
A64: Readiness_A (0..100) | B64: =100*SUM(Q10:Q59)/SUM(B10:B59)
A65: Readiness_B (0..100) | B65: =100*SUM(R10:R59)/SUM(B10:B59)
A66: ClusterPenaltySum_A | B66: =SUM(I10:I59)
A67: ClusterPenaltySum_B | B67: =SUM(M10:M59)
A69: Dimension | B69: Score (0..1)
A70: CommunicationHealth | B70: =IFERROR(SUMIF($C$10:$C$59,A70,$P$10:$P$59)/SUMIF($C$10:$C$59,A70,$B$10:$B$59),0)
A71: ConflictRepair | B71: =IFERROR(SUMIF($C$10:$C$59,A71,$P$10:$P$59)/SUMIF($C$10:$C$59,A71,$B$10:$B$59),0) | C71: answer_id_B | D71: shadowRiskA | E71: integrityA | F71: shadowTypeA | G71: shadowRiskB | H71: integrityB | I71: shadowTypeB
A72: EmotionalRegulation | B72: =IFERROR(SUMIF($C$10:$C$59,A72,$P$10:$P$59)/SUMIF($C$10:$C$59,A72,$B$10:$B$59),0) | D72: =IFERROR(VLOOKUP(B72,AnswerBank_v5!$A$2:$AP$311,21,FALSE)/10,0) | E72: =IFERROR(VLOOKUP(B72,AnswerBank_v5!$A$2:$AP$311,36,FALSE),"") | F72: =IFERROR(VLOOKUP(B72,AnswerBank_v5!$A$2:$AP$311,19,FALSE),"") | G72: =IFERROR(VLOOKUP(C72,AnswerBank_v5!$A$2:$AP$311,21,FALSE)/10,0) | H72: =IFERROR(VLOOKUP(C72,AnswerBank_v5!$A$2:$AP$311,36,FALSE),"") | I72: =IFERROR(VLOOKUP(C72,AnswerBank_v5!$A$2:$AP$311,19,FALSE),"")
A73: ValuesLifestyle | B73: =IFERROR(SUMIF($C$10:$C$59,A73,$P$10:$P$59)/SUMIF($C$10:$C$59,A73,$B$10:$B$59),0) | D73: =IFERROR(VLOOKUP(B73,AnswerBank_v5!$A$2:$AP$311,21,FALSE)/10,0) | E73: =IFERROR(VLOOKUP(B73,AnswerBank_v5!$A$2:$AP$311,36,FALSE),"") | F73: =IFERROR(VLOOKUP(B73,AnswerBank_v5!$A$2:$AP$311,19,FALSE),"") | G73: =IFERROR(VLOOKUP(C73,AnswerBank_v5!$A$2:$AP$311,21,FALSE)/10,0) | H73: =IFERROR(VLOOKUP(C73,AnswerBank_v5!$A$2:$AP$311,36,FALSE),"") | I73: =IFERROR(VLOOKUP(C73,AnswerBank_v5!$A$2:$AP$311,19,FALSE),"")
A74: CommitmentPace | B74: =IFERROR(SUMIF($C$10:$C$59,A74,$P$10:$P$59)/SUMIF($C$10:$C$59,A74,$B$10:$B$59),0) | D74: =IFERROR(VLOOKUP(B74,AnswerBank_v5!$A$2:$AP$311,21,FALSE)/10,0) | E74: =IFERROR(VLOOKUP(B74,AnswerBank_v5!$A$2:$AP$311,36,FALSE),"") | F74: =IFERROR(VLOOKUP(B74,AnswerBank_v5!$A$2:$AP$311,19,FALSE),"") | G74: =IFERROR(VLOOKUP(C74,AnswerBank_v5!$A$2:$AP$311,21,FALSE)/10,0) | H74: =IFERROR(VLOOKUP(C74,AnswerBank_v5!$A$2:$AP$311,36,FALSE),"") | I74: =IFERROR(VLOOKUP(C74,AnswerBank_v5!$A$2:$AP$311,19,FALSE),"")
A75: EmotionalNeeds | B75: =IFERROR(SUMIF($C$10:$C$59,A75,$P$10:$P$59)/SUMIF($C$10:$C$59,A75,$B$10:$B$59),0) | D75: =IFERROR(VLOOKUP(B75,AnswerBank_v5!$A$2:$AP$311,21,FALSE)/10,0) | E75: =IFERROR(VLOOKUP(B75,AnswerBank_v5!$A$2:$AP$311,36,FALSE),"") | F75: =IFERROR(VLOOKUP(B75,AnswerBank_v5!$A$2:$AP$311,19,FALSE),"") | G75: =IFERROR(VLOOKUP(C75,AnswerBank_v5!$A$2:$AP$311,21,FALSE)/10,0) | H75: =IFERROR(VLOOKUP(C75,AnswerBank_v5!$A$2:$AP$311,36,FALSE),"") | I75: =IFERROR(VLOOKUP(C75,AnswerBank_v5!$A$2:$AP$311,19,FALSE),"")
A76: 55 | D76: =IFERROR(VLOOKUP(B76,AnswerBank_v5!$A$2:$AP$311,21,FALSE)/10,0) | E76: =IFERROR(VLOOKUP(B76,AnswerBank_v5!$A$2:$AP$311,36,FALSE),"") | F76: =IFERROR(VLOOKUP(B76,AnswerBank_v5!$A$2:$AP$311,19,FALSE),"") | G76: =IFERROR(VLOOKUP(C76,AnswerBank_v5!$A$2:$AP$311,21,FALSE)/10,0) | H76: =IFERROR(VLOOKUP(C76,AnswerBank_v5!$A$2:$AP$311,36,FALSE),"") | I76: =IFERROR(VLOOKUP(C76,AnswerBank_v5!$A$2:$AP$311,19,FALSE),"")
A77: 56 | D77: =IFERROR(VLOOKUP(B77,AnswerBank_v5!$A$2:$AP$311,21,FALSE)/10,0) | E77: =IFERROR(VLOOKUP(B77,AnswerBank_v5!$A$2:$AP$311,36,FALSE),"") | F77: =IFERROR(VLOOKUP(B77,AnswerBank_v5!$A$2:$AP$311,19,FALSE),"") | G77: =IFERROR(VLOOKUP(C77,AnswerBank_v5!$A$2:$AP$311,21,FALSE)/10,0) | H77: =IFERROR(VLOOKUP(C77,AnswerBank_v5!$A$2:$AP$311,36,FALSE),"") | I77: =IFERROR(VLOOKUP(C77,AnswerBank_v5!$A$2:$AP$311,19,FALSE),"")
A78: 57 | D78: =IFERROR(VLOOKUP(B78,AnswerBank_v5!$A$2:$AP$311,21,FALSE)/10,0) | E78: =IFERROR(VLOOKUP(B78,AnswerBank_v5!$A$2:$AP$311,36,FALSE),"") | F78: =IFERROR(VLOOKUP(B78,AnswerBank_v5!$A$2:$AP$311,19,FALSE),"") | G78: =IFERROR(VLOOKUP(C78,AnswerBank_v5!$A$2:$AP$311,21,FALSE)/10,0) | H78: =IFERROR(VLOOKUP(C78,AnswerBank_v5!$A$2:$AP$311,36,FALSE),"") | I78: =IFERROR(VLOOKUP(C78,AnswerBank_v5!$A$2:$AP$311,19,FALSE),"")
A79: 58 | D79: =IFERROR(VLOOKUP(B79,AnswerBank_v5!$A$2:$AP$311,21,FALSE)/10,0) | E79: =IFERROR(VLOOKUP(B79,AnswerBank_v5!$A$2:$AP$311,36,FALSE),"") | F79: =IFERROR(VLOOKUP(B79,AnswerBank_v5!$A$2:$AP$311,19,FALSE),"") | G79: =IFERROR(VLOOKUP(C79,AnswerBank_v5!$A$2:$AP$311,21,FALSE)/10,0) | H79: =IFERROR(VLOOKUP(C79,AnswerBank_v5!$A$2:$AP$311,36,FALSE),"") | I79: =IFERROR(VLOOKUP(C79,AnswerBank_v5!$A$2:$AP$311,19,FALSE),"")
A80: 59 | D80: =IFERROR(VLOOKUP(B80,AnswerBank_v5!$A$2:$AP$311,21,FALSE)/10,0) | E80: =IFERROR(VLOOKUP(B80,AnswerBank_v5!$A$2:$AP$311,36,FALSE),"") | F80: =IFERROR(VLOOKUP(B80,AnswerBank_v5!$A$2:$AP$311,19,FALSE),"") | G80: =IFERROR(VLOOKUP(C80,AnswerBank_v5!$A$2:$AP$311,21,FALSE)/10,0) | H80: =IFERROR(VLOOKUP(C80,AnswerBank_v5!$A$2:$AP$311,36,FALSE),"") | I80: =IFERROR(VLOOKUP(C80,AnswerBank_v5!$A$2:$AP$311,19,FALSE),"")
A81: 60 | D81: =IFERROR(VLOOKUP(B81,AnswerBank_v5!$A$2:$AP$311,21,FALSE)/10,0) | E81: =IFERROR(VLOOKUP(B81,AnswerBank_v5!$A$2:$AP$311,36,FALSE),"") | F81: =IFERROR(VLOOKUP(B81,AnswerBank_v5!$A$2:$AP$311,19,FALSE),"") | G81: =IFERROR(VLOOKUP(C81,AnswerBank_v5!$A$2:$AP$311,21,FALSE)/10,0) | H81: =IFERROR(VLOOKUP(C81,AnswerBank_v5!$A$2:$AP$311,36,FALSE),"") | I81: =IFERROR(VLOOKUP(C81,AnswerBank_v5!$A$2:$AP$311,19,FALSE),"")
A83: ShadowIntensity_A | B83: =AVERAGE(D72:D81)
A84: ShadowIntensity_B | B84: =AVERAGE(G72:G81)
A85: IntegrityFlags_A | B85: =COUNTIF(E72:E81,"yes")
A86: IntegrityFlags_B | B86: =COUNTIF(H72:H81,"yes")
A87: PrimaryShadow_A | B87: =INDEX(F72:F81,MATCH(MAX(D72:D81),D72:D81,0))
A88: PrimaryShadow_B | B88: =INDEX(I72:I81,MATCH(MAX(G72:G81),G72:G81,0))

Sheet FinalScores_v4
A1: Final Scores v4 (deterministic prior, using all matrices)
A3: Pull from TestHarness_v4 | D3: Manual selections (use dropdowns in Excel)
A4: BehaviorCore | B4: =TestHarness_v4!B63 | D4: PrimaryArchetype_A | E4: REGULATED
A5: ClusterPenaltySum_A | B5: =TestHarness_v4!B66 | D5: SecondaryArchetype_A | E5: TRANSLATOR
A6: ClusterPenaltySum_B | B6: =TestHarness_v4!B67 | D6: PrimaryArchetype_B | E6: REGULATED
A7: ShadowIntensity_A | B7: =TestHarness_v4!B83 | D7: SecondaryArchetype_B | E7: ANALYZER
A8: ShadowIntensity_B | B8: =TestHarness_v4!B84
A9: IntegrityFlags_A | B9: =TestHarness_v4!B85 | D9: CommStyle_A | E9: COMM_Direct
A10: IntegrityFlags_B | B10: =TestHarness_v4!B86 | D10: CommStyle_B | E10: COMM_Emotional
A11: PrimaryShadow_A | B11: =TestHarness_v4!B87 | D11: RegStyle_A | E11: REG_CoRegulator
A12: PrimaryShadow_B | B12: =TestHarness_v4!B88 | D12: RegStyle_B | E12: REG_SelfSoother
D13: LoveLang_A | E13: LL_Words
A14: CommHealth | B14: =TestHarness_v4!B70 | D14: LoveLang_B | E14: LL_Touch
A15: ConflictRepair | B15: =TestHarness_v4!B71
A16: EmotionalReg | B16: =TestHarness_v4!B72 | D16: CommConflictNorm | E16: =IF(E9<E10,E9&"+" &E10,E10&"+" &E9) | F16: =IFERROR((VLOOKUP(E16,CommLookup_v4!$A$2:$B$16,2,FALSE)-2)/7,0.5)
A17: CommitmentPace | B17: =TestHarness_v4!B74 | D17: RegulationNorm | E17: =IF(E11<E12,E11&"+" &E12,E12&"+" &E11) | F17: =IFERROR((VLOOKUP(E17,RegLookup_v4!$A$2:$B$11,2,FALSE)-3)/7,0.5)
D18: LoveNorm | E18: =IF(E13<E14,E13&"+" &E14,E14&"+" &E13) | F18: =IFERROR((VLOOKUP(E18,LoveLookup_v4!$A$2:$B$16,2,FALSE)-5)/5,0.6)
D20: PP | E20: =IFERROR(VLOOKUP(E4&"|"&E6,ArchetypeLookup_v4!$A$2:$B$101,2,FALSE),7)
D21: PS | E21: =IFERROR(VLOOKUP(E4&"|"&E7,ArchetypeLookup_v4!$A$2:$B$101,2,FALSE),7)
D22: SP | E22: =IFERROR(VLOOKUP(E5&"|"&E6,ArchetypeLookup_v4!$A$2:$B$101,2,FALSE),7)
D23: SS | E23: =IFERROR(VLOOKUP(E5&"|"&E7,ArchetypeLookup_v4!$A$2:$B$101,2,FALSE),7)
D24: A (0..1) | E24: =((0.5*E20+0.2*E21+0.2*E22+0.1*E23)-2)/7
D26: ShadowKey | E26: =UPPER(SUBSTITUTE(SUBSTITUTE(B11," ",""),"-","")) | F26: =UPPER(SUBSTITUTE(SUBSTITUTE(B12," ",""),"-","")) | G26: =IF(E26<F26,E26&"_"&F26,F26&"_"&E26)
D27: ShadowScore | E27: =IFERROR(VLOOKUP(G26,ShadowLookup_v4!$A$2:$B$37,2,FALSE),3)
D28: S_risk | E28: =MIN(1,MAX(0,((E27-2)/4)*(0.7+0.15*B7+0.15*B8)))
D30: AstroKey | E30: =VLOOKUP(TestHarness_v4!B5,AstroSignMap_v4!$A$2:$B$13,2,FALSE)&"_"&TestHarness_v4!B4&"+" & VLOOKUP(TestHarness_v4!G5,AstroSignMap_v4!$A$2:$B$13,2,FALSE)&"_"&TestHarness_v4!G4
D31: Astro | E31: =IFERROR((VLOOKUP(E30,AstrologyLookup_v4!$A$2:$B$577,2,FALSE)-4)/4,0.5)
D32: NumKey | E32: =IF(TestHarness_v4!B6<TestHarness_v4!G6,TestHarness_v4!B6&"+" &TestHarness_v4!G6,TestHarness_v4!G6&"+" &TestHarness_v4!B6)
D33: Num | E33: =IFERROR((VLOOKUP(E32,NumerologyLookup_v4!$A$2:$B$67,2,FALSE)-3)/7,0.5)
D35: P (Polarity) | E35: 0.5
D37: B (Behavioral Alignment) | E37: =0.58*$B$4 + 0.18*$F$16 + 0.14*$F$17 + 0.1*$F$18
D39: ClusterPenaltyPair | E39: =MIN(35,0.35*(B5+B6))
D40: IntegrityPenalty | E40: =MIN(80,0.4*(2*B9+0.25*B5+4*B7)+0.4*(2*B10+0.25*B6+4*B8)+0.2*E39)
D41: InteractionCompatModifier | E41: 0
D42: InteractionForecastModifier | E42: 0
D44: CompatibilityScore (350-850) | E44: =MIN(850,MAX(350,350+500*(0.3*E37+0.22*E24+0.18*(1-E28)+0.12*E35+0.08*E31+0.05*E33)-E40-E39+E41))
D45: Forecast (0-100) | E45: =MIN(100,MAX(0, 100*(0.3*$F$17 + 0.25*$B$15 + 0.2*$B$14 + 0.15*$B$17 + 0.1*$E$46) - 20*$E$28 - 0.6*$E$39 + $E$42))
D46: PatternStability | E46: =0.45*$B$16+0.25*$B$15+0.15*$B$14+0.15*(1-$E$28)

Sheet AnswerBank_v5
A1: answer_id | B1: canonical_q | C1: question_number_int | D1: phase | E1: question_weight_v3 | F1: dimension_primary | G1: dimension_secondary | H1: question_text | I1: answer_option_id | J1: answer_letter | K1: answer_text | L1: score_weight | M1: compatibility_weight | N1: readiness_points_v3 | O1: compatibility_stance_v3 | P1: forecast_points_v3 | Q1: archetype | R1: archetype_id | S1: shadow_type | T1: shadow_type_id | U1: shadow_risk_points_v3 | V1: polarity_tag | W1: polarity_masc_delta_v3 | X1: polarity_fem_delta_v3 | Y1: comm_style | Z1: regulation_style | AA1: love_language | AB1: cluster_tags | AC1: cluster_1 | AD1: cluster_2 | AE1: cluster_penalty_points | AF1: pattern_tag | AG1: match_behavior_tag | AH1: pattern_risk | AI1: consistency_flag | AJ1: integrity_flag_v3 | AK1: drift_relevance | AL1: forecast_relevance | AM1: energy_type_tag | AN1: emotion_family | AO1: emotion_cell | AP1: version_snapshot | AQ1: score_weight_norm | AR1: compat_weight_norm | AS1: readiness_norm | AT1: stance_norm | AU1: forecast_norm | AV1: pattern_risk_norm | AW1: cluster_penalty_norm | AX1: polarity_masc_norm | AY1: polarity_fem_norm
A2: Q01_A | B2: 1 | C2: 1 | D2: Core | E2: 1 | F2: CommunicationHealth | G2: EmotionalNeeds | H2: When something feels off between you and someone you're dating, what usually happens next-internally or outwardly? | I2: A | J2: A | K2: It's probably nothing. I just shift into neutral and let it play out. If they bring it up, cool. If not, I'm not pushing it. | L2: 3 | M2: 4 | N2: 0 | O2: 0 | P2: 0 | Q2: Icebox | R2: 1 | U2: 0 | V2: masc:1.8;fem:-1.6 | W2: 1.8 | X2: -1.6 | Y2: COMM_Avoidant | Z2: REG_Suppressor | AA2: LANG_Time | AB2: Vulnerability_Loop , Pursuer_Distancer | AC2: Vulnerability_Loop | AD2: Pursuer_Distancer | AE2: 11 | AF2: emotional disengage | AG2: passive drifter | AH2: 0 | AI2: yes | AJ2: no | AK2: yes | AL2: yes | AP2: v3_2026-03-19 | AQ2: =(L2-Schema_v5!$C2)/(Schema_v5!$C3-Schema_v5!$C2) | AR2: =(M2-Schema_v5!$C4)/(Schema_v5!$C5-Schema_v5!$C4) | AS2: =N2/Schema_v5!$C6 | AT2: =O2/Schema_v5!$C7 | AU2: =P2/Schema_v5!$C8 | AV2: =IF(Schema_v5!$C9=0,0,AH2/Schema_v5!$C9) | AW2: =IF(Schema_v5!$C10=0,0,AE2/Schema_v5!$C10) | AX2: =(W2-Schema_v5!$C11)/(Schema_v5!$C12-Schema_v5!$C11) | AY2: =(X2-Schema_v5!$C13)/(Schema_v5!$C14-Schema_v5!$C13)
A3: Q01_B | B3: 1 | C3: 1 | D3: Core | E3: 1 | F3: CommunicationHealth | G3: EmotionalNeeds | I3: B | J3: B | K3: I start rereading everything. The tone in a text. A pause that felt a little too long. I like turning it into a puzzle to solve. | L3: 6 | M3: 7 | N3: 4 | O3: 6 | P3: 4 | Q3: Analyzer | R3: 2 | U3: 0 | V3: masc:1.4;fem:0.1 | W3: 1.4 | X3: 0.1 | Y3: COMM_Logical | Z3: REG_SelfSoother | AA3: LANG_Service | AB3: Trust_Tension | AC3: Trust_Tension | AE3: 6 | AF3: overanalysis | AG3: hyper-vigilant decoder | AH3: 0 | AI3: yes | AJ3: no | AK3: yes | AL3: yes | AP3: v3_2026-03-19 | AQ3: =(L3-Schema_v5!$C2)/(Schema_v5!$C3-Schema_v5!$C2) | AR3: =(M3-Schema_v5!$C4)/(Schema_v5!$C5-Schema_v5!$C4) | AS3: =N3/Schema_v5!$C6 | AT3: =O3/Schema_v5!$C7 | AU3: =P3/Schema_v5!$C8 | AV3: =IF(Schema_v5!$C9=0,0,AH3/Schema_v5!$C9) | AW3: =IF(Schema_v5!$C10=0,0,AE3/Schema_v5!$C10) | AX3: =(W3-Schema_v5!$C11)/(Schema_v5!$C12-Schema_v5!$C11) | AY3: =(X3-Schema_v5!$C13)/(Schema_v5!$C14-Schema_v5!$C13)
A4: Q01_C | B4: 1 | C4: 1 | D4: Core | E4: 1 | F4: CommunicationHealth | G4: EmotionalNeeds | I4: C | J4: C | K4: I'll bring something up, but I usually wrap it in a joke or a side comment. I'd rather ease into it than make it feel too serious. | L4: 7 | M4: 8 | N4: 6 | O4: 8 | P4: 8 | Q4: Translator | R4: 3 | U4: 0 | V4: masc:-0.1;fem:1.6 | W4: -0.1 | X4: 1.6 | Y4: COMM_Indirect | Z4: REG_CoRegulator | AA4: LANG_Words | AE4: 0 | AF4: soft entry communication | AG4: light approach | AH4: 0 | AI4: no | AJ4: no | AK4: yes | AL4: yes | AP4: v3_2026-03-19 | AQ4: =(L4-Schema_v5!$C2)/(Schema_v5!$C3-Schema_v5!$C2) | AR4: =(M4-Schema_v5!$C4)/(Schema_v5!$C5-Schema_v5!$C4) | AS4: =N4/Schema_v5!$C6 | AT4: =O4/Schema_v5!$C7 | AU4: =P4/Schema_v5!$C8 | AV4: =IF(Schema_v5!$C9=0,0,AH4/Schema_v5!$C9) | AW4: =IF(Schema_v5!$C10=0,0,AE4/Schema_v5!$C10) | AX4: =(W4-Schema_v5!$C11)/(Schema_v5!$C12-Schema_v5!$C11) | AY4: =(X4-Schema_v5!$C13)/(Schema_v5!$C14-Schema_v5!$C13)
A5: Q01_D | B5: 1 | C5: 1 | D5: Core | E5: 1 | F5: CommunicationHealth | G5: EmotionalNeeds | I5: D | J5: D | K5: I usually wait. Not to avoid it, just to feel it out first. I've learned not everything needs a reaction, but if it lingers, I'll say something. | L5: 8 | M5: 8 | N5: 8 | O5: 8 | P5: 6 | Q5: Survivor | R5: 8 | U5: 0 | V5: masc:0.3;fem:1.3 | W5: 0.3 | X5: 1.3 | Y5: COMM_Emotional | Z5: REG_SelfSoother | AA5: LANG_Service | AE5: 0 | AF5: measured patience | AG5: cautious feeler | AH5: 0.6 | AI5: no | AJ5: no | AK5: yes | AL5: yes | AP5: v3_2026-03-19 | AQ5: =(L5-Schema_v5!$C2)/(Schema_v5!$C3-Schema_v5!$C2) | AR5: =(M5-Schema_v5!$C4)/(Schema_v5!$C5-Schema_v5!$C4) | AS5: =N5/Schema_v5!$C6 | AT5: =O5/Schema_v5!$C7 | AU5: =P5/Schema_v5!$C8 | AV5: =IF(Schema_v5!$C9=0,0,AH5/Schema_v5!$C9) | AW5: =IF(Schema_v5!$C10=0,0,AE5/Schema_v5!$C10) | AX5: =(W5-Schema_v5!$C11)/(Schema_v5!$C12-Schema_v5!$C11) | AY5: =(X5-Schema_v5!$C13)/(Schema_v5!$C14-Schema_v5!$C13)
A6: Q01_E | B6: 1 | C6: 1 | D6: Core | E6: 1 | F6: CommunicationHealth | G6: EmotionalNeeds | I6: E | J6: E | K6: I don't do weird energy. I'm not unkind, but I also don't pretend. If something's off, I'm not sitting in it quietly. | L6: 9 | M6: 9 | N6: 10 | O6: 10 | P6: 10 | Q6: Regulated Grown-Up | R6: 9 | U6: 0 | V6: masc:1.1;fem:0.9 | W6: 1.1 | X6: 0.9 | Y6: COMM_Direct | Z6: REG_CoRegulator | AA6: LANG_Words | AE6: 0 | AF6: direct boundary setting | AG6: clear communicator | AH6: 0 | AI6: no | AJ6: no | AK6: yes | AL6: yes | AP6: v3_2026-03-19 | AQ6: =(L6-Schema_v5!$C2)/(Schema_v5!$C3-Schema_v5!$C2) | AR6: =(M6-Schema_v5!$C4)/(Schema_v5!$C5-Schema_v5!$C4) | AS6: =N6/Schema_v5!$C6 | AT6: =O6/Schema_v5!$C7 | AU6: =P6/Schema_v5!$C8 | AV6: =IF(Schema_v5!$C9=0,0,AH6/Schema_v5!$C9) | AW6: =IF(Schema_v5!$C10=0,0,AE6/Schema_v5!$C10) | AX6: =(W6-Schema_v5!$C11)/(Schema_v5!$C12-Schema_v5!$C11) | AY6: =(X6-Schema_v5!$C13)/(Schema_v5!$C14-Schema_v5!$C13)
A7: Q02_A | B7: 2 | C7: 2 | D7: Core | E7: 1 | F7: CommunicationHealth | G7: EmotionalNeeds | H7: You bring up something that bothered you. They brush it off or make a joke. What's your honest reaction? | I7: A | J7: A | K7: Not surprised. I usually go quieter after that. I've seen this play out before, no point chasing clarity where it's not offered. | L7: 5 | M7: 6 | N7: 0 | O7: 0 | P7: 0 | Q7: Quiet Exit | R7: 4 | U7: 0 | V7: masc:1.4;fem:-1.3 | W7: 1.4 | X7: -1.3 | Y7: COMM_Avoidant | Z7: REG_Suppressor | AA7: LANG_Time | AB7: Vulnerability_Loop , Pursuer_Distancer | AC7: Vulnerability_Loop | AD7: Pursuer_Distancer | AE7: 11 | AF7: withdrawal after dismissal | AG7: silent step-back | AH7: 0.8 | AI7: yes | AJ7: no | AK7: yes | AL7: yes | AP7: v3_2026-03-19 | AQ7: =(L7-Schema_v5!$C2)/(Schema_v5!$C3-Schema_v5!$C2) | AR7: =(M7-Schema_v5!$C4)/(Schema_v5!$C5-Schema_v5!$C4) | AS7: =N7/Schema_v5!$C6 | AT7: =O7/Schema_v5!$C7 | AU7: =P7/Schema_v5!$C8 | AV7: =IF(Schema_v5!$C9=0,0,AH7/Schema_v5!$C9) | AW7: =IF(Schema_v5!$C10=0,0,AE7/Schema_v5!$C10) | AX7: =(W7-Schema_v5!$C11)/(Schema_v5!$C12-Schema_v5!$C11) | AY7: =(X7-Schema_v5!$C13)/(Schema_v5!$C14-Schema_v5!$C13)
A8: Q02_B | B8: 2 | C8: 2 | D8: Core | E8: 1 | F8: CommunicationHealth | G8: EmotionalNeeds | I8: B | J8: B | K8: I'll play along, but it definitely changes how I see them. I keep score, even if they never know it. | L8: 4 | M8: 5 | N8: 0 | O8: 0 | P8: 0 | Q8: Performer | R8: 7 | U8: 0 | V8: masc:0.3;fem:0.5 | W8: 0.3 | X8: 0.5 | Y8: COMM_Indirect | Z8: REG_Distractor | AA8: LANG_Gifts | AB8: Control_Avoidance , Scorekeeping_Echo | AC8: Control_Avoidance | AD8: Scorekeeping_Echo | AE8: 14 | AF8: private resentment | AG8: image-based keeper | AH8: 1.2 | AI8: yes | AJ8: no | AK8: yes | AL8: yes | AP8: v3_2026-03-19 | AQ8: =(L8-Schema_v5!$C2)/(Schema_v5!$C3-Schema_v5!$C2) | AR8: =(M8-Schema_v5!$C4)/(Schema_v5!$C5-Schema_v5!$C4) | AS8: =N8/Schema_v5!$C6 | AT8: =O8/Schema_v5!$C7 | AU8: =P8/Schema_v5!$C8 | AV8: =IF(Schema_v5!$C9=0,0,AH8/Schema_v5!$C9) | AW8: =IF(Schema_v5!$C10=0,0,AE8/Schema_v5!$C10) | AX8: =(W8-Schema_v5!$C11)/(Schema_v5!$C12-Schema_v5!$C11) | AY8: =(X8-Schema_v5!$C13)/(Schema_v5!$C14-Schema_v5!$C13)
A9: Q02_C | B9: 2 | C9: 2 | D9: Core | E9: 1 | F9: CommunicationHealth | G9: EmotionalNeeds | I9: C | J9: C | K9: I bring it up again, but this time they can probably hear the shift in my tone. I'm not trying to argue, I just need them to actually hear me. | L9: 8 | M9: 8 | N9: 8 | O9: 8 | P9: 8 | Q9: Fixer | R9: 5 | U9: 0 | V9: masc:-0.4;fem:2.0 | W9: -0.4 | X9: 2 | Y9: COMM_Emotional | Z9: REG_CoRegulator | AA9: LANG_Service | AE9: 0 | AF9: persistence for resolution | AG9: consistent communicator | AH9: 0 | AI9: no | AJ9: no | AK9: yes | AL9: yes | AP9: v3_2026-03-19 | AQ9: =(L9-Schema_v5!$C2)/(Schema_v5!$C3-Schema_v5!$C2) | AR9: =(M9-Schema_v5!$C4)/(Schema_v5!$C5-Schema_v5!$C4) | AS9: =N9/Schema_v5!$C6 | AT9: =O9/Schema_v5!$C7 | AU9: =P9/Schema_v5!$C8 | AV9: =IF(Schema_v5!$C9=0,0,AH9/Schema_v5!$C9) | AW9: =IF(Schema_v5!$C10=0,0,AE9/Schema_v5!$C10) | AX9: =(W9-Schema_v5!$C11)/(Schema_v5!$C12-Schema_v5!$C11) | AY9: =(X9-Schema_v5!$C13)/(Schema_v5!$C14-Schema_v5!$C13)
A10: Q02_D | B10: 2 | C10: 2 | D10: Core | E10: 1 | F10: CommunicationHealth | G10: EmotionalNeeds | I10: D | J10: D | K10: I laugh too, but it sticks with me. Hours later I'm still replaying what I said, wondering if I should've just kept quiet. | L10: 5 | M10: 6 | N10: 2 | O10: 4 | P10: 2 | Q10: Phantom Seeker | R10: 10 | U10: 0 | V10: masc:-0.2;fem:1.5 | W10: -0.2 | X10: 1.5 | Y10: COMM_Emotional | Z10: REG_SelfSoother | AA10: LANG_Touch | AB10: Conflict_Flip | AC10: Conflict_Flip | AE10: 4 | AF10: quiet rumination | AG10: soft stewer | AH10: 0 | AI10: yes | AJ10: no | AK10: yes | AL10: yes | AP10: v3_2026-03-19 | AQ10: =(L10-Schema_v5!$C2)/(Schema_v5!$C3-Schema_v5!$C2) | AR10: =(M10-Schema_v5!$C4)/(Schema_v5!$C5-Schema_v5!$C4) | AS10: =N10/Schema_v5!$C6 | AT10: =O10/Schema_v5!$C7 | AU10: =P10/Schema_v5!$C8 | AV10: =IF(Schema_v5!$C9=0,0,AH10/Schema_v5!$C9) | AW10: =IF(Schema_v5!$C10=0,0,AE10/Schema_v5!$C10) | AX10: =(W10-Schema_v5!$C11)/(Schema_v5!$C12-Schema_v5!$C11) | AY10: =(X10-Schema_v5!$C13)/(Schema_v5!$C14-Schema_v5!$C13)
A11: Q02_E | B11: 2 | C11: 2 | D11: Core | E11: 1 | F11: CommunicationHealth | G11: EmotionalNeeds | I11: E | J11: E | K11: I clock that fast. If I opened up and they shrugged it off, I don't ask again. I don't mind being the bad guy if it means protecting my peace. | L11: 9 | M11: 9 | N11: 10 | O11: 10 | P11: 10 | Q11: Regulated Grown-Up | R11: 9 | U11: 0 | V11: masc:1.1;fem:0.9 | W11: 1.1 | X11: 0.9 | Y11: COMM_Direct | Z11: REG_CoRegulator | AA11: LANG_Words | AE11: 0 | AF11: fast boundary recognition | AG11: peace protector | AH11: 0 | AI11: no | AJ11: no | AK11: yes | AL11: yes | AP11: v3_2026-03-19 | AQ11: =(L11-Schema_v5!$C2)/(Schema_v5!$C3-Schema_v5!$C2) | AR11: =(M11-Schema_v5!$C4)/(Schema_v5!$C5-Schema_v5!$C4) | AS11: =N11/Schema_v5!$C6 | AT11: =O11/Schema_v5!$C7 | AU11: =P11/Schema_v5!$C8 | AV11: =IF(Schema_v5!$C9=0,0,AH11/Schema_v5!$C9) | AW11: =IF(Schema_v5!$C10=0,0,AE11/Schema_v5!$C10) | AX11: =(W11-Schema_v5!$C11)/(Schema_v5!$C12-Schema_v5!$C11) | AY11: =(X11-Schema_v5!$C13)/(Schema_v5!$C14-Schema_v5!$C13)
A12: Q03_A | B12: 3 | C12: 3 | D12: Core | E12: 1 | F12: CommunicationHealth | G12: EmotionalNeeds | H12: You start catching feelings and realizing you actually like this person. How does your energy shift? | I12: A | J12: A | K12: I pull back a little. Not to play games, I just need space to check if I'm seeing it clearly before I lean in. | L12: 6 | M12: 7 | N12: 2 | O12: 2 | P12: 0 | Q12: Icebox | R12: 1 | U12: 0 | V12: masc:1.8;fem:-1.6 | W12: 1.8 | X12: -1.6 | Y12: COMM_Avoidant | Z12: REG_Suppressor | AA12: LANG_Time | AE12: 0 | AF12: cautious distance | AG12: safety checker | AH12: 0.5 | AI12: no | AJ12: no | AK12: yes | AL12: yes | AP12: v3_2026-03-19 | AQ12: =(L12-Schema_v5!$C2)/(Schema_v5!$C3-Schema_v5!$C2) | AR12: =(M12-Schema_v5!$C4)/(Schema_v5!$C5-Schema_v5!$C4) | AS12: =N12/Schema_v5!$C6 | AT12: =O12/Schema_v5!$C7 | AU12: =P12/Schema_v5!$C8 | AV12: =IF(Schema_v5!$C9=0,0,AH12/Schema_v5!$C9) | AW12: =IF(Schema_v5!$C10=0,0,AE12/Schema_v5!$C10) | AX12: =(W12-Schema_v5!$C11)/(Schema_v5!$C12-Schema_v5!$C11) | AY12: =(X12-Schema_v5!$C13)/(Schema_v5!$C14-Schema_v5!$C13)
A13: Q03_B | B13: 3 | C13: 3 | D13: Core | E13: 1 | F13: CommunicationHealth | G13: EmotionalNeeds | I13: B | J13: B | K13: I start imagining what it could be. I try not to get ahead of myself, I just like feeling what it can be. | L13: 7 | M13: 8 | N13: 4 | O13: 6 | P13: 4 | Q13: Romantic Idealist | R13: 6 | U13: 0 | V13: masc:-0.4;fem:1.5 | W13: -0.4 | X13: 1.5 | Y13: COMM_Emotional | Z13: REG_Distractor | AA13: LANG_Gifts | AB13: Humor_Shield , Affection_Mismatch | AC13: Humor_Shield | AD13: Affection_Mismatch | AE13: 7 | AF13: guarded playfulness | AG13: safe tester | AH13: 0.2 | AI13: yes | AJ13: no | AK13: yes | AL13: yes | AP13: v3_2026-03-19 | AQ13: =(L13-Schema_v5!$C2)/(Schema_v5!$C3-Schema_v5!$C2) | AR13: =(M13-Schema_v5!$C4)/(Schema_v5!$C5-Schema_v5!$C4) | AS13: =N13/Schema_v5!$C6 | AT13: =O13/Schema_v5!$C7 | AU13: =P13/Schema_v5!$C8 | AV13: =IF(Schema_v5!$C9=0,0,AH13/Schema_v5!$C9) | AW13: =IF(Schema_v5!$C10=0,0,AE13/Schema_v5!$C10) | AX13: =(W13-Schema_v5!$C11)/(Schema_v5!$C12-Schema_v5!$C11) | AY13: =(X13-Schema_v5!$C13)/(Schema_v5!$C14-Schema_v5!$C13)
A14: Q03_C | B14: 3 | C14: 3 | D14: Core | E14: 1 | F14: CommunicationHealth | G14: EmotionalNeeds | I14: C | J14: C | K14: I don't say much, but I start showing up more, checking in, remembering little things. That's usually how I start showing my interest. | L14: 8 | M14: 9 | N14: 8 | O14: 8 | P14: 8 | Q14: Analyzer | R14: 2 | U14: 0 | V14: masc:1.4;fem:0.1 | W14: 1.4 | X14: 0.1 | Y14: COMM_Logical | Z14: REG_SelfSoother | AA14: LANG_Service | AE14: 0 | AF14: steady investment | AG14: quiet prover | AH14: 0 | AI14: no | AJ14: no | AK14: yes | AL14: yes | AP14: v3_2026-03-19 | AQ14: =(L14-Schema_v5!$C2)/(Schema_v5!$C3-Schema_v5!$C2) | AR14: =(M14-Schema_v5!$C4)/(Schema_v5!$C5-Schema_v5!$C4) | AS14: =N14/Schema_v5!$C6 | AT14: =O14/Schema_v5!$C7 | AU14: =P14/Schema_v5!$C8 | AV14: =IF(Schema_v5!$C9=0,0,AH14/Schema_v5!$C9) | AW14: =IF(Schema_v5!$C10=0,0,AE14/Schema_v5!$C10) | AX14: =(W14-Schema_v5!$C11)/(Schema_v5!$C12-Schema_v5!$C11) | AY14: =(X14-Schema_v5!$C13)/(Schema_v5!$C14-Schema_v5!$C13)
A15: Q03_D | B15: 3 | C15: 3 | D15: Core | E15: 1 | F15: CommunicationHealth | G15: EmotionalNeeds | I15: D | J15: D | K15: I want them to like me back, but I need to know it's safe first. So I keep it light while I wait on their actions. | L15: 6 | M15: 6 | N15: 4 | O15: 2 | P15: 2 | Q15: Phantom Seeker | R15: 10 | U15: 0 | V15: masc:-0.2;fem:1.5 | W15: -0.2 | X15: 1.5 | Y15: COMM_Emotional | Z15: REG_SelfSoother | AA15: LANG_Touch | AB15: Humor_Shield , Affection_Mismatch | AC15: Humor_Shield | AD15: Affection_Mismatch | AE15: 7 | AF15: guarded playfulness | AG15: safe tester | AH15: 0 | AI15: yes | AJ15: no | AK15: yes | AL15: yes | AP15: v3_2026-03-19 | AQ15: =(L15-Schema_v5!$C2)/(Schema_v5!$C3-Schema_v5!$C2) | AR15: =(M15-Schema_v5!$C4)/(Schema_v5!$C5-Schema_v5!$C4) | AS15: =N15/Schema_v5!$C6 | AT15: =O15/Schema_v5!$C7 | AU15: =P15/Schema_v5!$C8 | AV15: =IF(Schema_v5!$C9=0,0,AH15/Schema_v5!$C9) | AW15: =IF(Schema_v5!$C10=0,0,AE15/Schema_v5!$C10) | AX15: =(W15-Schema_v5!$C11)/(Schema_v5!$C12-Schema_v5!$C11) | AY15: =(X15-Schema_v5!$C13)/(Schema_v5!$C14-Schema_v5!$C13)
A16: Q03_E | B16: 3 | C16: 3 | D16: Core | E16: 1 | F16: CommunicationHealth | G16: EmotionalNeeds | I16: E | J16: E | K16: If I like someone, yeah, it shows. But I've learned not to lean too far until I know they're showing up too. I'm not trying to guess where I stand. | L16: 9 | M16: 9 | N16: 10 | O16: 10 | P16: 10 | Q16: Regulated Grown-Up | R16: 9 | U16: 0 | V16: masc:1.1;fem:0.9 | W16: 1.1 | X16: 0.9 | Y16: COMM_Direct | Z16: REG_CoRegulator | AA16: LANG_Words | AE16: 0 | AF16: balanced openness | AG16: readiness matcher | AH16: 0.2 | AI16: no | AJ16: no | AK16: yes | AL16: yes | AP16: v3_2026-03-19 | AQ16: =(L16-Schema_v5!$C2)/(Schema_v5!$C3-Schema_v5!$C2) | AR16: =(M16-Schema_v5!$C4)/(Schema_v5!$C5-Schema_v5!$C4) | AS16: =N16/Schema_v5!$C6 | AT16: =O16/Schema_v5!$C7 | AU16: =P16/Schema_v5!$C8 | AV16: =IF(Schema_v5!$C9=0,0,AH16/Schema_v5!$C9) | AW16: =IF(Schema_v5!$C10=0,0,AE16/Schema_v5!$C10) | AX16: =(W16-Schema_v5!$C11)/(Schema_v5!$C12-Schema_v5!$C11) | AY16: =(X16-Schema_v5!$C13)/(Schema_v5!$C14-Schema_v5!$C13)
A17: Q04_A | B17: 4 | C17: 4 | D17: Core | E17: 1 | F17: CommunicationHealth | G17: EmotionalNeeds | H17: You're starting to notice some red flags. Nothing explosive, just little things that don't sit right. What do you do with that feeling? | I17: A | J17: A | K17: I keep watching. I've learned not to bring things up too early. People need time to reveal themselves. | L17: 7 | M17: 8 | N17: 6 | O17: 6 | P17: 6 | Q17: Analyzer | R17: 2 | U17: 0 | V17: masc:1.4;fem:0.1 | W17: 1.4 | X17: 0.1 | Y17: COMM_Logical | Z17: REG_SelfSoother | AA17: LANG_Service | AE17: 0 | AF17: silent observation | AG17: patient tracker | AH17: 1.2 | AI17: no | AJ17: no | AK17: yes | AL17: yes | AP17: v3_2026-03-19 | AQ17: =(L17-Schema_v5!$C2)/(Schema_v5!$C3-Schema_v5!$C2) | AR17: =(M17-Schema_v5!$C4)/(Schema_v5!$C5-Schema_v5!$C4) | AS17: =N17/Schema_v5!$C6 | AT17: =O17/Schema_v5!$C7 | AU17: =P17/Schema_v5!$C8 | AV17: =IF(Schema_v5!$C9=0,0,AH17/Schema_v5!$C9) | AW17: =IF(Schema_v5!$C10=0,0,AE17/Schema_v5!$C10) | AX17: =(W17-Schema_v5!$C11)/(Schema_v5!$C12-Schema_v5!$C11) | AY17: =(X17-Schema_v5!$C13)/(Schema_v5!$C14-Schema_v5!$C13)
A18: Q04_B | B18: 4 | C18: 4 | D18: Core | E18: 1 | F18: CommunicationHealth | G18: EmotionalNeeds | I18: B | J18: B | K18: I ignore it at first. I don't want to ruin a good thing by overthinking. Sometimes I just want it to stay good for a little while. | L18: 5 | M18: 6 | N18: 2 | O18: 2 | P18: 0 | Q18: Romantic Idealist | R18: 6 | U18: 0 | V18: masc:-0.4;fem:1.5 | W18: -0.4 | X18: 1.5 | Y18: COMM_Emotional | Z18: REG_Distractor | AA18: LANG_Gifts | AB18: Commitment_Ambiguity | AC18: Commitment_Ambiguity | AE18: 5 | AF18: optimism over caution | AG18: avoidant hope | AH18: 0.6 | AI18: yes | AJ18: no | AK18: yes | AL18: yes | AP18: v3_2026-03-19 | AQ18: =(L18-Schema_v5!$C2)/(Schema_v5!$C3-Schema_v5!$C2) | AR18: =(M18-Schema_v5!$C4)/(Schema_v5!$C5-Schema_v5!$C4) | AS18: =N18/Schema_v5!$C6 | AT18: =O18/Schema_v5!$C7 | AU18: =P18/Schema_v5!$C8 | AV18: =IF(Schema_v5!$C9=0,0,AH18/Schema_v5!$C9) | AW18: =IF(Schema_v5!$C10=0,0,AE18/Schema_v5!$C10) | AX18: =(W18-Schema_v5!$C11)/(Schema_v5!$C12-Schema_v5!$C11) | AY18: =(X18-Schema_v5!$C13)/(Schema_v5!$C14-Schema_v5!$C13)
A19: Q04_C | B19: 4 | C19: 4 | D19: Core | E19: 1 | F19: CommunicationHealth | G19: EmotionalNeeds | I19: C | J19: C | K19: I call it out. I just say what I see. I'd rather know now than waste time. | L19: 10 | M19: 10 | N19: 10 | O19: 10 | P19: 10 | Q19: Regulated Grown-Up | R19: 9 | U19: 0 | V19: masc:1.1;fem:0.9 | W19: 1.1 | X19: 0.9 | Y19: COMM_Direct | Z19: REG_CoRegulator | AA19: LANG_Words | AE19: 0 | AF19: early clarity | AG19: straight talker | AH19: 0 | AI19: no | AJ19: no | AK19: yes | AL19: yes | AP19: v3_2026-03-19 | AQ19: =(L19-Schema_v5!$C2)/(Schema_v5!$C3-Schema_v5!$C2) | AR19: =(M19-Schema_v5!$C4)/(Schema_v5!$C5-Schema_v5!$C4) | AS19: =N19/Schema_v5!$C6 | AT19: =O19/Schema_v5!$C7 | AU19: =P19/Schema_v5!$C8 | AV19: =IF(Schema_v5!$C9=0,0,AH19/Schema_v5!$C9) | AW19: =IF(Schema_v5!$C10=0,0,AE19/Schema_v5!$C10) | AX19: =(W19-Schema_v5!$C11)/(Schema_v5!$C12-Schema_v5!$C11) | AY19: =(X19-Schema_v5!$C13)/(Schema_v5!$C14-Schema_v5!$C13)
A20: Q04_D | B20: 4 | C20: 4 | D20: Core | E20: 1 | F20: CommunicationHealth | G20: EmotionalNeeds | I20: D | J20: D | K20: I tell myself I'm just being too picky or expecting too much. So I wait. I just stop texting first and start holding back. | L20: 4 | M20: 5 | N20: 0 | O20: 2 | P20: 0 | Q20: Phantom Seeker | R20: 10 | U20: 0 | V20: masc:-0.2;fem:1.5 | W20: -0.2 | X20: 1.5 | Y20: COMM_Emotional | Z20: REG_SelfSoother | AA20: LANG_Touch | AB20: Commitment_Ambiguity | AC20: Commitment_Ambiguity | AE20: 5 | AF20: self-doubt delay | AG20: pullback protector | AH20: 0.6 | AI20: yes | AJ20: no | AK20: yes | AL20: yes | AP20: v3_2026-03-19 | AQ20: =(L20-Schema_v5!$C2)/(Schema_v5!$C3-Schema_v5!$C2) | AR20: =(M20-Schema_v5!$C4)/(Schema_v5!$C5-Schema_v5!$C4) | AS20: =N20/Schema_v5!$C6 | AT20: =O20/Schema_v5!$C7 | AU20: =P20/Schema_v5!$C8 | AV20: =IF(Schema_v5!$C9=0,0,AH20/Schema_v5!$C9) | AW20: =IF(Schema_v5!$C10=0,0,AE20/Schema_v5!$C10) | AX20: =(W20-Schema_v5!$C11)/(Schema_v5!$C12-Schema_v5!$C11) | AY20: =(X20-Schema_v5!$C13)/(Schema_v5!$C14-Schema_v5!$C13)
A21: Q04_E | B21: 4 | C21: 4 | D21: Core | E21: 1 | F21: CommunicationHealth | G21: EmotionalNeeds | I21: E | J21: E | K21: I've learned not to announce when I'm done, I just leave when I'm sure. I downplay it out loud, but mentally I start planning my exit. | L21: 8 | M21: 8 | N21: 4 | O21: 4 | P21: 0 | Q21: Quiet Exit | R21: 4 | U21: 0 | V21: masc:1.4;fem:-1.3 | W21: 1.4 | X21: -1.3 | Y21: COMM_Avoidant | Z21: REG_Suppressor | AA21: LANG_Time | AE21: 0 | AF21: silent exit plan | AG21: strategic withdrawer | AH21: 1.2 | AI21: no | AJ21: no | AK21: yes | AL21: yes | AP21: v3_2026-03-19 | AQ21: =(L21-Schema_v5!$C2)/(Schema_v5!$C3-Schema_v5!$C2) | AR21: =(M21-Schema_v5!$C4)/(Schema_v5!$C5-Schema_v5!$C4) | AS21: =N21/Schema_v5!$C6 | AT21: =O21/Schema_v5!$C7 | AU21: =P21/Schema_v5!$C8 | AV21: =IF(Schema_v5!$C9=0,0,AH21/Schema_v5!$C9) | AW21: =IF(Schema_v5!$C10=0,0,AE21/Schema_v5!$C10) | AX21: =(W21-Schema_v5!$C11)/(Schema_v5!$C12-Schema_v5!$C11) | AY21: =(X21-Schema_v5!$C13)/(Schema_v5!$C14-Schema_v5!$C13)
A22: Q05_A | B22: 5 | C22: 5 | D22: Core | E22: 1 | F22: CommunicationHealth | G22: EmotionalNeeds | H22: You open up about something personal. They listen, but they don't really respond or say much. How do you take that? | I22: A | J22: A | K22: I don't expect much from people emotionally. I just log it as "noted" and move on. No point getting deep with someone who doesn't meet you there. | L22: 4 | M22: 5 | N22: 0 | O22: 0 | P22: 0 | Q22: Icebox | R22: 1 | U22: 0 | V22: masc:1.8;fem:-1.6 | W22: 1.8 | X22: -1.6 | Y22: COMM_Avoidant | Z22: REG_Suppressor | AA22: LANG_Time | AB22: Scorekeeping_Echo , Vulnerability_Loop | AC22: Scorekeeping_Echo | AD22: Vulnerability_Loop | AE22: 13 | AF22: low expectation logging | AG22: cool detacher | AH22: 0.6 | AI22: yes | AJ22: no | AK22: yes | AL22: yes | AP22: v3_2026-03-19 | AQ22: =(L22-Schema_v5!$C2)/(Schema_v5!$C3-Schema_v5!$C2) | AR22: =(M22-Schema_v5!$C4)/(Schema_v5!$C5-Schema_v5!$C4) | AS22: =N22/Schema_v5!$C6 | AT22: =O22/Schema_v5!$C7 | AU22: =P22/Schema_v5!$C8 | AV22: =IF(Schema_v5!$C9=0,0,AH22/Schema_v5!$C9) | AW22: =IF(Schema_v5!$C10=0,0,AE22/Schema_v5!$C10) | AX22: =(W22-Schema_v5!$C11)/(Schema_v5!$C12-Schema_v5!$C11) | AY22: =(X22-Schema_v5!$C13)/(Schema_v5!$C14-Schema_v5!$C13)
A23: Q05_B | B23: 5 | C23: 5 | D23: Core | E23: 1 | F23: CommunicationHealth | G23: EmotionalNeeds | I23: B | J23: B | K23: I brush it off, but I don't forget it. Stuff like that reminds me who's safe and who just wants the easy version of me. | L23: 6 | M23: 7 | N23: 4 | O23: 6 | P23: 6 | Q23: Survivor | R23: 8 | U23: 0 | V23: masc:0.3;fem:1.3 | W23: 0.3 | X23: 1.3 | Y23: COMM_Emotional | Z23: REG_SelfSoother | AA23: LANG_Service | AE23: 0 | AF23: guarded memory | AG23: loyalty filter | AH23: 0 | AI23: no | AJ23: no | AK23: yes | AL23: yes | AP23: v3_2026-03-19 | AQ23: =(L23-Schema_v5!$C2)/(Schema_v5!$C3-Schema_v5!$C2) | AR23: =(M23-Schema_v5!$C4)/(Schema_v5!$C5-Schema_v5!$C4) | AS23: =N23/Schema_v5!$C6 | AT23: =O23/Schema_v5!$C7 | AU23: =P23/Schema_v5!$C8 | AV23: =IF(Schema_v5!$C9=0,0,AH23/Schema_v5!$C9) | AW23: =IF(Schema_v5!$C10=0,0,AE23/Schema_v5!$C10) | AX23: =(W23-Schema_v5!$C11)/(Schema_v5!$C12-Schema_v5!$C11) | AY23: =(X23-Schema_v5!$C13)/(Schema_v5!$C14-Schema_v5!$C13)
A24: Q05_C | B24: 5 | C24: 5 | D24: Core | E24: 1 | F24: CommunicationHealth | G24: EmotionalNeeds | I24: C | J24: C | K24: I try to explain again, maybe they didn't get it. And if they still don't? I stop showing that side to someone who doesn't see me. | L24: 8 | M24: 9 | N24: 8 | O24: 10 | P24: 8 | Q24: Fixer | R24: 5 | U24: 0 | V24: masc:-0.4;fem:2.0 | W24: -0.4 | X24: 2 | Y24: COMM_Emotional | Z24: REG_CoRegulator | AA24: LANG_Service | AE24: 0 | AF24: repair attempt | AG24: persistent helper | AH24: 0 | AI24: no | AJ24: no | AK24: yes | AL24: yes | AP24: v3_2026-03-19 | AQ24: =(L24-Schema_v5!$C2)/(Schema_v5!$C3-Schema_v5!$C2) | AR24: =(M24-Schema_v5!$C4)/(Schema_v5!$C5-Schema_v5!$C4) | AS24: =N24/Schema_v5!$C6 | AT24: =O24/Schema_v5!$C7 | AU24: =P24/Schema_v5!$C8 | AV24: =IF(Schema_v5!$C9=0,0,AH24/Schema_v5!$C9) | AW24: =IF(Schema_v5!$C10=0,0,AE24/Schema_v5!$C10) | AX24: =(W24-Schema_v5!$C11)/(Schema_v5!$C12-Schema_v5!$C11) | AY24: =(X24-Schema_v5!$C13)/(Schema_v5!$C14-Schema_v5!$C13)
A25: Q05_D | B25: 5 | C25: 5 | D25: Core | E25: 1 | F25: CommunicationHealth | G25: EmotionalNeeds | I25: D | J25: D | K25: I keep it smooth, but I notice the shift. Makes me rethink what I share next time, it's easier to just stay surface when people don't respond. | L25: 5 | M25: 6 | N25: 0 | O25: 2 | P25: 0 | Q25: Performer | R25: 7 | U25: 0 | V25: masc:0.3;fem:0.5 | W25: 0.3 | X25: 0.5 | Y25: COMM_Indirect | Z25: REG_Distractor | AA25: LANG_Gifts | AB25: Public_Private_Split , Conflict_Flip | AC25: Public_Private_Split | AD25: Conflict_Flip | AE25: 8 | AF25: image-based withdrawal | AG25: surface masker | AH25: 1.2 | AI25: yes | AJ25: no | AK25: yes | AL25: yes | AP25: v3_2026-03-19 | AQ25: =(L25-Schema_v5!$C2)/(Schema_v5!$C3-Schema_v5!$C2) | AR25: =(M25-Schema_v5!$C4)/(Schema_v5!$C5-Schema_v5!$C4) | AS25: =N25/Schema_v5!$C6 | AT25: =O25/Schema_v5!$C7 | AU25: =P25/Schema_v5!$C8 | AV25: =IF(Schema_v5!$C9=0,0,AH25/Schema_v5!$C9) | AW25: =IF(Schema_v5!$C10=0,0,AE25/Schema_v5!$C10) | AX25: =(W25-Schema_v5!$C11)/(Schema_v5!$C12-Schema_v5!$C11) | AY25: =(X25-Schema_v5!$C13)/(Schema_v5!$C14-Schema_v5!$C13)
A26: Q05_E | B26: 5 | C26: 5 | D26: Core | E26: 1 | F26: CommunicationHealth | G26: EmotionalNeeds | I26: E | J26: E | K26: Silence says a lot. I take note. If they care, it'll show later, if not, I don't open that part of me again. | L26: 9 | M26: 9 | N26: 10 | O26: 10 | P26: 10 | Q26: Regulated Grown-Up | R26: 9 | U26: 0 | V26: masc:1.1;fem:0.9 | W26: 1.1 | X26: 0.9 | Y26: COMM_Direct | Z26: REG_CoRegulator | AA26: LANG_Words | AE26: 0 | AF26: high awareness | AG26: calm sentinel | AH26: 0 | AI26: no | AJ26: no | AK26: yes | AL26: yes | AP26: v3_2026-03-19 | AQ26: =(L26-Schema_v5!$C2)/(Schema_v5!$C3-Schema_v5!$C2) | AR26: =(M26-Schema_v5!$C4)/(Schema_v5!$C5-Schema_v5!$C4) | AS26: =N26/Schema_v5!$C6 | AT26: =O26/Schema_v5!$C7 | AU26: =P26/Schema_v5!$C8 | AV26: =IF(Schema_v5!$C9=0,0,AH26/Schema_v5!$C9) | AW26: =IF(Schema_v5!$C10=0,0,AE26/Schema_v5!$C10) | AX26: =(W26-Schema_v5!$C11)/(Schema_v5!$C12-Schema_v5!$C11) | AY26: =(X26-Schema_v5!$C13)/(Schema_v5!$C14-Schema_v5!$C13)
A27: Q06_A | B27: 6 | C27: 6 | D27: Core | E27: 1 | F27: CommunicationHealth | G27: EmotionalNeeds | H27: Question 6: One day they're into you, then distant the next. How do you handle the mixed signals? | I27: A | J27: A | K27: If you're hot and cold, I'm room temperature and gone. I'm not here to decode moods. | L27: 9 | M27: 9 | N27: 10 | O27: 10 | P27: 10 | Q27: Regulated Grown-Up | R27: 9 | U27: 0 | V27: masc:1.1;fem:0.9 | W27: 1.1 | X27: 0.9 | Y27: COMM_Direct | Z27: REG_CoRegulator | AA27: LANG_Words | AE27: 0 | AF27: blunt detachment | AG27: immediate cutoff | AH27: 1.2 | AI27: no | AJ27: no | AK27: yes | AL27: yes | AP27: v3_2026-03-19 | AQ27: =(L27-Schema_v5!$C2)/(Schema_v5!$C3-Schema_v5!$C2) | AR27: =(M27-Schema_v5!$C4)/(Schema_v5!$C5-Schema_v5!$C4) | AS27: =N27/Schema_v5!$C6 | AT27: =O27/Schema_v5!$C7 | AU27: =P27/Schema_v5!$C8 | AV27: =IF(Schema_v5!$C9=0,0,AH27/Schema_v5!$C9) | AW27: =IF(Schema_v5!$C10=0,0,AE27/Schema_v5!$C10) | AX27: =(W27-Schema_v5!$C11)/(Schema_v5!$C12-Schema_v5!$C11) | AY27: =(X27-Schema_v5!$C13)/(Schema_v5!$C14-Schema_v5!$C13)
A28: Q06_B | B28: 6 | C28: 6 | D28: Core | E28: 1 | F28: CommunicationHealth | G28: EmotionalNeeds | I28: B | J28: B | K28: I recheck our last texts. Then I reread mine. Then I wonder if I should've said less, or more. I don't bring it up, but it definitely rewires how I respond. | L28: 5 | M28: 6 | N28: 4 | O28: 4 | P28: 2 | Q28: Analyzer | R28: 2 | U28: 0 | V28: masc:1.4;fem:0.1 | W28: 1.4 | X28: 0.1 | Y28: COMM_Logical | Z28: REG_SelfSoother | AA28: LANG_Service | AB28: Trust_Tension | AC28: Trust_Tension | AE28: 6 | AF28: emotional spiral | AG28: overanalyzer | AH28: 0 | AI28: yes | AJ28: no | AK28: yes | AL28: yes | AP28: v3_2026-03-19 | AQ28: =(L28-Schema_v5!$C2)/(Schema_v5!$C3-Schema_v5!$C2) | AR28: =(M28-Schema_v5!$C4)/(Schema_v5!$C5-Schema_v5!$C4) | AS28: =N28/Schema_v5!$C6 | AT28: =O28/Schema_v5!$C7 | AU28: =P28/Schema_v5!$C8 | AV28: =IF(Schema_v5!$C9=0,0,AH28/Schema_v5!$C9) | AW28: =IF(Schema_v5!$C10=0,0,AE28/Schema_v5!$C10) | AX28: =(W28-Schema_v5!$C11)/(Schema_v5!$C12-Schema_v5!$C11) | AY28: =(X28-Schema_v5!$C13)/(Schema_v5!$C14-Schema_v5!$C13)
A29: Q06_C | B29: 6 | C29: 6 | D29: Core | E29: 1 | F29: CommunicationHealth | G29: EmotionalNeeds | I29: C | J29: C | K29: I back off. They'll either notice or they won't. I'm not chasing people who don't know what they want. | L29: 4 | M29: 5 | N29: 0 | O29: 0 | P29: 0 | Q29: Icebox | R29: 1 | U29: 0 | V29: masc:1.8;fem:-1.6 | W29: 1.8 | X29: -1.6 | Y29: COMM_Avoidant | Z29: REG_Suppressor | AA29: LANG_Time | AB29: Vulnerability_Loop | AC29: Vulnerability_Loop | AE29: 5 | AF29: quiet burn | AG29: disengaged pullback | AH29: 0.6 | AI29: yes | AJ29: no | AK29: yes | AL29: yes | AP29: v3_2026-03-19 | AQ29: =(L29-Schema_v5!$C2)/(Schema_v5!$C3-Schema_v5!$C2) | AR29: =(M29-Schema_v5!$C4)/(Schema_v5!$C5-Schema_v5!$C4) | AS29: =N29/Schema_v5!$C6 | AT29: =O29/Schema_v5!$C7 | AU29: =P29/Schema_v5!$C8 | AV29: =IF(Schema_v5!$C9=0,0,AH29/Schema_v5!$C9) | AW29: =IF(Schema_v5!$C10=0,0,AE29/Schema_v5!$C10) | AX29: =(W29-Schema_v5!$C11)/(Schema_v5!$C12-Schema_v5!$C11) | AY29: =(X29-Schema_v5!$C13)/(Schema_v5!$C14-Schema_v5!$C13)
A30: Q06_D | B30: 6 | C30: 6 | D30: Core | E30: 1 | F30: CommunicationHealth | G30: EmotionalNeeds | I30: D | J30: D | K30: I stop bringing things up. If they don't want me, I'm not going to beg to be understood. I've played that game before. | L30: 6 | M30: 7 | N30: 4 | O30: 4 | P30: 4 | Q30: Fixer | R30: 5 | U30: 0 | V30: masc:-0.4;fem:2.0 | W30: -0.4 | X30: 2 | Y30: COMM_Emotional | Z30: REG_CoRegulator | AA30: LANG_Service | AB30: Affection_Mismatch , Independence_Collision | AC30: Affection_Mismatch | AD30: Independence_Collision | AE30: 9 | AF30: resigned caregiver | AG30: silent surrender | AH30: 1.2 | AI30: yes | AJ30: no | AK30: yes | AL30: yes | AP30: v3_2026-03-19 | AQ30: =(L30-Schema_v5!$C2)/(Schema_v5!$C3-Schema_v5!$C2) | AR30: =(M30-Schema_v5!$C4)/(Schema_v5!$C5-Schema_v5!$C4) | AS30: =N30/Schema_v5!$C6 | AT30: =O30/Schema_v5!$C7 | AU30: =P30/Schema_v5!$C8 | AV30: =IF(Schema_v5!$C9=0,0,AH30/Schema_v5!$C9) | AW30: =IF(Schema_v5!$C10=0,0,AE30/Schema_v5!$C10) | AX30: =(W30-Schema_v5!$C11)/(Schema_v5!$C12-Schema_v5!$C11) | AY30: =(X30-Schema_v5!$C13)/(Schema_v5!$C14-Schema_v5!$C13)
A31: Q06_E | B31: 6 | C31: 6 | D31: Core | E31: 1 | F31: CommunicationHealth | G31: EmotionalNeeds | I31: E | J31: E | K31: I tell myself it's probably just stress or a bad week. I don't want to give up too early, but it's hard not to notice when it shifts. | L31: 7 | M31: 8 | N31: 6 | O31: 6 | P31: 4 | Q31: Romantic Idealist | R31: 6 | U31: 0 | V31: masc:-0.4;fem:1.5 | W31: -0.4 | X31: 1.5 | Y31: COMM_Emotional | Z31: REG_Distractor | AA31: LANG_Gifts | AE31: 0 | AF31: tired hope | AG31: cautious optimist | AH31: 0 | AI31: no | AJ31: no | AK31: yes | AL31: yes | AP31: v3_2026-03-19 | AQ31: =(L31-Schema_v5!$C2)/(Schema_v5!$C3-Schema_v5!$C2) | AR31: =(M31-Schema_v5!$C4)/(Schema_v5!$C5-Schema_v5!$C4) | AS31: =N31/Schema_v5!$C6 | AT31: =O31/Schema_v5!$C7 | AU31: =P31/Schema_v5!$C8 | AV31: =IF(Schema_v5!$C9=0,0,AH31/Schema_v5!$C9) | AW31: =IF(Schema_v5!$C10=0,0,AE31/Schema_v5!$C10) | AX31: =(W31-Schema_v5!$C11)/(Schema_v5!$C12-Schema_v5!$C11) | AY31: =(X31-Schema_v5!$C13)/(Schema_v5!$C14-Schema_v5!$C13)
A32: Q07_A | B32: 7 | C32: 7 | D32: Core | E32: 1 | F32: CommunicationHealth | G32: EmotionalNeeds | H32: Question 7: You're deep in conversation and they suddenly shut down or go cold. What's your move? | I32: A | J32: A | K32: I pause. I've learned not everything's about me. If they want to talk, they will. If not, I don't chase silence. | L32: 8 | M32: 8 | N32: 4 | O32: 4 | P32: 0 | Q32: Icebox | R32: 1 | U32: 0 | V32: masc:1.8;fem:-1.6 | W32: 1.8 | X32: -1.6 | Y32: COMM_Avoidant | Z32: REG_Suppressor | AA32: LANG_Time | AE32: 0 | AF32: calm detachment | AG32: patient withdrawer | AH32: 0.8 | AI32: no | AJ32: no | AK32: yes | AL32: yes | AP32: v3_2026-03-19 | AQ32: =(L32-Schema_v5!$C2)/(Schema_v5!$C3-Schema_v5!$C2) | AR32: =(M32-Schema_v5!$C4)/(Schema_v5!$C5-Schema_v5!$C4) | AS32: =N32/Schema_v5!$C6 | AT32: =O32/Schema_v5!$C7 | AU32: =P32/Schema_v5!$C8 | AV32: =IF(Schema_v5!$C9=0,0,AH32/Schema_v5!$C9) | AW32: =IF(Schema_v5!$C10=0,0,AE32/Schema_v5!$C10) | AX32: =(W32-Schema_v5!$C11)/(Schema_v5!$C12-Schema_v5!$C11) | AY32: =(X32-Schema_v5!$C13)/(Schema_v5!$C14-Schema_v5!$C13)
A33: Q07_B | B33: 7 | C33: 7 | D33: Core | E33: 1 | F33: CommunicationHealth | G33: EmotionalNeeds | I33: B | J33: B | K33: I immediately think I said something wrong. I start scanning every word trying to figure out what triggered it. | L33: 5 | M33: 6 | N33: 4 | O33: 4 | P33: 2 | Q33: Analyzer | R33: 2 | U33: 0 | V33: masc:1.4;fem:0.1 | W33: 1.4 | X33: 0.1 | Y33: COMM_Logical | Z33: REG_SelfSoother | AA33: LANG_Service | AB33: Vulnerability_Loop | AC33: Vulnerability_Loop | AE33: 5 | AF33: inner spiral | AG33: self-blamer | AH33: 0 | AI33: yes | AJ33: no | AK33: yes | AL33: yes | AP33: v3_2026-03-19 | AQ33: =(L33-Schema_v5!$C2)/(Schema_v5!$C3-Schema_v5!$C2) | AR33: =(M33-Schema_v5!$C4)/(Schema_v5!$C5-Schema_v5!$C4) | AS33: =N33/Schema_v5!$C6 | AT33: =O33/Schema_v5!$C7 | AU33: =P33/Schema_v5!$C8 | AV33: =IF(Schema_v5!$C9=0,0,AH33/Schema_v5!$C9) | AW33: =IF(Schema_v5!$C10=0,0,AE33/Schema_v5!$C10) | AX33: =(W33-Schema_v5!$C11)/(Schema_v5!$C12-Schema_v5!$C11) | AY33: =(X33-Schema_v5!$C13)/(Schema_v5!$C14-Schema_v5!$C13)
A34: Q07_C | B34: 7 | C34: 7 | D34: Core | E34: 1 | F34: CommunicationHealth | G34: EmotionalNeeds | I34: C | J34: C | K34: I'll ask once. If it's brushed off or ignored, I shift. I'm not the type to sit in someone else's silence for long. | L34: 9 | M34: 9 | N34: 10 | O34: 10 | P34: 10 | Q34: Regulated Grown-Up | R34: 9 | U34: 0 | V34: masc:1.1;fem:0.9 | W34: 1.1 | X34: 0.9 | Y34: COMM_Direct | Z34: REG_CoRegulator | AA34: LANG_Words | AE34: 0 | AF34: direct with boundaries | AG34: firm line-setter | AH34: 0 | AI34: no | AJ34: no | AK34: yes | AL34: yes | AP34: v3_2026-03-19 | AQ34: =(L34-Schema_v5!$C2)/(Schema_v5!$C3-Schema_v5!$C2) | AR34: =(M34-Schema_v5!$C4)/(Schema_v5!$C5-Schema_v5!$C4) | AS34: =N34/Schema_v5!$C6 | AT34: =O34/Schema_v5!$C7 | AU34: =P34/Schema_v5!$C8 | AV34: =IF(Schema_v5!$C9=0,0,AH34/Schema_v5!$C9) | AW34: =IF(Schema_v5!$C10=0,0,AE34/Schema_v5!$C10) | AX34: =(W34-Schema_v5!$C11)/(Schema_v5!$C12-Schema_v5!$C11) | AY34: =(X34-Schema_v5!$C13)/(Schema_v5!$C14-Schema_v5!$C13)
A35: Q07_D | B35: 7 | C35: 7 | D35: Core | E35: 1 | F35: CommunicationHealth | G35: EmotionalNeeds | I35: D | J35: D | K35: I try to keep the mood up, shift the subject, make it feel less tense, even if I'm freaking out a little inside. | L35: 6 | M35: 7 | N35: 4 | O35: 4 | P35: 2 | Q35: Performer | R35: 7 | U35: 0 | V35: masc:0.3;fem:0.5 | W35: 0.3 | X35: 0.5 | Y35: COMM_Indirect | Z35: REG_Distractor | AA35: LANG_Gifts | AB35: Vulnerability_Loop | AC35: Vulnerability_Loop | AE35: 5 | AF35: smooth cover-up | AG35: tension diffuser | AH35: 0 | AI35: yes | AJ35: no | AK35: yes | AL35: yes | AP35: v3_2026-03-19 | AQ35: =(L35-Schema_v5!$C2)/(Schema_v5!$C3-Schema_v5!$C2) | AR35: =(M35-Schema_v5!$C4)/(Schema_v5!$C5-Schema_v5!$C4) | AS35: =N35/Schema_v5!$C6 | AT35: =O35/Schema_v5!$C7 | AU35: =P35/Schema_v5!$C8 | AV35: =IF(Schema_v5!$C9=0,0,AH35/Schema_v5!$C9) | AW35: =IF(Schema_v5!$C10=0,0,AE35/Schema_v5!$C10) | AX35: =(W35-Schema_v5!$C11)/(Schema_v5!$C12-Schema_v5!$C11) | AY35: =(X35-Schema_v5!$C13)/(Schema_v5!$C14-Schema_v5!$C13)
A36: Q07_E | B36: 7 | C36: 7 | D36: Core | E36: 1 | F36: CommunicationHealth | G36: EmotionalNeeds | I36: E | J36: E | K36: I feel it, but I don't say anything. I stay present, hoping they'll come back to me on their own. | L36: 6 | M36: 6 | N36: 4 | O36: 4 | P36: 4 | Q36: Translator | R36: 3 | U36: 0 | V36: masc:-0.1;fem:1.6 | W36: -0.1 | X36: 1.6 | Y36: COMM_Indirect | Z36: REG_CoRegulator | AA36: LANG_Words | AB36: Vulnerability_Loop | AC36: Vulnerability_Loop | AE36: 5 | AF36: gentle waiter | AG36: silent holder | AH36: 0.6 | AI36: yes | AJ36: no | AK36: yes | AL36: yes | AP36: v3_2026-03-19 | AQ36: =(L36-Schema_v5!$C2)/(Schema_v5!$C3-Schema_v5!$C2) | AR36: =(M36-Schema_v5!$C4)/(Schema_v5!$C5-Schema_v5!$C4) | AS36: =N36/Schema_v5!$C6 | AT36: =O36/Schema_v5!$C7 | AU36: =P36/Schema_v5!$C8 | AV36: =IF(Schema_v5!$C9=0,0,AH36/Schema_v5!$C9) | AW36: =IF(Schema_v5!$C10=0,0,AE36/Schema_v5!$C10) | AX36: =(W36-Schema_v5!$C11)/(Schema_v5!$C12-Schema_v5!$C11) | AY36: =(X36-Schema_v5!$C13)/(Schema_v5!$C14-Schema_v5!$C13)
A37: Q08_A | B37: 8 | C37: 8 | D37: Core | E37: 1 | F37: CommunicationHealth | G37: EmotionalNeeds | H37: Question 8: You feel them pulling away. They haven't said it, but the shift is obvious. What runs through your head first? | I37: A | J37: A | K37: Here we go again. I already know how this plays out. I stop trying the second I feel myself caring more than they do. | L37: 5 | M37: 5 | N37: 4 | O37: 2 | P37: 2 | Q37: Survivor | R37: 8 | U37: 0 | V37: masc:0.3;fem:1.3 | W37: 0.3 | X37: 1.3 | Y37: COMM_Emotional | Z37: REG_SelfSoother | AA37: LANG_Service | AB37: Vulnerability_Loop | AC37: Vulnerability_Loop | AE37: 5 | AF37: pain-calibrated exit | AG37: early withdrawer | AH37: 0.6 | AI37: yes | AJ37: no | AK37: yes | AL37: yes | AP37: v3_2026-03-19 | AQ37: =(L37-Schema_v5!$C2)/(Schema_v5!$C3-Schema_v5!$C2) | AR37: =(M37-Schema_v5!$C4)/(Schema_v5!$C5-Schema_v5!$C4) | AS37: =N37/Schema_v5!$C6 | AT37: =O37/Schema_v5!$C7 | AU37: =P37/Schema_v5!$C8 | AV37: =IF(Schema_v5!$C9=0,0,AH37/Schema_v5!$C9) | AW37: =IF(Schema_v5!$C10=0,0,AE37/Schema_v5!$C10) | AX37: =(W37-Schema_v5!$C11)/(Schema_v5!$C12-Schema_v5!$C11) | AY37: =(X37-Schema_v5!$C13)/(Schema_v5!$C14-Schema_v5!$C13)
A38: Q08_B | B38: 8 | C38: 8 | D38: Core | E38: 1 | F38: CommunicationHealth | G38: EmotionalNeeds | I38: B | J38: B | K38: It's subtle, but I clock everything. Less emojis. Slower replies. Something's off, I just haven't figured out what yet. | L38: 7 | M38: 8 | N38: 6 | O38: 6 | P38: 6 | Q38: Analyzer | R38: 2 | U38: 0 | V38: masc:1.4;fem:0.1 | W38: 1.4 | X38: 0.1 | Y38: COMM_Logical | Z38: REG_SelfSoother | AA38: LANG_Service | AE38: 0 | AF38: pattern tracker | AG38: micro-signal reader | AH38: 0.6 | AI38: no | AJ38: no | AK38: yes | AL38: yes | AP38: v3_2026-03-19 | AQ38: =(L38-Schema_v5!$C2)/(Schema_v5!$C3-Schema_v5!$C2) | AR38: =(M38-Schema_v5!$C4)/(Schema_v5!$C5-Schema_v5!$C4) | AS38: =N38/Schema_v5!$C6 | AT38: =O38/Schema_v5!$C7 | AU38: =P38/Schema_v5!$C8 | AV38: =IF(Schema_v5!$C9=0,0,AH38/Schema_v5!$C9) | AW38: =IF(Schema_v5!$C10=0,0,AE38/Schema_v5!$C10) | AX38: =(W38-Schema_v5!$C11)/(Schema_v5!$C12-Schema_v5!$C11) | AY38: =(X38-Schema_v5!$C13)/(Schema_v5!$C14-Schema_v5!$C13)
A39: Q08_C | B39: 8 | C39: 8 | D39: Core | E39: 1 | F39: CommunicationHealth | G39: EmotionalNeeds | I39: C | J39: C | K39: I don't ask. I just start detaching. If you're fading, I'm not chasing. I've done that before, and I don't owe anyone a meltdown. | L39: 5 | M39: 6 | N39: 0 | O39: 2 | P39: 0 | Q39: Quiet Exit | R39: 4 | U39: 0 | V39: masc:1.4;fem:-1.3 | W39: 1.4 | X39: -1.3 | Y39: COMM_Avoidant | Z39: REG_Suppressor | AA39: LANG_Time | AB39: Vulnerability_Loop | AC39: Vulnerability_Loop | AE39: 5 | AF39: soft boundary | AG39: quiet exit | AH39: 0.2 | AI39: yes | AJ39: no | AK39: yes | AL39: yes | AP39: v3_2026-03-19 | AQ39: =(L39-Schema_v5!$C2)/(Schema_v5!$C3-Schema_v5!$C2) | AR39: =(M39-Schema_v5!$C4)/(Schema_v5!$C5-Schema_v5!$C4) | AS39: =N39/Schema_v5!$C6 | AT39: =O39/Schema_v5!$C7 | AU39: =P39/Schema_v5!$C8 | AV39: =IF(Schema_v5!$C9=0,0,AH39/Schema_v5!$C9) | AW39: =IF(Schema_v5!$C10=0,0,AE39/Schema_v5!$C10) | AX39: =(W39-Schema_v5!$C11)/(Schema_v5!$C12-Schema_v5!$C11) | AY39: =(X39-Schema_v5!$C13)/(Schema_v5!$C14-Schema_v5!$C13)
A40: Q08_D | B40: 8 | C40: 8 | D40: Core | E40: 1 | F40: CommunicationHealth | G40: EmotionalNeeds | I40: D | J40: D | K40: Maybe they just need space. I try not to assume the worst... but yeah, it's hard not to take it personal. | L40: 7 | M40: 8 | N40: 6 | O40: 6 | P40: 4 | Q40: Romantic Idealist | R40: 6 | U40: 0 | V40: masc:-0.4;fem:1.5 | W40: -0.4 | X40: 1.5 | Y40: COMM_Emotional | Z40: REG_Distractor | AA40: LANG_Gifts | AE40: 0 | AF40: fragile optimism | AG40: tentative hope | AH40: 0 | AI40: no | AJ40: no | AK40: yes | AL40: yes | AP40: v3_2026-03-19 | AQ40: =(L40-Schema_v5!$C2)/(Schema_v5!$C3-Schema_v5!$C2) | AR40: =(M40-Schema_v5!$C4)/(Schema_v5!$C5-Schema_v5!$C4) | AS40: =N40/Schema_v5!$C6 | AT40: =O40/Schema_v5!$C7 | AU40: =P40/Schema_v5!$C8 | AV40: =IF(Schema_v5!$C9=0,0,AH40/Schema_v5!$C9) | AW40: =IF(Schema_v5!$C10=0,0,AE40/Schema_v5!$C10) | AX40: =(W40-Schema_v5!$C11)/(Schema_v5!$C12-Schema_v5!$C11) | AY40: =(X40-Schema_v5!$C13)/(Schema_v5!$C14-Schema_v5!$C13)
A41: Q08_E | B41: 8 | C41: 8 | D41: Core | E41: 1 | F41: CommunicationHealth | G41: EmotionalNeeds | I41: E | J41: E | K41: Cool. If they're gonna play distant, I'll be busy too. I'm not built to beg for consistency. | L41: 4 | M41: 5 | N41: 0 | O41: 0 | P41: 0 | Q41: Icebox | R41: 1 | U41: 0 | V41: masc:1.8;fem:-1.6 | W41: 1.8 | X41: -1.6 | Y41: COMM_Avoidant | Z41: REG_Suppressor | AA41: LANG_Time | AB41: Vulnerability_Loop , Pursuer_Distancer | AC41: Vulnerability_Loop | AD41: Pursuer_Distancer | AE41: 11 | AF41: defensive control | AG41: mirrored distance | AH41: 0 | AI41: yes | AJ41: no | AK41: yes | AL41: yes | AP41: v3_2026-03-19 | AQ41: =(L41-Schema_v5!$C2)/(Schema_v5!$C3-Schema_v5!$C2) | AR41: =(M41-Schema_v5!$C4)/(Schema_v5!$C5-Schema_v5!$C4) | AS41: =N41/Schema_v5!$C6 | AT41: =O41/Schema_v5!$C7 | AU41: =P41/Schema_v5!$C8 | AV41: =IF(Schema_v5!$C9=0,0,AH41/Schema_v5!$C9) | AW41: =IF(Schema_v5!$C10=0,0,AE41/Schema_v5!$C10) | AX41: =(W41-Schema_v5!$C11)/(Schema_v5!$C12-Schema_v5!$C11) | AY41: =(X41-Schema_v5!$C13)/(Schema_v5!$C14-Schema_v5!$C13)
A42: Q09_A | B42: 9 | C42: 9 | D42: Core | E42: 1.05 | F42: ConflictRepair | G42: CommunicationHealth | H42: Question 9: They cancel plans last minute. No real reason, no reschedule. How do you take it? | I42: A | J42: A | K42: Noted. That's usually my cue to start pulling my energy back. I don't throw a fit, I just stop handing out access. | L42: 7 | M42: 8 | N42: 4 | O42: 4 | P42: 0 | Q42: Quiet Exit | R42: 4 | U42: 0 | V42: masc:1.4;fem:-1.3 | W42: 1.4 | X42: -1.3 | Y42: COMM_Avoidant | Z42: REG_Suppressor | AA42: LANG_Time | AE42: 0 | AF42: soft withdrawal | AG42: quiet boundary | AH42: 0.2 | AI42: no | AJ42: no | AK42: yes | AL42: yes | AP42: v3_2026-03-19 | AQ42: =(L42-Schema_v5!$C2)/(Schema_v5!$C3-Schema_v5!$C2) | AR42: =(M42-Schema_v5!$C4)/(Schema_v5!$C5-Schema_v5!$C4) | AS42: =N42/Schema_v5!$C6 | AT42: =O42/Schema_v5!$C7 | AU42: =P42/Schema_v5!$C8 | AV42: =IF(Schema_v5!$C9=0,0,AH42/Schema_v5!$C9) | AW42: =IF(Schema_v5!$C10=0,0,AE42/Schema_v5!$C10) | AX42: =(W42-Schema_v5!$C11)/(Schema_v5!$C12-Schema_v5!$C11) | AY42: =(X42-Schema_v5!$C13)/(Schema_v5!$C14-Schema_v5!$C13)
A43: Q09_B | B43: 9 | C43: 9 | D43: Core | E43: 1.05 | F43: ConflictRepair | G43: CommunicationHealth | I43: B | J43: B | K43: I act like it's fine, but it lingers. Now I'm checking who else they were with, what story that timing fits into. I overthink for a living. | L43: 5 | M43: 6 | N43: 4 | O43: 4 | P43: 2 | Q43: Analyzer | R43: 2 | U43: 0 | V43: masc:1.4;fem:0.1 | W43: 1.4 | X43: 0.1 | Y43: COMM_Logical | Z43: REG_SelfSoother | AA43: LANG_Service | AB43: Vulnerability_Loop | AC43: Vulnerability_Loop | AE43: 5 | AF43: obsessive cross-referencer | AG43: trust checker | AH43: 0 | AI43: yes | AJ43: no | AK43: yes | AL43: yes | AP43: v3_2026-03-19 | AQ43: =(L43-Schema_v5!$C2)/(Schema_v5!$C3-Schema_v5!$C2) | AR43: =(M43-Schema_v5!$C4)/(Schema_v5!$C5-Schema_v5!$C4) | AS43: =N43/Schema_v5!$C6 | AT43: =O43/Schema_v5!$C7 | AU43: =P43/Schema_v5!$C8 | AV43: =IF(Schema_v5!$C9=0,0,AH43/Schema_v5!$C9) | AW43: =IF(Schema_v5!$C10=0,0,AE43/Schema_v5!$C10) | AX43: =(W43-Schema_v5!$C11)/(Schema_v5!$C12-Schema_v5!$C11) | AY43: =(X43-Schema_v5!$C13)/(Schema_v5!$C14-Schema_v5!$C13)
A44: Q09_C | B44: 9 | C44: 9 | D44: Core | E44: 1.05 | F44: ConflictRepair | G44: CommunicationHealth | I44: C | J44: C | K44: It stings. I replay the texts a few times, wondering what I said or didn't say. I don't bring it up, but I definitely adjust after that. | L44: 5 | M44: 6 | N44: 2 | O44: 4 | P44: 2 | Q44: Phantom Seeker | R44: 10 | U44: 0 | V44: masc:-0.2;fem:1.5 | W44: -0.2 | X44: 1.5 | Y44: COMM_Emotional | Z44: REG_SelfSoother | AA44: LANG_Touch | AB44: Vulnerability_Loop | AC44: Vulnerability_Loop | AE44: 5 | AF44: internalizer pullback | AG44: cautious retreater | AH44: 0 | AI44: yes | AJ44: no | AK44: yes | AL44: yes | AP44: v3_2026-03-19 | AQ44: =(L44-Schema_v5!$C2)/(Schema_v5!$C3-Schema_v5!$C2) | AR44: =(M44-Schema_v5!$C4)/(Schema_v5!$C5-Schema_v5!$C4) | AS44: =N44/Schema_v5!$C6 | AT44: =O44/Schema_v5!$C7 | AU44: =P44/Schema_v5!$C8 | AV44: =IF(Schema_v5!$C9=0,0,AH44/Schema_v5!$C9) | AW44: =IF(Schema_v5!$C10=0,0,AE44/Schema_v5!$C10) | AX44: =(W44-Schema_v5!$C11)/(Schema_v5!$C12-Schema_v5!$C11) | AY44: =(X44-Schema_v5!$C13)/(Schema_v5!$C14-Schema_v5!$C13)
A45: Q09_D | B45: 9 | C45: 9 | D45: Core | E45: 1.05 | F45: ConflictRepair | G45: CommunicationHealth | I45: D | J45: D | K45: I get annoyed, then weirdly try harder. Like maybe if I'm more consistent, they'll start matching that. It never really works, but I still do it. | L45: 4 | M45: 5 | N45: 2 | O45: 2 | P45: 2 | Q45: Fixer | R45: 5 | U45: 0 | V45: masc:-0.4;fem:2.0 | W45: -0.4 | X45: 2 | Y45: COMM_Emotional | Z45: REG_CoRegulator | AA45: LANG_Service | AB45: Commitment_Ambiguity | AC45: Commitment_Ambiguity | AE45: 5 | AF45: conditional effort loop | AG45: overcompensator | AH45: 0 | AI45: yes | AJ45: no | AK45: yes | AL45: yes | AP45: v3_2026-03-19 | AQ45: =(L45-Schema_v5!$C2)/(Schema_v5!$C3-Schema_v5!$C2) | AR45: =(M45-Schema_v5!$C4)/(Schema_v5!$C5-Schema_v5!$C4) | AS45: =N45/Schema_v5!$C6 | AT45: =O45/Schema_v5!$C7 | AU45: =P45/Schema_v5!$C8 | AV45: =IF(Schema_v5!$C9=0,0,AH45/Schema_v5!$C9) | AW45: =IF(Schema_v5!$C10=0,0,AE45/Schema_v5!$C10) | AX45: =(W45-Schema_v5!$C11)/(Schema_v5!$C12-Schema_v5!$C11) | AY45: =(X45-Schema_v5!$C13)/(Schema_v5!$C14-Schema_v5!$C13)
A46: Q09_E | B46: 9 | C46: 9 | D46: Core | E46: 1.05 | F46: ConflictRepair | G46: CommunicationHealth | I46: E | J46: E | K46: Cool. That tells me everything I needed to know. I move different after that, no announcement required. | L46: 4 | M46: 5 | N46: 0 | O46: 0 | P46: 0 | Q46: Icebox | R46: 1 | U46: 0 | V46: masc:1.8;fem:-1.6 | W46: 1.8 | X46: -1.6 | Y46: COMM_Avoidant | Z46: REG_Suppressor | AA46: LANG_Time | AE46: 0 | AF46: cold logic | AG46: decisive exit | AH46: 0.6 | AI46: no | AJ46: no | AK46: yes | AL46: yes | AP46: v3_2026-03-19 | AQ46: =(L46-Schema_v5!$C2)/(Schema_v5!$C3-Schema_v5!$C2) | AR46: =(M46-Schema_v5!$C4)/(Schema_v5!$C5-Schema_v5!$C4) | AS46: =N46/Schema_v5!$C6 | AT46: =O46/Schema_v5!$C7 | AU46: =P46/Schema_v5!$C8 | AV46: =IF(Schema_v5!$C9=0,0,AH46/Schema_v5!$C9) | AW46: =IF(Schema_v5!$C10=0,0,AE46/Schema_v5!$C10) | AX46: =(W46-Schema_v5!$C11)/(Schema_v5!$C12-Schema_v5!$C11) | AY46: =(X46-Schema_v5!$C13)/(Schema_v5!$C14-Schema_v5!$C13)
A47: Q10_A | B47: 10 | C47: 10 | D47: Core | E47: 1.05 | F47: ConflictRepair | G47: CommunicationHealth | H47: Question 10: They come to you for comfort when things go wrong-but you're not sure they'd do the same for you. What runs through your mind? | I47: A | J47: A | K47: I play the part, but I clock the imbalance. I've been the safe place before, doesn't mean they ever planned to stay. | L47: 7 | M47: 8 | N47: 6 | O47: 8 | P47: 6 | Q47: Survivor | R47: 8 | U47: 0 | V47: masc:0.3;fem:1.3 | W47: 0.3 | X47: 1.3 | Y47: COMM_Emotional | Z47: REG_SelfSoother | AA47: LANG_Service | AE47: 0 | AF47: burned-out responder | AG47: guarded giver | AH47: 0 | AI47: no | AJ47: no | AK47: yes | AL47: yes | AP47: v3_2026-03-19 | AQ47: =(L47-Schema_v5!$C2)/(Schema_v5!$C3-Schema_v5!$C2) | AR47: =(M47-Schema_v5!$C4)/(Schema_v5!$C5-Schema_v5!$C4) | AS47: =N47/Schema_v5!$C6 | AT47: =O47/Schema_v5!$C7 | AU47: =P47/Schema_v5!$C8 | AV47: =IF(Schema_v5!$C9=0,0,AH47/Schema_v5!$C9) | AW47: =IF(Schema_v5!$C10=0,0,AE47/Schema_v5!$C10) | AX47: =(W47-Schema_v5!$C11)/(Schema_v5!$C12-Schema_v5!$C11) | AY47: =(X47-Schema_v5!$C13)/(Schema_v5!$C14-Schema_v5!$C13)
A48: Q10_B | B48: 10 | C48: 10 | D48: Core | E48: 1.05 | F48: ConflictRepair | G48: CommunicationHealth | I48: B | J48: B | K48: I try to be what they need, hoping maybe this time they'll realize I'm more than a backup plan. | L48: 6 | M48: 7 | N48: 4 | O48: 6 | P48: 4 | Q48: Fixer | R48: 5 | U48: 0 | V48: masc:-0.4;fem:2.0 | W48: -0.4 | X48: 2 | Y48: COMM_Emotional | Z48: REG_CoRegulator | AA48: LANG_Service | AB48: Commitment_Ambiguity | AC48: Commitment_Ambiguity | AE48: 5 | AF48: approval-seeking caretaker | AG48: hopeful server | AH48: 0 | AI48: yes | AJ48: no | AK48: yes | AL48: yes | AP48: v3_2026-03-19 | AQ48: =(L48-Schema_v5!$C2)/(Schema_v5!$C3-Schema_v5!$C2) | AR48: =(M48-Schema_v5!$C4)/(Schema_v5!$C5-Schema_v5!$C4) | AS48: =N48/Schema_v5!$C6 | AT48: =O48/Schema_v5!$C7 | AU48: =P48/Schema_v5!$C8 | AV48: =IF(Schema_v5!$C9=0,0,AH48/Schema_v5!$C9) | AW48: =IF(Schema_v5!$C10=0,0,AE48/Schema_v5!$C10) | AX48: =(W48-Schema_v5!$C11)/(Schema_v5!$C12-Schema_v5!$C11) | AY48: =(X48-Schema_v5!$C13)/(Schema_v5!$C14-Schema_v5!$C13)
A49: Q10_C | B49: 10 | C49: 10 | D49: Core | E49: 1.05 | F49: ConflictRepair | G49: CommunicationHealth | I49: C | J49: C | K49: I comfort them, but in my head I'm already creating distance. If I can't count on them too, this whole thing is one-sided. | L49: 7 | M49: 8 | N49: 6 | O49: 8 | P49: 6 | Q49: Analyzer | R49: 2 | U49: 0 | V49: masc:1.4;fem:0.1 | W49: 1.4 | X49: 0.1 | Y49: COMM_Logical | Z49: REG_SelfSoother | AA49: LANG_Service | AE49: 0 | AF49: measured pullback | AG49: quiet assessor | AH49: 0 | AI49: no | AJ49: no | AK49: yes | AL49: yes | AP49: v3_2026-03-19 | AQ49: =(L49-Schema_v5!$C2)/(Schema_v5!$C3-Schema_v5!$C2) | AR49: =(M49-Schema_v5!$C4)/(Schema_v5!$C5-Schema_v5!$C4) | AS49: =N49/Schema_v5!$C6 | AT49: =O49/Schema_v5!$C7 | AU49: =P49/Schema_v5!$C8 | AV49: =IF(Schema_v5!$C9=0,0,AH49/Schema_v5!$C9) | AW49: =IF(Schema_v5!$C10=0,0,AE49/Schema_v5!$C10) | AX49: =(W49-Schema_v5!$C11)/(Schema_v5!$C12-Schema_v5!$C11) | AY49: =(X49-Schema_v5!$C13)/(Schema_v5!$C14-Schema_v5!$C13)
A50: Q10_D | B50: 10 | C50: 10 | D50: Core | E50: 1.05 | F50: ConflictRepair | G50: CommunicationHealth | I50: D | J50: D | K50: I act calm, but I feel it. When I need someone, I keep it to myself, so watching them lean on me makes the silence louder. | L50: 5 | M50: 6 | N50: 2 | O50: 4 | P50: 2 | Q50: Phantom Seeker | R50: 10 | U50: 0 | V50: masc:-0.2;fem:1.5 | W50: -0.2 | X50: 1.5 | Y50: COMM_Emotional | Z50: REG_SelfSoother | AA50: LANG_Touch | AB50: Transparency_Gap | AC50: Transparency_Gap | AE50: 5 | AF50: quiet resentment | AG50: unspoken holder | AH50: 0 | AI50: yes | AJ50: no | AK50: yes | AL50: yes | AP50: v3_2026-03-19 | AQ50: =(L50-Schema_v5!$C2)/(Schema_v5!$C3-Schema_v5!$C2) | AR50: =(M50-Schema_v5!$C4)/(Schema_v5!$C5-Schema_v5!$C4) | AS50: =N50/Schema_v5!$C6 | AT50: =O50/Schema_v5!$C7 | AU50: =P50/Schema_v5!$C8 | AV50: =IF(Schema_v5!$C9=0,0,AH50/Schema_v5!$C9) | AW50: =IF(Schema_v5!$C10=0,0,AE50/Schema_v5!$C10) | AX50: =(W50-Schema_v5!$C11)/(Schema_v5!$C12-Schema_v5!$C11) | AY50: =(X50-Schema_v5!$C13)/(Schema_v5!$C14-Schema_v5!$C13)
A51: Q10_E | B51: 10 | C51: 10 | D51: Core | E51: 1.05 | F51: ConflictRepair | G51: CommunicationHealth | I51: E | J51: E | K51: I give them what they need in the moment. Then I sit with the feeling later, wondering why I always end up being the one who shows up. | L51: 6 | M51: 7 | N51: 4 | O51: 4 | P51: 4 | Q51: Romantic Idealist | R51: 6 | U51: 0 | V51: masc:-0.4;fem:1.5 | W51: -0.4 | X51: 1.5 | Y51: COMM_Emotional | Z51: REG_Distractor | AA51: LANG_Gifts | AE51: 0 | AF51: tired loyal dreamer | AG51: devoted but drained | AH51: 0 | AI51: no | AJ51: no | AK51: yes | AL51: yes | AP51: v3_2026-03-19 | AQ51: =(L51-Schema_v5!$C2)/(Schema_v5!$C3-Schema_v5!$C2) | AR51: =(M51-Schema_v5!$C4)/(Schema_v5!$C5-Schema_v5!$C4) | AS51: =N51/Schema_v5!$C6 | AT51: =O51/Schema_v5!$C7 | AU51: =P51/Schema_v5!$C8 | AV51: =IF(Schema_v5!$C9=0,0,AH51/Schema_v5!$C9) | AW51: =IF(Schema_v5!$C10=0,0,AE51/Schema_v5!$C10) | AX51: =(W51-Schema_v5!$C11)/(Schema_v5!$C12-Schema_v5!$C11) | AY51: =(X51-Schema_v5!$C13)/(Schema_v5!$C14-Schema_v5!$C13)
A52: Q11_A | B52: 11 | C52: 11 | D52: Core | E52: 1.05 | F52: ConflictRepair | G52: CommunicationHealth | H52: They start acting distant-less replies, colder tone, still polite. What's your first move? | I52: A | J52: A | K52: I give them space. If they want to talk, they will. If not, I take the hint. | L52: 7 | M52: 8 | N52: 4 | O52: 4 | P52: 0 | Q52: Icebox | R52: 1 | U52: 0 | V52: masc:1.8;fem:-1.6 | W52: 1.8 | X52: -1.6 | Y52: COMM_Avoidant | Z52: REG_Suppressor | AA52: LANG_Time | AE52: 0 | AF52: detached cool | AG52: patient withdrawer | AH52: 1.2 | AI52: no | AJ52: no | AK52: yes | AL52: yes | AP52: v3_2026-03-19 | AQ52: =(L52-Schema_v5!$C2)/(Schema_v5!$C3-Schema_v5!$C2) | AR52: =(M52-Schema_v5!$C4)/(Schema_v5!$C5-Schema_v5!$C4) | AS52: =N52/Schema_v5!$C6 | AT52: =O52/Schema_v5!$C7 | AU52: =P52/Schema_v5!$C8 | AV52: =IF(Schema_v5!$C9=0,0,AH52/Schema_v5!$C9) | AW52: =IF(Schema_v5!$C10=0,0,AE52/Schema_v5!$C10) | AX52: =(W52-Schema_v5!$C11)/(Schema_v5!$C12-Schema_v5!$C11) | AY52: =(X52-Schema_v5!$C13)/(Schema_v5!$C14-Schema_v5!$C13)
A53: Q11_B | B53: 11 | C53: 11 | D53: Core | E53: 1.05 | F53: ConflictRepair | G53: CommunicationHealth | I53: B | J53: B | K53: I reread every text. Then I spiral into what I should've said differently. | L53: 4 | M53: 5 | N53: 2 | O53: 2 | P53: 2 | Q53: Analyzer | R53: 2 | U53: 0 | V53: masc:1.4;fem:0.1 | W53: 1.4 | X53: 0.1 | Y53: COMM_Logical | Z53: REG_SelfSoother | AA53: LANG_Service | AB53: Trust_Tension | AC53: Trust_Tension | AE53: 6 | AF53: ruminating replayer | AG53: overanalyzer | AH53: 0 | AI53: yes | AJ53: no | AK53: yes | AL53: yes | AP53: v3_2026-03-19 | AQ53: =(L53-Schema_v5!$C2)/(Schema_v5!$C3-Schema_v5!$C2) | AR53: =(M53-Schema_v5!$C4)/(Schema_v5!$C5-Schema_v5!$C4) | AS53: =N53/Schema_v5!$C6 | AT53: =O53/Schema_v5!$C7 | AU53: =P53/Schema_v5!$C8 | AV53: =IF(Schema_v5!$C9=0,0,AH53/Schema_v5!$C9) | AW53: =IF(Schema_v5!$C10=0,0,AE53/Schema_v5!$C10) | AX53: =(W53-Schema_v5!$C11)/(Schema_v5!$C12-Schema_v5!$C11) | AY53: =(X53-Schema_v5!$C13)/(Schema_v5!$C14-Schema_v5!$C13)
A54: Q11_C | B54: 11 | C54: 11 | D54: Core | E54: 1.05 | F54: ConflictRepair | G54: CommunicationHealth | I54: C | J54: C | K54: I mirror their shift. If they're pulling back, so am I, no explanations. | L54: 6 | M54: 7 | N54: 2 | O54: 2 | P54: 0 | Q54: Quiet Exit | R54: 4 | U54: 0 | V54: masc:1.4;fem:-1.3 | W54: 1.4 | X54: -1.3 | Y54: COMM_Avoidant | Z54: REG_Suppressor | AA54: LANG_Time | AB54: Pursuer_Distancer | AC54: Pursuer_Distancer | AE54: 6 | AF54: soft echo | AG54: mirrored withdrawal | AH54: 0.6 | AI54: yes | AJ54: no | AK54: yes | AL54: yes | AP54: v3_2026-03-19 | AQ54: =(L54-Schema_v5!$C2)/(Schema_v5!$C3-Schema_v5!$C2) | AR54: =(M54-Schema_v5!$C4)/(Schema_v5!$C5-Schema_v5!$C4) | AS54: =N54/Schema_v5!$C6 | AT54: =O54/Schema_v5!$C7 | AU54: =P54/Schema_v5!$C8 | AV54: =IF(Schema_v5!$C9=0,0,AH54/Schema_v5!$C9) | AW54: =IF(Schema_v5!$C10=0,0,AE54/Schema_v5!$C10) | AX54: =(W54-Schema_v5!$C11)/(Schema_v5!$C12-Schema_v5!$C11) | AY54: =(X54-Schema_v5!$C13)/(Schema_v5!$C14-Schema_v5!$C13)
A55: Q11_D | B55: 11 | C55: 11 | D55: Core | E55: 1.05 | F55: ConflictRepair | G55: CommunicationHealth | I55: D | J55: D | K55: I try to re-engage them. Make them laugh. Be light. I don't want to feel the shift. | L55: 6 | M55: 7 | N55: 4 | O55: 4 | P55: 2 | Q55: Performer | R55: 7 | U55: 0 | V55: masc:0.3;fem:0.5 | W55: 0.3 | X55: 0.5 | Y55: COMM_Indirect | Z55: REG_Distractor | AA55: LANG_Gifts | AB55: Vulnerability_Loop | AC55: Vulnerability_Loop | AE55: 5 | AF55: mood manager | AG55: tension diffuser | AH55: 0 | AI55: yes | AJ55: no | AK55: yes | AL55: yes | AP55: v3_2026-03-19 | AQ55: =(L55-Schema_v5!$C2)/(Schema_v5!$C3-Schema_v5!$C2) | AR55: =(M55-Schema_v5!$C4)/(Schema_v5!$C5-Schema_v5!$C4) | AS55: =N55/Schema_v5!$C6 | AT55: =O55/Schema_v5!$C7 | AU55: =P55/Schema_v5!$C8 | AV55: =IF(Schema_v5!$C9=0,0,AH55/Schema_v5!$C9) | AW55: =IF(Schema_v5!$C10=0,0,AE55/Schema_v5!$C10) | AX55: =(W55-Schema_v5!$C11)/(Schema_v5!$C12-Schema_v5!$C11) | AY55: =(X55-Schema_v5!$C13)/(Schema_v5!$C14-Schema_v5!$C13)
A56: Q11_E | B56: 11 | C56: 11 | D56: Core | E56: 1.05 | F56: ConflictRepair | G56: CommunicationHealth | I56: E | J56: E | K56: I sit with it, hoping they'll come back on their own. I don't press. I just wait. | L56: 7 | M56: 8 | N56: 6 | O56: 8 | P56: 8 | Q56: Translator | R56: 3 | U56: 0 | V56: masc:-0.1;fem:1.6 | W56: -0.1 | X56: 1.6 | Y56: COMM_Indirect | Z56: REG_CoRegulator | AA56: LANG_Words | AE56: 0 | AF56: gentle responder | AG56: quiet holder | AH56: 0 | AI56: no | AJ56: no | AK56: yes | AL56: yes | AP56: v3_2026-03-19 | AQ56: =(L56-Schema_v5!$C2)/(Schema_v5!$C3-Schema_v5!$C2) | AR56: =(M56-Schema_v5!$C4)/(Schema_v5!$C5-Schema_v5!$C4) | AS56: =N56/Schema_v5!$C6 | AT56: =O56/Schema_v5!$C7 | AU56: =P56/Schema_v5!$C8 | AV56: =IF(Schema_v5!$C9=0,0,AH56/Schema_v5!$C9) | AW56: =IF(Schema_v5!$C10=0,0,AE56/Schema_v5!$C10) | AX56: =(W56-Schema_v5!$C11)/(Schema_v5!$C12-Schema_v5!$C11) | AY56: =(X56-Schema_v5!$C13)/(Schema_v5!$C14-Schema_v5!$C13)
A57: Q12_A | B57: 12 | C57: 12 | D57: Core | E57: 1.05 | F57: ConflictRepair | G57: CommunicationHealth | H57: They used to check in every day. Now they don't. You haven't brought it up yet. What's brewing in your head? | I57: A | J57: A | K57: Something changed. I don't know what, but it's not just in my head. | L57: 7 | M57: 8 | N57: 6 | O57: 8 | P57: 6 | Q57: Analyzer | R57: 2 | U57: 0 | V57: masc:1.4;fem:0.1 | W57: 1.4 | X57: 0.1 | Y57: COMM_Logical | Z57: REG_SelfSoother | AA57: LANG_Service | AE57: 0 | AF57: pattern watcher | AG57: subtle signal reader | AH57: 0 | AI57: no | AJ57: no | AK57: yes | AL57: yes | AP57: v3_2026-03-19 | AQ57: =(L57-Schema_v5!$C2)/(Schema_v5!$C3-Schema_v5!$C2) | AR57: =(M57-Schema_v5!$C4)/(Schema_v5!$C5-Schema_v5!$C4) | AS57: =N57/Schema_v5!$C6 | AT57: =O57/Schema_v5!$C7 | AU57: =P57/Schema_v5!$C8 | AV57: =IF(Schema_v5!$C9=0,0,AH57/Schema_v5!$C9) | AW57: =IF(Schema_v5!$C10=0,0,AE57/Schema_v5!$C10) | AX57: =(W57-Schema_v5!$C11)/(Schema_v5!$C12-Schema_v5!$C11) | AY57: =(X57-Schema_v5!$C13)/(Schema_v5!$C14-Schema_v5!$C13)
A58: Q12_B | B58: 12 | C58: 12 | D58: Core | E58: 1.05 | F58: ConflictRepair | G58: CommunicationHealth | I58: B | J58: B | K58: I try not to assume. I wait. If I ask and it's nothing, I'll feel stupid. | L58: 5 | M58: 6 | N58: 2 | O58: 4 | P58: 2 | Q58: Phantom Seeker | R58: 10 | U58: 0 | V58: masc:-0.2;fem:1.5 | W58: -0.2 | X58: 1.5 | Y58: COMM_Emotional | Z58: REG_SelfSoother | AA58: LANG_Touch | AB58: Vulnerability_Loop | AC58: Vulnerability_Loop | AE58: 5 | AF58: doubtful waiter | AG58: hesitant checker | AH58: 0 | AI58: yes | AJ58: no | AK58: yes | AL58: yes | AP58: v3_2026-03-19 | AQ58: =(L58-Schema_v5!$C2)/(Schema_v5!$C3-Schema_v5!$C2) | AR58: =(M58-Schema_v5!$C4)/(Schema_v5!$C5-Schema_v5!$C4) | AS58: =N58/Schema_v5!$C6 | AT58: =O58/Schema_v5!$C7 | AU58: =P58/Schema_v5!$C8 | AV58: =IF(Schema_v5!$C9=0,0,AH58/Schema_v5!$C9) | AW58: =IF(Schema_v5!$C10=0,0,AE58/Schema_v5!$C10) | AX58: =(W58-Schema_v5!$C11)/(Schema_v5!$C12-Schema_v5!$C11) | AY58: =(X58-Schema_v5!$C13)/(Schema_v5!$C14-Schema_v5!$C13)
A59: Q12_C | B59: 12 | C59: 12 | D59: Core | E59: 1.05 | F59: ConflictRepair | G59: CommunicationHealth | I59: C | J59: C | K59: I bring it up again, but this time they can probably hear the shift in my tone. I'm not trying to argue-I just need them to actually hear me. | L59: 9 | M59: 9 | N59: 10 | O59: 10 | P59: 10 | Q59: Regulated Grown-Up | R59: 9 | U59: 0 | V59: masc:1.1;fem:0.9 | W59: 1.1 | X59: 0.9 | Y59: COMM_Direct | Z59: REG_CoRegulator | AA59: LANG_Words | AE59: 0 | AF59: calm confronter | AG59: direct communicator | AH59: 0 | AI59: no | AJ59: no | AK59: yes | AL59: yes | AP59: v3_2026-03-19 | AQ59: =(L59-Schema_v5!$C2)/(Schema_v5!$C3-Schema_v5!$C2) | AR59: =(M59-Schema_v5!$C4)/(Schema_v5!$C5-Schema_v5!$C4) | AS59: =N59/Schema_v5!$C6 | AT59: =O59/Schema_v5!$C7 | AU59: =P59/Schema_v5!$C8 | AV59: =IF(Schema_v5!$C9=0,0,AH59/Schema_v5!$C9) | AW59: =IF(Schema_v5!$C10=0,0,AE59/Schema_v5!$C10) | AX59: =(W59-Schema_v5!$C11)/(Schema_v5!$C12-Schema_v5!$C11) | AY59: =(X59-Schema_v5!$C13)/(Schema_v5!$C14-Schema_v5!$C13)
A60: Q12_D | B60: 12 | C60: 12 | D60: Core | E60: 1.05 | F60: ConflictRepair | G60: CommunicationHealth | I60: D | J60: D | K60: I joke about it to see how they react. If they don't bite, I pull back quietly. | L60: 6 | M60: 7 | N60: 2 | O60: 2 | P60: 0 | Q60: Performer | R60: 7 | U60: 0 | V60: masc:0.3;fem:0.5 | W60: 0.3 | X60: 0.5 | Y60: COMM_Indirect | Z60: REG_Distractor | AA60: LANG_Gifts | AB60: Vulnerability_Loop , Scorekeeping_Echo | AC60: Vulnerability_Loop | AD60: Scorekeeping_Echo | AE60: 13 | AF60: playful tester | AG60: indirect feeler | AH60: 0.8 | AI60: yes | AJ60: no | AK60: yes | AL60: yes | AP60: v3_2026-03-19 | AQ60: =(L60-Schema_v5!$C2)/(Schema_v5!$C3-Schema_v5!$C2) | AR60: =(M60-Schema_v5!$C4)/(Schema_v5!$C5-Schema_v5!$C4) | AS60: =N60/Schema_v5!$C6 | AT60: =O60/Schema_v5!$C7 | AU60: =P60/Schema_v5!$C8 | AV60: =IF(Schema_v5!$C9=0,0,AH60/Schema_v5!$C9) | AW60: =IF(Schema_v5!$C10=0,0,AE60/Schema_v5!$C10) | AX60: =(W60-Schema_v5!$C11)/(Schema_v5!$C12-Schema_v5!$C11) | AY60: =(X60-Schema_v5!$C13)/(Schema_v5!$C14-Schema_v5!$C13)
A61: Q12_E | B61: 12 | C61: 12 | D61: Core | E61: 1.05 | F61: ConflictRepair | G61: CommunicationHealth | I61: E | J61: E | K61: I shift before they get the chance to. I've seen this pattern before, I know how it ends. | L61: 6 | M61: 7 | N61: 4 | O61: 6 | P61: 4 | Q61: Survivor | R61: 8 | U61: 0 | V61: masc:0.3;fem:1.3 | W61: 0.3 | X61: 1.3 | Y61: COMM_Emotional | Z61: REG_SelfSoother | AA61: LANG_Service | AB61: Vulnerability_Loop | AC61: Vulnerability_Loop | AE61: 5 | AF61: pain-preemptive responder | AG61: early exit planner | AH61: 0 | AI61: yes | AJ61: no | AK61: yes | AL61: yes | AP61: v3_2026-03-19 | AQ61: =(L61-Schema_v5!$C2)/(Schema_v5!$C3-Schema_v5!$C2) | AR61: =(M61-Schema_v5!$C4)/(Schema_v5!$C5-Schema_v5!$C4) | AS61: =N61/Schema_v5!$C6 | AT61: =O61/Schema_v5!$C7 | AU61: =P61/Schema_v5!$C8 | AV61: =IF(Schema_v5!$C9=0,0,AH61/Schema_v5!$C9) | AW61: =IF(Schema_v5!$C10=0,0,AE61/Schema_v5!$C10) | AX61: =(W61-Schema_v5!$C11)/(Schema_v5!$C12-Schema_v5!$C11) | AY61: =(X61-Schema_v5!$C13)/(Schema_v5!$C14-Schema_v5!$C13)
A62: Q13_A | B62: 13 | C62: 13 | D62: Core | E62: 1.05 | F62: ConflictRepair | G62: CommunicationHealth | H62: They say they like you-but they're inconsistent. What part of you answers that first? | I62: A | J62: A | K62: I just need space to check if I'm seeing it clearly before I lean in. Not to play games. | L62: 8 | M62: 8 | N62: 4 | O62: 4 | P62: 2 | Q62: Quiet Exit | R62: 4 | U62: 0 | V62: masc:1.4;fem:-1.3 | W62: 1.4 | X62: -1.3 | Y62: COMM_Avoidant | Z62: REG_Suppressor | AA62: LANG_Time | AE62: 0 | AF62: observer mode | AG62: cautious engager | AH62: 0.2 | AI62: no | AJ62: no | AK62: yes | AL62: yes | AP62: v3_2026-03-19 | AQ62: =(L62-Schema_v5!$C2)/(Schema_v5!$C3-Schema_v5!$C2) | AR62: =(M62-Schema_v5!$C4)/(Schema_v5!$C5-Schema_v5!$C4) | AS62: =N62/Schema_v5!$C6 | AT62: =O62/Schema_v5!$C7 | AU62: =P62/Schema_v5!$C8 | AV62: =IF(Schema_v5!$C9=0,0,AH62/Schema_v5!$C9) | AW62: =IF(Schema_v5!$C10=0,0,AE62/Schema_v5!$C10) | AX62: =(W62-Schema_v5!$C11)/(Schema_v5!$C12-Schema_v5!$C11) | AY62: =(X62-Schema_v5!$C13)/(Schema_v5!$C14-Schema_v5!$C13)
A63: Q13_B | B63: 13 | C63: 13 | D63: Core | E63: 1.05 | F63: ConflictRepair | G63: CommunicationHealth | I63: B | J63: B | K63: I start imagining what it could be. I try not to get ahead of myself, I just like feeling what it can be. | L63: 7 | M63: 8 | N63: 6 | O63: 6 | P63: 4 | Q63: Romantic Idealist | R63: 6 | U63: 0 | V63: masc:-0.4;fem:1.5 | W63: -0.4 | X63: 1.5 | Y63: COMM_Emotional | Z63: REG_Distractor | AA63: LANG_Gifts | AE63: 0 | AF63: daydreaming hopeful | AG63: romantic visionary | AH63: 0 | AI63: no | AJ63: no | AK63: yes | AL63: yes | AP63: v3_2026-03-19 | AQ63: =(L63-Schema_v5!$C2)/(Schema_v5!$C3-Schema_v5!$C2) | AR63: =(M63-Schema_v5!$C4)/(Schema_v5!$C5-Schema_v5!$C4) | AS63: =N63/Schema_v5!$C6 | AT63: =O63/Schema_v5!$C7 | AU63: =P63/Schema_v5!$C8 | AV63: =IF(Schema_v5!$C9=0,0,AH63/Schema_v5!$C9) | AW63: =IF(Schema_v5!$C10=0,0,AE63/Schema_v5!$C10) | AX63: =(W63-Schema_v5!$C11)/(Schema_v5!$C12-Schema_v5!$C11) | AY63: =(X63-Schema_v5!$C13)/(Schema_v5!$C14-Schema_v5!$C13)
A64: Q13_C | B64: 13 | C64: 13 | D64: Core | E64: 1.05 | F64: ConflictRepair | G64: CommunicationHealth | I64: C | J64: C | K64: I don't say much, but I start showing up more, checking in, remembering little things. That's usually how I start showing my interest. | L64: 8 | M64: 9 | N64: 8 | O64: 10 | P64: 8 | Q64: Translator | R64: 3 | U64: 0 | V64: masc:-0.1;fem:1.6 | W64: -0.1 | X64: 1.6 | Y64: COMM_Indirect | Z64: REG_CoRegulator | AA64: LANG_Words | AE64: 0 | AF64: steady signaler | AG64: consistent investor | AH64: 0 | AI64: no | AJ64: no | AK64: yes | AL64: yes | AP64: v3_2026-03-19 | AQ64: =(L64-Schema_v5!$C2)/(Schema_v5!$C3-Schema_v5!$C2) | AR64: =(M64-Schema_v5!$C4)/(Schema_v5!$C5-Schema_v5!$C4) | AS64: =N64/Schema_v5!$C6 | AT64: =O64/Schema_v5!$C7 | AU64: =P64/Schema_v5!$C8 | AV64: =IF(Schema_v5!$C9=0,0,AH64/Schema_v5!$C9) | AW64: =IF(Schema_v5!$C10=0,0,AE64/Schema_v5!$C10) | AX64: =(W64-Schema_v5!$C11)/(Schema_v5!$C12-Schema_v5!$C11) | AY64: =(X64-Schema_v5!$C13)/(Schema_v5!$C14-Schema_v5!$C13)
A65: Q13_D | B65: 13 | C65: 13 | D65: Core | E65: 1.05 | F65: ConflictRepair | G65: CommunicationHealth | I65: D | J65: D | K65: I want them to like me back, but I need to know it's safe first, so I keep it light while I wait on their actions. | L65: 7 | M65: 8 | N65: 4 | O65: 6 | P65: 4 | Q65: Performer | R65: 7 | U65: 0 | V65: masc:0.3;fem:0.5 | W65: 0.3 | X65: 0.5 | Y65: COMM_Indirect | Z65: REG_Distractor | AA65: LANG_Gifts | AE65: 0 | AF65: strategic flirter | AG65: cautious charmer | AH65: 0.2 | AI65: no | AJ65: no | AK65: yes | AL65: yes | AP65: v3_2026-03-19 | AQ65: =(L65-Schema_v5!$C2)/(Schema_v5!$C3-Schema_v5!$C2) | AR65: =(M65-Schema_v5!$C4)/(Schema_v5!$C5-Schema_v5!$C4) | AS65: =N65/Schema_v5!$C6 | AT65: =O65/Schema_v5!$C7 | AU65: =P65/Schema_v5!$C8 | AV65: =IF(Schema_v5!$C9=0,0,AH65/Schema_v5!$C9) | AW65: =IF(Schema_v5!$C10=0,0,AE65/Schema_v5!$C10) | AX65: =(W65-Schema_v5!$C11)/(Schema_v5!$C12-Schema_v5!$C11) | AY65: =(X65-Schema_v5!$C13)/(Schema_v5!$C14-Schema_v5!$C13)
A66: Q13_E | B66: 13 | C66: 13 | D66: Core | E66: 1.05 | F66: ConflictRepair | G66: CommunicationHealth | I66: E | J66: E | K66: If I like someone, it shows, but I don't rush just because the vibe is good. I wait to see if the energy stays real. | L66: 8 | M66: 9 | N66: 4 | O66: 6 | P66: 2 | Q66: Icebox | R66: 1 | U66: 0 | V66: masc:1.8;fem:-1.6 | W66: 1.8 | X66: -1.6 | Y66: COMM_Avoidant | Z66: REG_Suppressor | AA66: LANG_Time | AE66: 0 | AF66: guarded realist | AG66: patient tester | AH66: 0.6 | AI66: no | AJ66: no | AK66: yes | AL66: yes | AP66: v3_2026-03-19 | AQ66: =(L66-Schema_v5!$C2)/(Schema_v5!$C3-Schema_v5!$C2) | AR66: =(M66-Schema_v5!$C4)/(Schema_v5!$C5-Schema_v5!$C4) | AS66: =N66/Schema_v5!$C6 | AT66: =O66/Schema_v5!$C7 | AU66: =P66/Schema_v5!$C8 | AV66: =IF(Schema_v5!$C9=0,0,AH66/Schema_v5!$C9) | AW66: =IF(Schema_v5!$C10=0,0,AE66/Schema_v5!$C10) | AX66: =(W66-Schema_v5!$C11)/(Schema_v5!$C12-Schema_v5!$C11) | AY66: =(X66-Schema_v5!$C13)/(Schema_v5!$C14-Schema_v5!$C13)
A67: Q14_A | B67: 14 | C67: 14 | D67: Core | E67: 1.05 | F67: ConflictRepair | G67: CommunicationHealth | H67: They keep you in the loop, but never quite make you the priority. What shifts in you? | I67: A | J67: A | K67: I mirror it. They get the same version of me they're handing out. No extra effort for bare minimum. | L67: 7 | M67: 8 | N67: 4 | O67: 4 | P67: 0 | Q67: Icebox | R67: 1 | U67: 0 | V67: masc:1.8;fem:-1.6 | W67: 1.8 | X67: -1.6 | Y67: COMM_Avoidant | Z67: REG_Suppressor | AA67: LANG_Time | AE67: 0 | AF67: tactical disengagement | AG67: mirrored detachment | AH67: 0.6 | AI67: no | AJ67: no | AK67: yes | AL67: yes | AP67: v3_2026-03-19 | AQ67: =(L67-Schema_v5!$C2)/(Schema_v5!$C3-Schema_v5!$C2) | AR67: =(M67-Schema_v5!$C4)/(Schema_v5!$C5-Schema_v5!$C4) | AS67: =N67/Schema_v5!$C6 | AT67: =O67/Schema_v5!$C7 | AU67: =P67/Schema_v5!$C8 | AV67: =IF(Schema_v5!$C9=0,0,AH67/Schema_v5!$C9) | AW67: =IF(Schema_v5!$C10=0,0,AE67/Schema_v5!$C10) | AX67: =(W67-Schema_v5!$C11)/(Schema_v5!$C12-Schema_v5!$C11) | AY67: =(X67-Schema_v5!$C13)/(Schema_v5!$C14-Schema_v5!$C13)
A68: Q14_B | B68: 14 | C68: 14 | D68: Core | E68: 1.05 | F68: ConflictRepair | G68: CommunicationHealth | I68: B | J68: B | K68: I start overexplaining, why I care, what I mean, what I hope for. I try to make it easier to choose me. | L68: 5 | M68: 6 | N68: 4 | O68: 4 | P68: 4 | Q68: Fixer | R68: 5 | U68: 0 | V68: masc:-0.4;fem:2.0 | W68: -0.4 | X68: 2 | Y68: COMM_Emotional | Z68: REG_CoRegulator | AA68: LANG_Service | AB68: Vulnerability_Loop | AC68: Vulnerability_Loop | AE68: 5 | AF68: emotional sales pitch | AG68: approval seeker | AH68: 0 | AI68: yes | AJ68: no | AK68: yes | AL68: yes | AP68: v3_2026-03-19 | AQ68: =(L68-Schema_v5!$C2)/(Schema_v5!$C3-Schema_v5!$C2) | AR68: =(M68-Schema_v5!$C4)/(Schema_v5!$C5-Schema_v5!$C4) | AS68: =N68/Schema_v5!$C6 | AT68: =O68/Schema_v5!$C7 | AU68: =P68/Schema_v5!$C8 | AV68: =IF(Schema_v5!$C9=0,0,AH68/Schema_v5!$C9) | AW68: =IF(Schema_v5!$C10=0,0,AE68/Schema_v5!$C10) | AX68: =(W68-Schema_v5!$C11)/(Schema_v5!$C12-Schema_v5!$C11) | AY68: =(X68-Schema_v5!$C13)/(Schema_v5!$C14-Schema_v5!$C13)
A69: Q14_C | B69: 14 | C69: 14 | D69: Core | E69: 1.05 | F69: ConflictRepair | G69: CommunicationHealth | I69: C | J69: C | K69: I act like I don't care, but it eats at me. I show up less, talk less, but I'm still watching every move. | L69: 5 | M69: 6 | N69: 2 | O69: 4 | P69: 2 | Q69: Phantom Seeker | R69: 10 | U69: 0 | V69: masc:-0.2;fem:1.5 | W69: -0.2 | X69: 1.5 | Y69: COMM_Emotional | Z69: REG_SelfSoother | AA69: LANG_Touch | AB69: Vulnerability_Loop | AC69: Vulnerability_Loop | AE69: 5 | AF69: internal retreat | AG69: quiet stewer | AH69: 0 | AI69: yes | AJ69: no | AK69: yes | AL69: yes | AP69: v3_2026-03-19 | AQ69: =(L69-Schema_v5!$C2)/(Schema_v5!$C3-Schema_v5!$C2) | AR69: =(M69-Schema_v5!$C4)/(Schema_v5!$C5-Schema_v5!$C4) | AS69: =N69/Schema_v5!$C6 | AT69: =O69/Schema_v5!$C7 | AU69: =P69/Schema_v5!$C8 | AV69: =IF(Schema_v5!$C9=0,0,AH69/Schema_v5!$C9) | AW69: =IF(Schema_v5!$C10=0,0,AE69/Schema_v5!$C10) | AX69: =(W69-Schema_v5!$C11)/(Schema_v5!$C12-Schema_v5!$C11) | AY69: =(X69-Schema_v5!$C13)/(Schema_v5!$C14-Schema_v5!$C13)
A70: Q14_D | B70: 14 | C70: 14 | D70: Core | E70: 1.05 | F70: ConflictRepair | G70: CommunicationHealth | I70: D | J70: D | K70: I pretend I'm fine, but the shift gets loud. Suddenly I'm noticing who they respond to faster. Who gets their energy. | L70: 6 | M70: 7 | N70: 4 | O70: 4 | P70: 2 | Q70: Analyzer | R70: 2 | U70: 0 | V70: masc:1.4;fem:0.1 | W70: 1.4 | X70: 0.1 | Y70: COMM_Logical | Z70: REG_SelfSoother | AA70: LANG_Service | AB70: Vulnerability_Loop | AC70: Vulnerability_Loop | AE70: 5 | AF70: silent scorekeeper | AG70: attention tracker | AH70: 1.8 | AI70: yes | AJ70: no | AK70: yes | AL70: yes | AP70: v3_2026-03-19 | AQ70: =(L70-Schema_v5!$C2)/(Schema_v5!$C3-Schema_v5!$C2) | AR70: =(M70-Schema_v5!$C4)/(Schema_v5!$C5-Schema_v5!$C4) | AS70: =N70/Schema_v5!$C6 | AT70: =O70/Schema_v5!$C7 | AU70: =P70/Schema_v5!$C8 | AV70: =IF(Schema_v5!$C9=0,0,AH70/Schema_v5!$C9) | AW70: =IF(Schema_v5!$C10=0,0,AE70/Schema_v5!$C10) | AX70: =(W70-Schema_v5!$C11)/(Schema_v5!$C12-Schema_v5!$C11) | AY70: =(X70-Schema_v5!$C13)/(Schema_v5!$C14-Schema_v5!$C13)
A71: Q14_E | B71: 14 | C71: 14 | D71: Core | E71: 1.05 | F71: ConflictRepair | G71: CommunicationHealth | I71: E | J71: E | K71: I clock it, stash the receipt, and stop reaching out. I've made that mistake before, won't repeat it. | L71: 8 | M71: 9 | N71: 4 | O71: 6 | P71: 2 | Q71: Quiet Exit | R71: 4 | U71: 0 | V71: masc:1.4;fem:-1.3 | W71: 1.4 | X71: -1.3 | Y71: COMM_Avoidant | Z71: REG_Suppressor | AA71: LANG_Time | AE71: 0 | AF71: strategic shutdown | AG71: decisive withdrawer | AH71: 0.6 | AI71: no | AJ71: no | AK71: yes | AL71: yes | AP71: v3_2026-03-19 | AQ71: =(L71-Schema_v5!$C2)/(Schema_v5!$C3-Schema_v5!$C2) | AR71: =(M71-Schema_v5!$C4)/(Schema_v5!$C5-Schema_v5!$C4) | AS71: =N71/Schema_v5!$C6 | AT71: =O71/Schema_v5!$C7 | AU71: =P71/Schema_v5!$C8 | AV71: =IF(Schema_v5!$C9=0,0,AH71/Schema_v5!$C9) | AW71: =IF(Schema_v5!$C10=0,0,AE71/Schema_v5!$C10) | AX71: =(W71-Schema_v5!$C11)/(Schema_v5!$C12-Schema_v5!$C11) | AY71: =(X71-Schema_v5!$C13)/(Schema_v5!$C14-Schema_v5!$C13)
A72: Q15_A | B72: 15 | C72: 15 | D72: Core | E72: 1.05 | F72: ConflictRepair | G72: CommunicationHealth | H72: They respond fast. They remember what you say. No mixed signals. It's easy. How does your brain react to that kind of consistency? | I72: A | J72: A | K72: I wait for the twist. Nobody's that into me for no reason. I enjoy it, but I stay suspicious. | L72: 6 | M72: 7 | N72: 4 | O72: 6 | P72: 4 | Q72: Survivor | R72: 8 | U72: 0 | V72: masc:0.3;fem:1.3 | W72: 0.3 | X72: 1.3 | Y72: COMM_Emotional | Z72: REG_SelfSoother | AA72: LANG_Service | AB72: Vulnerability_Loop | AC72: Vulnerability_Loop | AE72: 5 | AF72: trauma-calibrated skepticism | AG72: guarded receiver | AH72: 0 | AI72: yes | AJ72: no | AK72: yes | AL72: yes | AP72: v3_2026-03-19 | AQ72: =(L72-Schema_v5!$C2)/(Schema_v5!$C3-Schema_v5!$C2) | AR72: =(M72-Schema_v5!$C4)/(Schema_v5!$C5-Schema_v5!$C4) | AS72: =N72/Schema_v5!$C6 | AT72: =O72/Schema_v5!$C7 | AU72: =P72/Schema_v5!$C8 | AV72: =IF(Schema_v5!$C9=0,0,AH72/Schema_v5!$C9) | AW72: =IF(Schema_v5!$C10=0,0,AE72/Schema_v5!$C10) | AX72: =(W72-Schema_v5!$C11)/(Schema_v5!$C12-Schema_v5!$C11) | AY72: =(X72-Schema_v5!$C13)/(Schema_v5!$C14-Schema_v5!$C13)
A73: Q15_B | B73: 15 | C73: 15 | D73: Core | E73: 1.05 | F73: ConflictRepair | G73: CommunicationHealth | I73: B | J73: B | K73: I get anxious. Like... if it's this easy now, what happens when I actually need something? | L73: 5 | M73: 6 | N73: 2 | O73: 4 | P73: 2 | Q73: Phantom Seeker | R73: 10 | U73: 0 | V73: masc:-0.2;fem:1.5 | W73: -0.2 | X73: 1.5 | Y73: COMM_Emotional | Z73: REG_SelfSoother | AA73: LANG_Touch | AB73: Vulnerability_Loop | AC73: Vulnerability_Loop | AE73: 5 | AF73: fragile trust reflex | AG73: uneasy believer | AH73: 0 | AI73: yes | AJ73: no | AK73: yes | AL73: yes | AP73: v3_2026-03-19 | AQ73: =(L73-Schema_v5!$C2)/(Schema_v5!$C3-Schema_v5!$C2) | AR73: =(M73-Schema_v5!$C4)/(Schema_v5!$C5-Schema_v5!$C4) | AS73: =N73/Schema_v5!$C6 | AT73: =O73/Schema_v5!$C7 | AU73: =P73/Schema_v5!$C8 | AV73: =IF(Schema_v5!$C9=0,0,AH73/Schema_v5!$C9) | AW73: =IF(Schema_v5!$C10=0,0,AE73/Schema_v5!$C10) | AX73: =(W73-Schema_v5!$C11)/(Schema_v5!$C12-Schema_v5!$C11) | AY73: =(X73-Schema_v5!$C13)/(Schema_v5!$C14-Schema_v5!$C13)
A74: Q15_C | B74: 15 | C74: 15 | D74: Core | E74: 1.05 | F74: ConflictRepair | G74: CommunicationHealth | I74: C | J74: C | K74: I like it, but I start checking what they want from me. Nobody invests like that unless they're expecting a return. | L74: 6 | M74: 7 | N74: 4 | O74: 6 | P74: 4 | Q74: Analyzer | R74: 2 | U74: 0 | V74: masc:1.4;fem:0.1 | W74: 1.4 | X74: 0.1 | Y74: COMM_Logical | Z74: REG_SelfSoother | AA74: LANG_Service | AB74: Vulnerability_Loop | AC74: Vulnerability_Loop | AE74: 5 | AF74: reciprocity scanner | AG74: cautious assessor | AH74: 0 | AI74: yes | AJ74: no | AK74: yes | AL74: yes | AP74: v3_2026-03-19 | AQ74: =(L74-Schema_v5!$C2)/(Schema_v5!$C3-Schema_v5!$C2) | AR74: =(M74-Schema_v5!$C4)/(Schema_v5!$C5-Schema_v5!$C4) | AS74: =N74/Schema_v5!$C6 | AT74: =O74/Schema_v5!$C7 | AU74: =P74/Schema_v5!$C8 | AV74: =IF(Schema_v5!$C9=0,0,AH74/Schema_v5!$C9) | AW74: =IF(Schema_v5!$C10=0,0,AE74/Schema_v5!$C10) | AX74: =(W74-Schema_v5!$C11)/(Schema_v5!$C12-Schema_v5!$C11) | AY74: =(X74-Schema_v5!$C13)/(Schema_v5!$C14-Schema_v5!$C13)
A75: Q15_D | B75: 15 | C75: 15 | D75: Core | E75: 1.05 | F75: ConflictRepair | G75: CommunicationHealth | I75: D | J75: D | K75: I try not to mess it up. I overthink everything I send back. It feels good, but fragile. | L75: 6 | M75: 7 | N75: 4 | O75: 4 | P75: 2 | Q75: Performer | R75: 7 | U75: 0 | V75: masc:0.3;fem:0.5 | W75: 0.3 | X75: 0.5 | Y75: COMM_Indirect | Z75: REG_Distractor | AA75: LANG_Gifts | AB75: Vulnerability_Loop | AC75: Vulnerability_Loop | AE75: 5 | AF75: image anxiety | AG75: careful performer | AH75: 0 | AI75: yes | AJ75: no | AK75: yes | AL75: yes | AP75: v3_2026-03-19 | AQ75: =(L75-Schema_v5!$C2)/(Schema_v5!$C3-Schema_v5!$C2) | AR75: =(M75-Schema_v5!$C4)/(Schema_v5!$C5-Schema_v5!$C4) | AS75: =N75/Schema_v5!$C6 | AT75: =O75/Schema_v5!$C7 | AU75: =P75/Schema_v5!$C8 | AV75: =IF(Schema_v5!$C9=0,0,AH75/Schema_v5!$C9) | AW75: =IF(Schema_v5!$C10=0,0,AE75/Schema_v5!$C10) | AX75: =(W75-Schema_v5!$C11)/(Schema_v5!$C12-Schema_v5!$C11) | AY75: =(X75-Schema_v5!$C13)/(Schema_v5!$C14-Schema_v5!$C13)
A76: Q15_E | B76: 15 | C76: 15 | D76: Core | E76: 1.05 | F76: ConflictRepair | G76: CommunicationHealth | I76: E | J76: E | K76: I match it, but I don't flood it. Feels rare, and I'm not about to fumble it with weird energy. | L76: 9 | M76: 9 | N76: 6 | O76: 6 | P76: 2 | Q76: Icebox | R76: 1 | U76: 0 | V76: masc:1.8;fem:-1.6 | W76: 1.8 | X76: -1.6 | Y76: COMM_Avoidant | Z76: REG_Suppressor | AA76: LANG_Time | AE76: 0 | AF76: cautious returner | AG76: balanced engager | AH76: 0 | AI76: no | AJ76: no | AK76: yes | AL76: yes | AP76: v3_2026-03-19 | AQ76: =(L76-Schema_v5!$C2)/(Schema_v5!$C3-Schema_v5!$C2) | AR76: =(M76-Schema_v5!$C4)/(Schema_v5!$C5-Schema_v5!$C4) | AS76: =N76/Schema_v5!$C6 | AT76: =O76/Schema_v5!$C7 | AU76: =P76/Schema_v5!$C8 | AV76: =IF(Schema_v5!$C9=0,0,AH76/Schema_v5!$C9) | AW76: =IF(Schema_v5!$C10=0,0,AE76/Schema_v5!$C10) | AX76: =(W76-Schema_v5!$C11)/(Schema_v5!$C12-Schema_v5!$C11) | AY76: =(X76-Schema_v5!$C13)/(Schema_v5!$C14-Schema_v5!$C13)
A77: Q16_A | B77: 16 | C77: 16 | D77: Core | E77: 1.05 | F77: ConflictRepair | G77: CommunicationHealth | H77: They go from warm to cold out of nowhere. What's your first move? | I77: A | J77: A | K77: If you're hot and cold, I'm room temperature and gone. I'm not here to decode moods. | L77: 9 | M77: 9 | N77: 10 | O77: 10 | P77: 10 | Q77: Regulated Grown-Up | R77: 9 | U77: 0 | V77: masc:1.1;fem:0.9 | W77: 1.1 | X77: 0.9 | Y77: COMM_Direct | Z77: REG_CoRegulator | AA77: LANG_Words | AE77: 0 | AF77: blunt detachment | AG77: immediate cutoff | AH77: 1.2 | AI77: no | AJ77: no | AK77: yes | AL77: yes | AP77: v3_2026-03-19 | AQ77: =(L77-Schema_v5!$C2)/(Schema_v5!$C3-Schema_v5!$C2) | AR77: =(M77-Schema_v5!$C4)/(Schema_v5!$C5-Schema_v5!$C4) | AS77: =N77/Schema_v5!$C6 | AT77: =O77/Schema_v5!$C7 | AU77: =P77/Schema_v5!$C8 | AV77: =IF(Schema_v5!$C9=0,0,AH77/Schema_v5!$C9) | AW77: =IF(Schema_v5!$C10=0,0,AE77/Schema_v5!$C10) | AX77: =(W77-Schema_v5!$C11)/(Schema_v5!$C12-Schema_v5!$C11) | AY77: =(X77-Schema_v5!$C13)/(Schema_v5!$C14-Schema_v5!$C13)
A78: Q16_B | B78: 16 | C78: 16 | D78: Core | E78: 1.05 | F78: ConflictRepair | G78: CommunicationHealth | I78: B | J78: B | K78: I recheck our last texts. Then I reread mine. Then I wonder if I should've said less, or more. I don't bring it up, but it definitely rewires how I respond. | L78: 5 | M78: 6 | N78: 4 | O78: 4 | P78: 2 | Q78: Analyzer | R78: 2 | U78: 0 | V78: masc:1.4;fem:0.1 | W78: 1.4 | X78: 0.1 | Y78: COMM_Logical | Z78: REG_SelfSoother | AA78: LANG_Service | AB78: Trust_Tension | AC78: Trust_Tension | AE78: 6 | AF78: emotional spiral | AG78: overanalyzer | AH78: 0 | AI78: yes | AJ78: no | AK78: yes | AL78: yes | AP78: v3_2026-03-19 | AQ78: =(L78-Schema_v5!$C2)/(Schema_v5!$C3-Schema_v5!$C2) | AR78: =(M78-Schema_v5!$C4)/(Schema_v5!$C5-Schema_v5!$C4) | AS78: =N78/Schema_v5!$C6 | AT78: =O78/Schema_v5!$C7 | AU78: =P78/Schema_v5!$C8 | AV78: =IF(Schema_v5!$C9=0,0,AH78/Schema_v5!$C9) | AW78: =IF(Schema_v5!$C10=0,0,AE78/Schema_v5!$C10) | AX78: =(W78-Schema_v5!$C11)/(Schema_v5!$C12-Schema_v5!$C11) | AY78: =(X78-Schema_v5!$C13)/(Schema_v5!$C14-Schema_v5!$C13)
A79: Q16_C | B79: 16 | C79: 16 | D79: Core | E79: 1.05 | F79: ConflictRepair | G79: CommunicationHealth | I79: C | J79: C | K79: I back off. They'll either notice or they won't. I'm not chasing people who don't know what they want. | L79: 4 | M79: 5 | N79: 0 | O79: 0 | P79: 0 | Q79: Icebox | R79: 1 | U79: 0 | V79: masc:1.8;fem:-1.6 | W79: 1.8 | X79: -1.6 | Y79: COMM_Avoidant | Z79: REG_Suppressor | AA79: LANG_Time | AB79: Vulnerability_Loop | AC79: Vulnerability_Loop | AE79: 5 | AF79: quiet burn | AG79: disengaged pullback | AH79: 0.6 | AI79: yes | AJ79: no | AK79: yes | AL79: yes | AP79: v3_2026-03-19 | AQ79: =(L79-Schema_v5!$C2)/(Schema_v5!$C3-Schema_v5!$C2) | AR79: =(M79-Schema_v5!$C4)/(Schema_v5!$C5-Schema_v5!$C4) | AS79: =N79/Schema_v5!$C6 | AT79: =O79/Schema_v5!$C7 | AU79: =P79/Schema_v5!$C8 | AV79: =IF(Schema_v5!$C9=0,0,AH79/Schema_v5!$C9) | AW79: =IF(Schema_v5!$C10=0,0,AE79/Schema_v5!$C10) | AX79: =(W79-Schema_v5!$C11)/(Schema_v5!$C12-Schema_v5!$C11) | AY79: =(X79-Schema_v5!$C13)/(Schema_v5!$C14-Schema_v5!$C13)
A80: Q16_D | B80: 16 | C80: 16 | D80: Core | E80: 1.05 | F80: ConflictRepair | G80: CommunicationHealth | I80: D | J80: D | K80: I stop bringing things up. If they don't want me, I'm not going to beg to be understood. I've played that game before. | L80: 6 | M80: 7 | N80: 4 | O80: 4 | P80: 4 | Q80: Fixer | R80: 5 | U80: 0 | V80: masc:-0.4;fem:2.0 | W80: -0.4 | X80: 2 | Y80: COMM_Emotional | Z80: REG_CoRegulator | AA80: LANG_Service | AB80: Affection_Mismatch , Independence_Collision | AC80: Affection_Mismatch | AD80: Independence_Collision | AE80: 9 | AF80: resigned caregiver | AG80: silent surrender | AH80: 1.2 | AI80: yes | AJ80: no | AK80: yes | AL80: yes | AP80: v3_2026-03-19 | AQ80: =(L80-Schema_v5!$C2)/(Schema_v5!$C3-Schema_v5!$C2) | AR80: =(M80-Schema_v5!$C4)/(Schema_v5!$C5-Schema_v5!$C4) | AS80: =N80/Schema_v5!$C6 | AT80: =O80/Schema_v5!$C7 | AU80: =P80/Schema_v5!$C8 | AV80: =IF(Schema_v5!$C9=0,0,AH80/Schema_v5!$C9) | AW80: =IF(Schema_v5!$C10=0,0,AE80/Schema_v5!$C10) | AX80: =(W80-Schema_v5!$C11)/(Schema_v5!$C12-Schema_v5!$C11) | AY80: =(X80-Schema_v5!$C13)/(Schema_v5!$C14-Schema_v5!$C13)
A81: Q16_E | B81: 16 | C81: 16 | D81: Core | E81: 1.05 | F81: ConflictRepair | G81: CommunicationHealth | I81: E | J81: E | K81: I tell myself it's probably just stress or a bad week. I don't want to give up too early, but it's hard not to notice when it shifts. | L81: 7 | M81: 8 | N81: 6 | O81: 6 | P81: 4 | Q81: Romantic Idealist | R81: 6 | U81: 0 | V81: masc:-0.4;fem:1.5 | W81: -0.4 | X81: 1.5 | Y81: COMM_Emotional | Z81: REG_Distractor | AA81: LANG_Gifts | AE81: 0 | AF81: tired hope | AG81: cautious optimist | AH81: 0 | AI81: no | AJ81: no | AK81: yes | AL81: yes | AP81: v3_2026-03-19 | AQ81: =(L81-Schema_v5!$C2)/(Schema_v5!$C3-Schema_v5!$C2) | AR81: =(M81-Schema_v5!$C4)/(Schema_v5!$C5-Schema_v5!$C4) | AS81: =N81/Schema_v5!$C6 | AT81: =O81/Schema_v5!$C7 | AU81: =P81/Schema_v5!$C8 | AV81: =IF(Schema_v5!$C9=0,0,AH81/Schema_v5!$C9) | AW81: =IF(Schema_v5!$C10=0,0,AE81/Schema_v5!$C10) | AX81: =(W81-Schema_v5!$C11)/(Schema_v5!$C12-Schema_v5!$C11) | AY81: =(X81-Schema_v5!$C13)/(Schema_v5!$C14-Schema_v5!$C13)
A82: Q17_A | B82: 17 | C82: 17 | D82: Core | E82: 1.1 | F82: EmotionalRegulation | G82: AttachmentSafety | H82: You're deep in conversation and they suddenly shut down or go quiet. What do you do next? | I82: A | J82: A | K82: I give them space. If they want to talk, they will. If not, I take the hint. | L82: 8 | M82: 8 | N82: 4 | O82: 4 | P82: 0 | Q82: Icebox | R82: 1 | U82: 0 | V82: masc:1.8;fem:-1.6 | W82: 1.8 | X82: -1.6 | Y82: COMM_Avoidant | Z82: REG_Suppressor | AA82: LANG_Time | AE82: 0 | AF82: detached cool | AG82: patient withdrawer | AH82: 1.2 | AI82: no | AJ82: no | AK82: yes | AL82: yes | AP82: v3_2026-03-19 | AQ82: =(L82-Schema_v5!$C2)/(Schema_v5!$C3-Schema_v5!$C2) | AR82: =(M82-Schema_v5!$C4)/(Schema_v5!$C5-Schema_v5!$C4) | AS82: =N82/Schema_v5!$C6 | AT82: =O82/Schema_v5!$C7 | AU82: =P82/Schema_v5!$C8 | AV82: =IF(Schema_v5!$C9=0,0,AH82/Schema_v5!$C9) | AW82: =IF(Schema_v5!$C10=0,0,AE82/Schema_v5!$C10) | AX82: =(W82-Schema_v5!$C11)/(Schema_v5!$C12-Schema_v5!$C11) | AY82: =(X82-Schema_v5!$C13)/(Schema_v5!$C14-Schema_v5!$C13)
A83: Q17_B | B83: 17 | C83: 17 | D83: Core | E83: 1.1 | F83: EmotionalRegulation | G83: AttachmentSafety | I83: B | J83: B | K83: I immediately think I said something wrong. I start scanning every word trying to figure out what triggered it. | L83: 4 | M83: 5 | N83: 2 | O83: 2 | P83: 2 | Q83: Analyzer | R83: 2 | U83: 0 | V83: masc:1.4;fem:0.1 | W83: 1.4 | X83: 0.1 | Y83: COMM_Logical | Z83: REG_SelfSoother | AA83: LANG_Service | AB83: Vulnerability_Loop | AC83: Vulnerability_Loop | AE83: 5 | AF83: inner spiral | AG83: self-blamer | AH83: 0 | AI83: yes | AJ83: no | AK83: yes | AL83: yes | AP83: v3_2026-03-19 | AQ83: =(L83-Schema_v5!$C2)/(Schema_v5!$C3-Schema_v5!$C2) | AR83: =(M83-Schema_v5!$C4)/(Schema_v5!$C5-Schema_v5!$C4) | AS83: =N83/Schema_v5!$C6 | AT83: =O83/Schema_v5!$C7 | AU83: =P83/Schema_v5!$C8 | AV83: =IF(Schema_v5!$C9=0,0,AH83/Schema_v5!$C9) | AW83: =IF(Schema_v5!$C10=0,0,AE83/Schema_v5!$C10) | AX83: =(W83-Schema_v5!$C11)/(Schema_v5!$C12-Schema_v5!$C11) | AY83: =(X83-Schema_v5!$C13)/(Schema_v5!$C14-Schema_v5!$C13)
A84: Q17_C | B84: 17 | C84: 17 | D84: Core | E84: 1.1 | F84: EmotionalRegulation | G84: AttachmentSafety | I84: C | J84: C | K84: I'll ask once. If it's brushed off or ignored, I shift. I'm not the type to sit in someone else's silence for long. | L84: 9 | M84: 9 | N84: 10 | O84: 10 | P84: 10 | Q84: Regulated Grown-Up | R84: 9 | U84: 0 | V84: masc:1.1;fem:0.9 | W84: 1.1 | X84: 0.9 | Y84: COMM_Direct | Z84: REG_CoRegulator | AA84: LANG_Words | AE84: 0 | AF84: direct with boundaries | AG84: firm line-setter | AH84: 0 | AI84: no | AJ84: no | AK84: yes | AL84: yes | AP84: v3_2026-03-19 | AQ84: =(L84-Schema_v5!$C2)/(Schema_v5!$C3-Schema_v5!$C2) | AR84: =(M84-Schema_v5!$C4)/(Schema_v5!$C5-Schema_v5!$C4) | AS84: =N84/Schema_v5!$C6 | AT84: =O84/Schema_v5!$C7 | AU84: =P84/Schema_v5!$C8 | AV84: =IF(Schema_v5!$C9=0,0,AH84/Schema_v5!$C9) | AW84: =IF(Schema_v5!$C10=0,0,AE84/Schema_v5!$C10) | AX84: =(W84-Schema_v5!$C11)/(Schema_v5!$C12-Schema_v5!$C11) | AY84: =(X84-Schema_v5!$C13)/(Schema_v5!$C14-Schema_v5!$C13)
A85: Q17_D | B85: 17 | C85: 17 | D85: Core | E85: 1.1 | F85: EmotionalRegulation | G85: AttachmentSafety | I85: D | J85: D | K85: I try to keep the mood up, shift the subject, make it feel less tense, even if I'm freaking out a little inside. | L85: 6 | M85: 7 | N85: 4 | O85: 4 | P85: 2 | Q85: Performer | R85: 7 | U85: 0 | V85: masc:0.3;fem:0.5 | W85: 0.3 | X85: 0.5 | Y85: COMM_Indirect | Z85: REG_Distractor | AA85: LANG_Gifts | AB85: Vulnerability_Loop | AC85: Vulnerability_Loop | AE85: 5 | AF85: smooth cover-up | AG85: tension diffuser | AH85: 0 | AI85: yes | AJ85: no | AK85: yes | AL85: yes | AP85: v3_2026-03-19 | AQ85: =(L85-Schema_v5!$C2)/(Schema_v5!$C3-Schema_v5!$C2) | AR85: =(M85-Schema_v5!$C4)/(Schema_v5!$C5-Schema_v5!$C4) | AS85: =N85/Schema_v5!$C6 | AT85: =O85/Schema_v5!$C7 | AU85: =P85/Schema_v5!$C8 | AV85: =IF(Schema_v5!$C9=0,0,AH85/Schema_v5!$C9) | AW85: =IF(Schema_v5!$C10=0,0,AE85/Schema_v5!$C10) | AX85: =(W85-Schema_v5!$C11)/(Schema_v5!$C12-Schema_v5!$C11) | AY85: =(X85-Schema_v5!$C13)/(Schema_v5!$C14-Schema_v5!$C13)
A86: Q17_E | B86: 17 | C86: 17 | D86: Core | E86: 1.1 | F86: EmotionalRegulation | G86: AttachmentSafety | I86: E | J86: E | K86: I feel it, but I don't say anything. I stay present, hoping they'll come back to me on their own. | L86: 6 | M86: 6 | N86: 4 | O86: 4 | P86: 4 | Q86: Translator | R86: 3 | U86: 0 | V86: masc:-0.1;fem:1.6 | W86: -0.1 | X86: 1.6 | Y86: COMM_Indirect | Z86: REG_CoRegulator | AA86: LANG_Words | AB86: Vulnerability_Loop | AC86: Vulnerability_Loop | AE86: 5 | AF86: gentle waiter | AG86: silent holder | AH86: 0.6 | AI86: yes | AJ86: no | AK86: yes | AL86: yes | AP86: v3_2026-03-19 | AQ86: =(L86-Schema_v5!$C2)/(Schema_v5!$C3-Schema_v5!$C2) | AR86: =(M86-Schema_v5!$C4)/(Schema_v5!$C5-Schema_v5!$C4) | AS86: =N86/Schema_v5!$C6 | AT86: =O86/Schema_v5!$C7 | AU86: =P86/Schema_v5!$C8 | AV86: =IF(Schema_v5!$C9=0,0,AH86/Schema_v5!$C9) | AW86: =IF(Schema_v5!$C10=0,0,AE86/Schema_v5!$C10) | AX86: =(W86-Schema_v5!$C11)/(Schema_v5!$C12-Schema_v5!$C11) | AY86: =(X86-Schema_v5!$C13)/(Schema_v5!$C14-Schema_v5!$C13)
A87: Q18_A | B87: 18 | C87: 18 | D87: Core | E87: 1.1 | F87: EmotionalRegulation | G87: AttachmentSafety | H87: They open up to you-then start pulling back. No explanation, just distance. What do you do with that shift? | I87: A | J87: A | K87: I match the energy. You pull back? I pull back faster. I've learned not to chase clarity from people who hide when it gets real. | L87: 7 | M87: 8 | N87: 4 | O87: 4 | P87: 0 | Q87: Icebox | R87: 1 | U87: 0 | V87: masc:1.8;fem:-1.6 | W87: 1.8 | X87: -1.6 | Y87: COMM_Avoidant | Z87: REG_Suppressor | AA87: LANG_Time | AE87: 0 | AF87: fast mirror exit | AG87: decisive mirror | AH87: 0.8 | AI87: no | AJ87: no | AK87: yes | AL87: yes | AP87: v3_2026-03-19 | AQ87: =(L87-Schema_v5!$C2)/(Schema_v5!$C3-Schema_v5!$C2) | AR87: =(M87-Schema_v5!$C4)/(Schema_v5!$C5-Schema_v5!$C4) | AS87: =N87/Schema_v5!$C6 | AT87: =O87/Schema_v5!$C7 | AU87: =P87/Schema_v5!$C8 | AV87: =IF(Schema_v5!$C9=0,0,AH87/Schema_v5!$C9) | AW87: =IF(Schema_v5!$C10=0,0,AE87/Schema_v5!$C10) | AX87: =(W87-Schema_v5!$C11)/(Schema_v5!$C12-Schema_v5!$C11) | AY87: =(X87-Schema_v5!$C13)/(Schema_v5!$C14-Schema_v5!$C13)
A88: Q18_B | B88: 18 | C88: 18 | D88: Core | E88: 1.1 | F88: EmotionalRegulation | G88: AttachmentSafety | I88: B | J88: B | K88: I start thinking I pushed too far. I replay the moment, wondering what I said that made them go quiet. It usually ends with me blaming myself. | L88: 4 | M88: 5 | N88: 2 | O88: 2 | P88: 2 | Q88: Analyzer | R88: 2 | U88: 0 | V88: masc:1.4;fem:0.1 | W88: 1.4 | X88: 0.1 | Y88: COMM_Logical | Z88: REG_SelfSoother | AA88: LANG_Service | AB88: Vulnerability_Loop | AC88: Vulnerability_Loop | AE88: 5 | AF88: shame loop | AG88: self-blamer | AH88: 0 | AI88: yes | AJ88: no | AK88: yes | AL88: yes | AP88: v3_2026-03-19 | AQ88: =(L88-Schema_v5!$C2)/(Schema_v5!$C3-Schema_v5!$C2) | AR88: =(M88-Schema_v5!$C4)/(Schema_v5!$C5-Schema_v5!$C4) | AS88: =N88/Schema_v5!$C6 | AT88: =O88/Schema_v5!$C7 | AU88: =P88/Schema_v5!$C8 | AV88: =IF(Schema_v5!$C9=0,0,AH88/Schema_v5!$C9) | AW88: =IF(Schema_v5!$C10=0,0,AE88/Schema_v5!$C10) | AX88: =(W88-Schema_v5!$C11)/(Schema_v5!$C12-Schema_v5!$C11) | AY88: =(X88-Schema_v5!$C13)/(Schema_v5!$C14-Schema_v5!$C13)
A89: Q18_C | B89: 18 | C89: 18 | D89: Core | E89: 1.1 | F89: EmotionalRegulation | G89: AttachmentSafety | I89: C | J89: C | K89: I wait. Sometimes people get scared when they feel seen, I don't want to add pressure, but I definitely notice the change. | L89: 7 | M89: 8 | N89: 6 | O89: 6 | P89: 4 | Q89: Romantic Idealist | R89: 6 | U89: 0 | V89: masc:-0.4;fem:1.5 | W89: -0.4 | X89: 1.5 | Y89: COMM_Emotional | Z89: REG_Distractor | AA89: LANG_Gifts | AE89: 0 | AF89: patient rationalizer | AG89: hopeful waiter | AH89: 0 | AI89: no | AJ89: no | AK89: yes | AL89: yes | AP89: v3_2026-03-19 | AQ89: =(L89-Schema_v5!$C2)/(Schema_v5!$C3-Schema_v5!$C2) | AR89: =(M89-Schema_v5!$C4)/(Schema_v5!$C5-Schema_v5!$C4) | AS89: =N89/Schema_v5!$C6 | AT89: =O89/Schema_v5!$C7 | AU89: =P89/Schema_v5!$C8 | AV89: =IF(Schema_v5!$C9=0,0,AH89/Schema_v5!$C9) | AW89: =IF(Schema_v5!$C10=0,0,AE89/Schema_v5!$C10) | AX89: =(W89-Schema_v5!$C11)/(Schema_v5!$C12-Schema_v5!$C11) | AY89: =(X89-Schema_v5!$C13)/(Schema_v5!$C14-Schema_v5!$C13)
A90: Q18_D | B90: 18 | C90: 18 | D90: Core | E90: 1.1 | F90: EmotionalRegulation | G90: AttachmentSafety | I90: D | J90: D | K90: I go into fix-it mode. Check in more. Try to feel lighter, easier, more fun, anything to bring us back to how it felt before. | L90: 5 | M90: 6 | N90: 4 | O90: 4 | P90: 4 | Q90: Fixer | R90: 5 | U90: 0 | V90: masc:-0.4;fem:2.0 | W90: -0.4 | X90: 2 | Y90: COMM_Emotional | Z90: REG_CoRegulator | AA90: LANG_Service | AB90: Vulnerability_Loop | AC90: Vulnerability_Loop | AE90: 5 | AF90: emotional reset attempt | AG90: overcompensator | AH90: 0 | AI90: yes | AJ90: no | AK90: yes | AL90: yes | AP90: v3_2026-03-19 | AQ90: =(L90-Schema_v5!$C2)/(Schema_v5!$C3-Schema_v5!$C2) | AR90: =(M90-Schema_v5!$C4)/(Schema_v5!$C5-Schema_v5!$C4) | AS90: =N90/Schema_v5!$C6 | AT90: =O90/Schema_v5!$C7 | AU90: =P90/Schema_v5!$C8 | AV90: =IF(Schema_v5!$C9=0,0,AH90/Schema_v5!$C9) | AW90: =IF(Schema_v5!$C10=0,0,AE90/Schema_v5!$C10) | AX90: =(W90-Schema_v5!$C11)/(Schema_v5!$C12-Schema_v5!$C11) | AY90: =(X90-Schema_v5!$C13)/(Schema_v5!$C14-Schema_v5!$C13)
A91: Q18_E | B91: 18 | C91: 18 | D91: Core | E91: 1.1 | F91: EmotionalRegulation | G91: AttachmentSafety | I91: E | J91: E | K91: I make myself busy. I don't ask, I don't chase. But I clock it. I'll still be polite, but they won't get the same version of me again. | L91: 7 | M91: 8 | N91: 4 | O91: 4 | P91: 0 | Q91: Quiet Exit | R91: 4 | U91: 0 | V91: masc:1.4;fem:-1.3 | W91: 1.4 | X91: -1.3 | Y91: COMM_Avoidant | Z91: REG_Suppressor | AA91: LANG_Time | AE91: 0 | AF91: soft lockdown | AG91: guarded exit | AH91: 0 | AI91: no | AJ91: no | AK91: yes | AL91: yes | AP91: v3_2026-03-19 | AQ91: =(L91-Schema_v5!$C2)/(Schema_v5!$C3-Schema_v5!$C2) | AR91: =(M91-Schema_v5!$C4)/(Schema_v5!$C5-Schema_v5!$C4) | AS91: =N91/Schema_v5!$C6 | AT91: =O91/Schema_v5!$C7 | AU91: =P91/Schema_v5!$C8 | AV91: =IF(Schema_v5!$C9=0,0,AH91/Schema_v5!$C9) | AW91: =IF(Schema_v5!$C10=0,0,AE91/Schema_v5!$C10) | AX91: =(W91-Schema_v5!$C11)/(Schema_v5!$C12-Schema_v5!$C11) | AY91: =(X91-Schema_v5!$C13)/(Schema_v5!$C14-Schema_v5!$C13)
A92: Q19_A | B92: 19 | C92: 19 | D92: Core | E92: 1.1 | F92: EmotionalRegulation | G92: AttachmentSafety | H92: You're starting to really like them. But they haven't asked much about you. How do you handle that imbalance? | I92: A | J92: A | K92: I clock it. If they're not curious, they're not serious. I don't make speeches, I just start pulling back and let them figure it out. | L92: 8 | M92: 9 | N92: 4 | O92: 6 | P92: 2 | Q92: Icebox | R92: 1 | U92: 0 | V92: masc:1.8;fem:-1.6 | W92: 1.8 | X92: -1.6 | Y92: COMM_Avoidant | Z92: REG_Suppressor | AA92: LANG_Time | AE92: 0 | AF92: quiet disengagement | AG92: measured pullback | AH92: 0 | AI92: no | AJ92: no | AK92: yes | AL92: yes | AP92: v3_2026-03-19 | AQ92: =(L92-Schema_v5!$C2)/(Schema_v5!$C3-Schema_v5!$C2) | AR92: =(M92-Schema_v5!$C4)/(Schema_v5!$C5-Schema_v5!$C4) | AS92: =N92/Schema_v5!$C6 | AT92: =O92/Schema_v5!$C7 | AU92: =P92/Schema_v5!$C8 | AV92: =IF(Schema_v5!$C9=0,0,AH92/Schema_v5!$C9) | AW92: =IF(Schema_v5!$C10=0,0,AE92/Schema_v5!$C10) | AX92: =(W92-Schema_v5!$C11)/(Schema_v5!$C12-Schema_v5!$C11) | AY92: =(X92-Schema_v5!$C13)/(Schema_v5!$C14-Schema_v5!$C13)
A93: Q19_B | B93: 19 | C93: 19 | D93: Core | E93: 1.1 | F93: EmotionalRegulation | G93: AttachmentSafety | I93: B | J93: B | K93: I start telling little stories about myself anyway, hoping they'll finally ask more. When they don't, it stings more than I let on. | L93: 5 | M93: 6 | N93: 2 | O93: 2 | P93: 0 | Q93: Phantom Seeker | R93: 10 | U93: 0 | V93: masc:-0.2;fem:1.5 | W93: -0.2 | X93: 1.5 | Y93: COMM_Emotional | Z93: REG_SelfSoother | AA93: LANG_Touch | AB93: Scorekeeping_Echo | AC93: Scorekeeping_Echo | AE93: 8 | AF93: indirect yearning | AG93: subtle tester | AH93: 0.2 | AI93: yes | AJ93: no | AK93: yes | AL93: yes | AP93: v3_2026-03-19 | AQ93: =(L93-Schema_v5!$C2)/(Schema_v5!$C3-Schema_v5!$C2) | AR93: =(M93-Schema_v5!$C4)/(Schema_v5!$C5-Schema_v5!$C4) | AS93: =N93/Schema_v5!$C6 | AT93: =O93/Schema_v5!$C7 | AU93: =P93/Schema_v5!$C8 | AV93: =IF(Schema_v5!$C9=0,0,AH93/Schema_v5!$C9) | AW93: =IF(Schema_v5!$C10=0,0,AE93/Schema_v5!$C10) | AX93: =(W93-Schema_v5!$C11)/(Schema_v5!$C12-Schema_v5!$C11) | AY93: =(X93-Schema_v5!$C13)/(Schema_v5!$C14-Schema_v5!$C13)
A94: Q19_C | B94: 19 | C94: 19 | D94: Core | E94: 1.1 | F94: EmotionalRegulation | G94: AttachmentSafety | I94: C | J94: C | K94: I keep the conversation going but note the pattern. If it keeps feeling one-sided, I stop investing. Curiosity should go both ways. | L94: 7 | M94: 8 | N94: 6 | O94: 8 | P94: 6 | Q94: Analyzer | R94: 2 | U94: 0 | V94: masc:1.4;fem:0.1 | W94: 1.4 | X94: 0.1 | Y94: COMM_Logical | Z94: REG_SelfSoother | AA94: LANG_Service | AE94: 0 | AF94: measured monitoring | AG94: balanced assessor | AH94: 0 | AI94: no | AJ94: no | AK94: yes | AL94: yes | AP94: v3_2026-03-19 | AQ94: =(L94-Schema_v5!$C2)/(Schema_v5!$C3-Schema_v5!$C2) | AR94: =(M94-Schema_v5!$C4)/(Schema_v5!$C5-Schema_v5!$C4) | AS94: =N94/Schema_v5!$C6 | AT94: =O94/Schema_v5!$C7 | AU94: =P94/Schema_v5!$C8 | AV94: =IF(Schema_v5!$C9=0,0,AH94/Schema_v5!$C9) | AW94: =IF(Schema_v5!$C10=0,0,AE94/Schema_v5!$C10) | AX94: =(W94-Schema_v5!$C11)/(Schema_v5!$C12-Schema_v5!$C11) | AY94: =(X94-Schema_v5!$C13)/(Schema_v5!$C14-Schema_v5!$C13)
